Workbook

Sheet 基本信息统计
A1: 基本信息统计
A2: 176份原始答卷；主分析122份。各题有效分母另列。
A4: 样本流程 | B4: 人数
A5: 原始回收 | B5: =COUNTA(#REF!) -> 1 | I5: 选项 | J5: 人数
A6: 筛选结束 | B6: =COUNTIFS(数据清洗!$D$2:$D$177,0) -> 1 | I6: 18–22岁 | J6: =基本信息统计!C16 -> 35
A7: 筛选后记录 | B7: =COUNTIFS(数据清洗!$D$2:$D$177,1) -> 175 | I7: 23–29岁 | J7: =基本信息统计!C15 -> 55
A8: 重复文本群暂不纳入 | B8: =COUNTIFS(数据清洗!$D$2:$D$177,1,数据清洗!$Q$2:$Q$177,1) -> 53 | I8: 30–39岁 | J8: =基本信息统计!C14 -> 26
A9: 主分析样本 | B9: =COUNTIFS(数据清洗!$E$2:$E$177,1) -> 122 | I9: 40岁及以上 | J9: =基本信息统计!C18 -> 3
I10: 不愿透露 | J10: =基本信息统计!C17 -> 3
A11: 提交时间：2026-09-25 07:16:40至14:19:23（原导出时区未注明）。主样本用时128–2796秒，中位312.5秒。
A13: 题目/范围 | B13: 选项 | C13: 人数 n | D13: 有效分母 N | E13: 比例 n/N | F13: 口径
A14: 年龄 | B14: 30–39岁 | C14: =COUNTIFS(数据清洗!$E$2:$E$177,1,数据清洗!$G$2:$G$177,"30–39岁") -> 26 | D14: =COUNTIFS(数据清洗!$E$2:$E$177,1) -> 122 | E14: =IF(D14=0,"",C14/D14) -> 0.21311475 | F14: 主分析样本
A15: 年龄 | B15: 23–29岁 | C15: =COUNTIFS(数据清洗!$E$2:$E$177,1,数据清洗!$G$2:$G$177,"23–29岁") -> 55 | D15: =COUNTIFS(数据清洗!$E$2:$E$177,1) -> 122 | E15: =IF(D15=0,"",C15/D15) -> 0.45081967 | F15: 主分析样本
A16: 年龄 | B16: 18–22岁 | C16: =COUNTIFS(数据清洗!$E$2:$E$177,1,数据清洗!$G$2:$G$177,"18–22岁") -> 35 | D16: =COUNTIFS(数据清洗!$E$2:$E$177,1) -> 122 | E16: =IF(D16=0,"",C16/D16) -> 0.28688525 | F16: 主分析样本
A17: 年龄 | B17: 不愿透露 | C17: =COUNTIFS(数据清洗!$E$2:$E$177,1,数据清洗!$G$2:$G$177,"不愿透露") -> 3 | D17: =COUNTIFS(数据清洗!$E$2:$E$177,1) -> 122 | E17: =IF(D17=0,"",C17/D17) -> 0.024590164 | F17: 主分析样本
A18: 年龄 | B18: 40岁及以上 | C18: =COUNTIFS(数据清洗!$E$2:$E$177,1,数据清洗!$G$2:$G$177,"40岁及以上") -> 3 | D18: =COUNTIFS(数据清洗!$E$2:$E$177,1) -> 122 | E18: =IF(D18=0,"",C18/D18) -> 0.024590164 | F18: 主分析样本
A19: 性别 | B19: 女 | C19: =COUNTIFS(数据清洗!$E$2:$E$177,1,数据清洗!$H$2:$H$177,"女") -> 40 | D19: =COUNTIFS(数据清洗!$E$2:$E$177,1) -> 122 | E19: =IF(D19=0,"",C19/D19) -> 0.32786885 | F19: 主分析样本
A20: 性别 | B20: 男 | C20: =COUNTIFS(数据清洗!$E$2:$E$177,1,数据清洗!$H$2:$H$177,"男") -> 75 | D20: =COUNTIFS(数据清洗!$E$2:$E$177,1) -> 122 | E20: =IF(D20=0,"",C20/D20) -> 0.6147541 | F20: 主分析样本
A21: 性别 | B21: 其他 | C21: =COUNTIFS(数据清洗!$E$2:$E$177,1,数据清洗!$H$2:$H$177,"其他") -> 4 | D21: =COUNTIFS(数据清洗!$E$2:$E$177,1) -> 122 | E21: =IF(D21=0,"",C21/D21) -> 0.032786885 | F21: 主分析样本
A22: 性别 | B22: 不愿透露 | C22: =COUNTIFS(数据清洗!$E$2:$E$177,1,数据清洗!$H$2:$H$177,"不愿透露") -> 3 | D22: =COUNTIFS(数据清洗!$E$2:$E$177,1) -> 122 | E22: =IF(D22=0,"",C22/D22) -> 0.024590164 | F22: 主分析样本
A23: 学历 | B23: 硕士研究生及以上 | C23: =COUNTIFS(数据清洗!$E$2:$E$177,1,数据清洗!$I$2:$I$177,"硕士研究生及以上") -> 4 | D23: =COUNTIFS(数据清洗!$E$2:$E$177,1) -> 122 | E23: =IF(D23=0,"",C23/D23) -> 0.032786885 | F23: 主分析样本
A24: 学历 | B24: 本科 | C24: =COUNTIFS(数据清洗!$E$2:$E$177,1,数据清洗!$I$2:$I$177,"本科") -> 78 | D24: =COUNTIFS(数据清洗!$E$2:$E$177,1) -> 122 | E24: =IF(D24=0,"",C24/D24) -> 0.63934426 | F24: 主分析样本
A25: 学历 | B25: 大专 | C25: =COUNTIFS(数据清洗!$E$2:$E$177,1,数据清洗!$I$2:$I$177,"大专") -> 25 | D25: =COUNTIFS(数据清洗!$E$2:$E$177,1) -> 122 | E25: =IF(D25=0,"",C25/D25) -> 0.20491803 | F25: 主分析样本
A26: 学历 | B26: 不愿透露 | C26: =COUNTIFS(数据清洗!$E$2:$E$177,1,数据清洗!$I$2:$I$177,"不愿透露") -> 2 | D26: =COUNTIFS(数据清洗!$E$2:$E$177,1) -> 122 | E26: =IF(D26=0,"",C26/D26) -> 0.016393443 | F26: 主分析样本
A27: 学历 | B27: 高中／中专／职高／技校 | C27: =COUNTIFS(数据清洗!$E$2:$E$177,1,数据清洗!$I$2:$I$177,"高中／中专／职高／技校") -> 12 | D27: =COUNTIFS(数据清洗!$E$2:$E$177,1) -> 122 | E27: =IF(D27=0,"",C27/D27) -> 0.098360656 | F27: 主分析样本
A28: 学历 | B28: 初中及以下 | C28: =COUNTIFS(数据清洗!$E$2:$E$177,1,数据清洗!$I$2:$I$177,"初中及以下") -> 1 | D28: =COUNTIFS(数据清洗!$E$2:$E$177,1) -> 122 | E28: =IF(D28=0,"",C28/D28) -> 0.0081967213 | F28: 主分析样本
A29: B站频率 | B29: 从未使用过B站 | C29: =COUNTIFS(数据清洗!$E$2:$E$177,1,数据清洗!$J$2:$J$177,"从未使用过B站") -> 5 | D29: =COUNTIFS(数据清洗!$E$2:$E$177,1) -> 122 | E29: =IF(D29=0,"",C29/D29) -> 0.040983607 | F29: 主分析样本
A30: B站频率 | B30: 每周1–2天 | C30: =COUNTIFS(数据清洗!$E$2:$E$177,1,数据清洗!$J$2:$J$177,"每周1–2天") -> 29 | D30: =COUNTIFS(数据清洗!$E$2:$E$177,1) -> 122 | E30: =IF(D30=0,"",C30/D30) -> 0.23770492 | F30: 主分析样本
A31: B站频率 | B31: 几乎每天 | C31: =COUNTIFS(数据清洗!$E$2:$E$177,1,数据清洗!$J$2:$J$177,"几乎每天") -> 39 | D31: =COUNTIFS(数据清洗!$E$2:$E$177,1) -> 122 | E31: =IF(D31=0,"",C31/D31) -> 0.31967213 | F31: 主分析样本
A32: B站频率 | B32: 少于每周1天 | C32: =COUNTIFS(数据清洗!$E$2:$E$177,1,数据清洗!$J$2:$J$177,"少于每周1天") -> 13 | D32: =COUNTIFS(数据清洗!$E$2:$E$177,1) -> 122 | E32: =IF(D32=0,"",C32/D32) -> 0.10655738 | F32: 主分析样本
A33: B站频率 | B33: 每周3–6天 | C33: =COUNTIFS(数据清洗!$E$2:$E$177,1,数据清洗!$J$2:$J$177,"每周3–6天") -> 34 | D33: =COUNTIFS(数据清洗!$E$2:$E$177,1) -> 122 | E33: =IF(D33=0,"",C33/D33) -> 0.27868852 | F33: 主分析样本
A34: B站频率 | B34: 过去3个月没有使用过 | C34: =COUNTIFS(数据清洗!$E$2:$E$177,1,数据清洗!$J$2:$J$177,"过去3个月没有使用过") -> 2 | D34: =COUNTIFS(数据清洗!$E$2:$E$177,1) -> 122 | E34: =IF(D34=0,"",C34/D34) -> 0.016393443 | F34: 主分析样本

Sheet 购买及闲置行为
A1: 购买及闲置行为
A2: 购买、闲置单选按主样本统计；Q8/9仅购买者；Q11排除9份与明确未尝试冲突的记录。多选百分比可超过100%。
A5: 题目/范围 | B5: 选项 | C5: 人数 n | D5: 有效分母 N | E5: 比例 n/N | F5: 口径 | I5: 选项 | J5: 人数
A6: 购买次数 | B6: 1–2次 | C6: =COUNTIFS(数据清洗!$E$2:$E$177,1,数据清洗!$K$2:$K$177,"1–2次") -> 33 | D6: =COUNTIFS(数据清洗!$E$2:$E$177,1) -> 122 | E6: =IF(D6=0,"",C6/D6) -> 0.2704918 | F6: 主分析样本 | I6: 有 | J6: =购买及闲置行为!C12 -> 58
A7: 购买次数 | B7: 3–5次 | C7: =COUNTIFS(数据清洗!$E$2:$E$177,1,数据清洗!$K$2:$K$177,"3–5次") -> 38 | D7: =COUNTIFS(数据清洗!$E$2:$E$177,1) -> 122 | E7: =IF(D7=0,"",C7/D7) -> 0.31147541 | F7: 主分析样本 | I7: 没有 | J7: =购买及闲置行为!C13 -> 43
A8: 购买次数 | B8: 0次 | C8: =COUNTIFS(数据清洗!$E$2:$E$177,1,数据清洗!$K$2:$K$177,"0次") -> 28 | D8: =COUNTIFS(数据清洗!$E$2:$E$177,1) -> 122 | E8: =IF(D8=0,"",C8/D8) -> 0.2295082 | F8: 主分析样本 | I8: 不确定 | J8: =购买及闲置行为!C14 -> 21
A9: 购买次数 | B9: 6–11次 | C9: =COUNTIFS(数据清洗!$E$2:$E$177,1,数据清洗!$K$2:$K$177,"6–11次") -> 20 | D9: =COUNTIFS(数据清洗!$E$2:$E$177,1) -> 122 | E9: =IF(D9=0,"",C9/D9) -> 0.16393443 | F9: 主分析样本
A10: 购买次数 | B10: 12次及以上 | C10: =COUNTIFS(数据清洗!$E$2:$E$177,1,数据清洗!$K$2:$K$177,"12次及以上") -> 2 | D10: =COUNTIFS(数据清洗!$E$2:$E$177,1) -> 122 | E10: =IF(D10=0,"",C10/D10) -> 0.016393443 | F10: 主分析样本
A11: 购买次数 | B11: 买过，但记不清次数 | C11: =COUNTIFS(数据清洗!$E$2:$E$177,1,数据清洗!$K$2:$K$177,"买过，但记不清次数") -> 1 | D11: =COUNTIFS(数据清洗!$E$2:$E$177,1) -> 122 | E11: =IF(D11=0,"",C11/D11) -> 0.0081967213 | F11: 主分析样本
A12: 闲置情况 | B12: 有 | C12: =COUNTIFS(数据清洗!$E$2:$E$177,1,数据清洗!$M$2:$M$177,"有") -> 58 | D12: =COUNTIFS(数据清洗!$E$2:$E$177,1) -> 122 | E12: =IF(D12=0,"",C12/D12) -> 0.47540984 | F12: 主分析样本
A13: 闲置情况 | B13: 没有 | C13: =COUNTIFS(数据清洗!$E$2:$E$177,1,数据清洗!$M$2:$M$177,"没有") -> 43 | D13: =COUNTIFS(数据清洗!$E$2:$E$177,1) -> 122 | E13: =IF(D13=0,"",C13/D13) -> 0.35245902 | F13: 主分析样本
A14: 闲置情况 | B14: 不确定 | C14: =COUNTIFS(数据清洗!$E$2:$E$177,1,数据清洗!$M$2:$M$177,"不确定") -> 21 | D14: =COUNTIFS(数据清洗!$E$2:$E$177,1) -> 122 | E14: =IF(D14=0,"",C14/D14) -> 0.17213115 | F14: 主分析样本
A15: Q8 购买类型（多选） | B15: 亚克力立牌／挂件等 | C15: =COUNTIFS(数据清洗!$E$2:$E$177,1,数据清洗!$Y$2:$Y$177,1,数据清洗!$Z$2:$Z$177,1) -> 45 | D15: =COUNTIFS(数据清洗!$E$2:$E$177,1,数据清洗!$Y$2:$Y$177,1) -> 93 | E15: =IF(D15=0,"",C15/D15) -> 0.48387097 | F15: Q8购买类型；限近期购买且无互斥冲突
A16: Q8 购买类型（多选） | B16: 其他，请注明: | C16: =COUNTIFS(数据清洗!$E$2:$E$177,1,数据清洗!$Y$2:$Y$177,1,数据清洗!$AA$2:$AA$177,1) -> 1 | D16: =COUNTIFS(数据清洗!$E$2:$E$177,1,数据清洗!$Y$2:$Y$177,1) -> 93 | E16: =IF(D16=0,"",C16/D16) -> 0.010752688 | F16: Q8购买类型；限近期购买且无互斥冲突
A17: Q8 购买类型（多选） | B17: 卡片／拍立得／纸类周边 | C17: =COUNTIFS(数据清洗!$E$2:$E$177,1,数据清洗!$Y$2:$Y$177,1,数据清洗!$AB$2:$AB$177,1) -> 38 | D17: =COUNTIFS(数据清洗!$E$2:$E$177,1,数据清洗!$Y$2:$Y$177,1) -> 93 | E17: =IF(D17=0,"",C17/D17) -> 0.40860215 | F17: Q8购买类型；限近期购买且无互斥冲突
A18: Q8 购买类型（多选） | B18: 徽章／吧唧 | C18: =COUNTIFS(数据清洗!$E$2:$E$177,1,数据清洗!$Y$2:$Y$177,1,数据清洗!$AC$2:$AC$177,1) -> 36 | D18: =COUNTIFS(数据清洗!$E$2:$E$177,1,数据清洗!$Y$2:$Y$177,1) -> 93 | E18: =IF(D18=0,"",C18/D18) -> 0.38709677 | F18: Q8购买类型；限近期购买且无互斥冲突
A19: Q8 购买类型（多选） | B19: 手办／模型 | C19: =COUNTIFS(数据清洗!$E$2:$E$177,1,数据清洗!$Y$2:$Y$177,1,数据清洗!$AD$2:$AD$177,1) -> 55 | D19: =COUNTIFS(数据清洗!$E$2:$E$177,1,数据清洗!$Y$2:$Y$177,1) -> 93 | E19: =IF(D19=0,"",C19/D19) -> 0.59139785 | F19: Q8购买类型；限近期购买且无互斥冲突
A20: Q8 购买类型（多选） | B20: 毛绒玩具／棉花娃娃 | C20: =COUNTIFS(数据清洗!$E$2:$E$177,1,数据清洗!$Y$2:$Y$177,1,数据清洗!$AE$2:$AE$177,1) -> 30 | D20: =COUNTIFS(数据清洗!$E$2:$E$177,1,数据清洗!$Y$2:$Y$177,1) -> 93 | E20: =IF(D20=0,"",C20/D20) -> 0.32258065 | F20: Q8购买类型；限近期购买且无互斥冲突
A21: Q8 购买类型（多选） | B21: 记不清 | C21: =COUNTIFS(数据清洗!$E$2:$E$177,1,数据清洗!$Y$2:$Y$177,1,数据清洗!$AF$2:$AF$177,1) -> 0 | D21: =COUNTIFS(数据清洗!$E$2:$E$177,1,数据清洗!$Y$2:$Y$177,1) -> 93 | E21: =IF(D21=0,"",C21/D21) -> 0 | F21: Q8购买类型；限近期购买且无互斥冲突
A22: Q9 购买渠道（多选） | B22: B站会员购市集 | C22: =COUNTIFS(数据清洗!$E$2:$E$177,1,数据清洗!$AG$2:$AG$177,1,数据清洗!$AH$2:$AH$177,1) -> 41 | D22: =COUNTIFS(数据清洗!$E$2:$E$177,1,数据清洗!$AG$2:$AG$177,1) -> 93 | E22: =IF(D22=0,"",C22/D22) -> 0.44086022 | F22: Q9购买渠道；限近期购买且无互斥冲突
A23: Q9 购买渠道（多选） | B23: B站会员购（不含市集） | C23: =COUNTIFS(数据清洗!$E$2:$E$177,1,数据清洗!$AG$2:$AG$177,1,数据清洗!$AI$2:$AI$177,1) -> 38 | D23: =COUNTIFS(数据清洗!$E$2:$E$177,1,数据清洗!$AG$2:$AG$177,1) -> 93 | E23: =IF(D23=0,"",C23/D23) -> 0.40860215 | F23: Q9购买渠道；限近期购买且无互斥冲突
A24: Q9 购买渠道（多选） | B24: QQ群／QQ同好 | C24: =COUNTIFS(数据清洗!$E$2:$E$177,1,数据清洗!$AG$2:$AG$177,1,数据清洗!$AJ$2:$AJ$177,1) -> 18 | D24: =COUNTIFS(数据清洗!$E$2:$E$177,1,数据清洗!$AG$2:$AG$177,1) -> 93 | E24: =IF(D24=0,"",C24/D24) -> 0.19354839 | F24: Q9购买渠道；限近期购买且无互斥冲突
A25: Q9 购买渠道（多选） | B25: 其他线上渠道，如淘宝、品牌官方店等 | C25: =COUNTIFS(数据清洗!$E$2:$E$177,1,数据清洗!$AG$2:$AG$177,1,数据清洗!$AK$2:$AK$177,1) -> 44 | D25: =COUNTIFS(数据清洗!$E$2:$E$177,1,数据清洗!$AG$2:$AG$177,1) -> 93 | E25: =IF(D25=0,"",C25/D25) -> 0.47311828 | F25: Q9购买渠道；限近期购买且无互斥冲突
A26: Q9 购买渠道（多选） | B26: 其他，请注明: | C26: =COUNTIFS(数据清洗!$E$2:$E$177,1,数据清洗!$AG$2:$AG$177,1,数据清洗!$AL$2:$AL$177,1) -> 3 | D26: =COUNTIFS(数据清洗!$E$2:$E$177,1,数据清洗!$AG$2:$AG$177,1) -> 93 | E26: =IF(D26=0,"",C26/D26) -> 0.032258065 | F26: Q9购买渠道；限近期购买且无互斥冲突
A27: Q9 购买渠道（多选） | B27: 微信群／微信同好 | C27: =COUNTIFS(数据清洗!$E$2:$E$177,1,数据清洗!$AG$2:$AG$177,1,数据清洗!$AM$2:$AM$177,1) -> 26 | D27: =COUNTIFS(数据清洗!$E$2:$E$177,1,数据清洗!$AG$2:$AG$177,1) -> 93 | E27: =IF(D27=0,"",C27/D27) -> 0.27956989 | F27: Q9购买渠道；限近期购买且无互斥冲突
A28: Q9 购买渠道（多选） | B28: 线下门店／展会／同好活动 | C28: =COUNTIFS(数据清洗!$E$2:$E$177,1,数据清洗!$AG$2:$AG$177,1,数据清洗!$AN$2:$AN$177,1) -> 18 | D28: =COUNTIFS(数据清洗!$E$2:$E$177,1,数据清洗!$AG$2:$AG$177,1) -> 93 | E28: =IF(D28=0,"",C28/D28) -> 0.19354839 | F28: Q9购买渠道；限近期购买且无互斥冲突 | I28: 选项 | J28: 人数
A29: Q9 购买渠道（多选） | B29: 记不清 | C29: =COUNTIFS(数据清洗!$E$2:$E$177,1,数据清洗!$AG$2:$AG$177,1,数据清洗!$AO$2:$AO$177,1) -> 0 | D29: =COUNTIFS(数据清洗!$E$2:$E$177,1,数据清洗!$AG$2:$AG$177,1) -> 93 | E29: =IF(D29=0,"",C29/D29) -> 0 | F29: Q9购买渠道；限近期购买且无互斥冲突 | I29: 尝试出售 | J29: =购买及闲置行为!C34 -> 31
A30: Q9 购买渠道（多选） | B30: 闲鱼 | C30: =COUNTIFS(数据清洗!$E$2:$E$177,1,数据清洗!$AG$2:$AG$177,1,数据清洗!$AP$2:$AP$177,1) -> 49 | D30: =COUNTIFS(数据清洗!$E$2:$E$177,1,数据清洗!$AG$2:$AG$177,1) -> 93 | E30: =IF(D30=0,"",C30/D30) -> 0.52688172 | F30: Q9购买渠道；限近期购买且无互斥冲突 | I30: 尝试交换 | J30: =购买及闲置行为!C33 -> 26
A31: Q11 处理方式（多选） | B31: 丢弃／回收 | C31: =COUNTIFS(数据清洗!$E$2:$E$177,1,数据清洗!$AQ$2:$AQ$177,1,数据清洗!$AR$2:$AR$177,1) -> 5 | D31: =COUNTIFS(数据清洗!$E$2:$E$177,1,数据清洗!$AQ$2:$AQ$177,1) -> 49 | E31: =IF(D31=0,"",C31/D31) -> 0.10204082 | F31: Q11处理方式；限Q10有闲置且与明确均未尝试不冲突 | I31: 继续保留 | J31: =购买及闲置行为!C35 -> 18
A32: Q11 处理方式（多选） | B32: 其他，请注明: | C32: =COUNTIFS(数据清洗!$E$2:$E$177,1,数据清洗!$AQ$2:$AQ$177,1,数据清洗!$AS$2:$AS$177,1) -> 0 | D32: =COUNTIFS(数据清洗!$E$2:$E$177,1,数据清洗!$AQ$2:$AQ$177,1) -> 49 | E32: =IF(D32=0,"",C32/D32) -> 0 | F32: Q11处理方式；限Q10有闲置且与明确均未尝试不冲突 | I32: 赠送 | J32: =购买及闲置行为!C36 -> 11
A33: Q11 处理方式（多选） | B33: 尝试交换，包括发布换物信息或联系交换对象 | C33: =COUNTIFS(数据清洗!$E$2:$E$177,1,数据清洗!$AQ$2:$AQ$177,1,数据清洗!$AT$2:$AT$177,1) -> 26 | D33: =COUNTIFS(数据清洗!$E$2:$E$177,1,数据清洗!$AQ$2:$AQ$177,1) -> 49 | E33: =IF(D33=0,"",C33/D33) -> 0.53061224 | F33: Q11处理方式；限Q10有闲置且与明确均未尝试不冲突 | I33: 丢弃／回收 | J33: =购买及闲置行为!C31 -> 5
A34: Q11 处理方式（多选） | B34: 尝试出售，包括发布信息、询价或联系买家 | C34: =COUNTIFS(数据清洗!$E$2:$E$177,1,数据清洗!$AQ$2:$AQ$177,1,数据清洗!$AU$2:$AU$177,1) -> 31 | D34: =COUNTIFS(数据清洗!$E$2:$E$177,1,数据清洗!$AQ$2:$AQ$177,1) -> 49 | E34: =IF(D34=0,"",C34/D34) -> 0.63265306 | F34: Q11处理方式；限Q10有闲置且与明确均未尝试不冲突
A35: Q11 处理方式（多选） | B35: 继续保留，尚未采取处理行动 | C35: =COUNTIFS(数据清洗!$E$2:$E$177,1,数据清洗!$AQ$2:$AQ$177,1,数据清洗!$AV$2:$AV$177,1) -> 18 | D35: =COUNTIFS(数据清洗!$E$2:$E$177,1,数据清洗!$AQ$2:$AQ$177,1) -> 49 | E35: =IF(D35=0,"",C35/D35) -> 0.36734694 | F35: Q11处理方式；限Q10有闲置且与明确均未尝试不冲突
A36: Q11 处理方式（多选） | B36: 赠送 | C36: =COUNTIFS(数据清洗!$E$2:$E$177,1,数据清洗!$AQ$2:$AQ$177,1,数据清洗!$AW$2:$AW$177,1) -> 11 | D36: =COUNTIFS(数据清洗!$E$2:$E$177,1,数据清洗!$AQ$2:$AQ$177,1) -> 49 | E36: =IF(D36=0,"",C36/D36) -> 0.2244898 | F36: Q11处理方式；限Q10有闲置且与明确均未尝试不冲突

Sheet 交易痛点
A1: 交易痛点
A2: 出售、交换按Q12可确认的记录分列；另一行为未知。Q14严格可配对子样本仅27份，不能据此推算总体痛点发生率。
A5: 题目/范围 | B5: 选项 | C5: 人数 n | D5: 有效分母 N | E5: 比例 n/N | F5: 口径 | I5: 选项 | J5: 人数
A6: 交易分组 | B6: 交换尝试记录 | C6: =COUNTIFS(数据清洗!$E$2:$E$177,1,数据清洗!$X$2:$X$177,"交换尝试记录") -> 40 | D6: =COUNTIFS(数据清洗!$E$2:$E$177,1) -> 122 | E6: =IF(D6=0,"",C6/D6) -> 0.32786885 | F6: 主分析样本 | I6: 出售尝试记录 | J6: =交易痛点!C7 -> 28
A7: 交易分组 | B7: 出售尝试记录 | C7: =COUNTIFS(数据清洗!$E$2:$E$177,1,数据清洗!$X$2:$X$177,"出售尝试记录") -> 28 | D7: =COUNTIFS(数据清洗!$E$2:$E$177,1) -> 122 | E7: =IF(D7=0,"",C7/D7) -> 0.2295082 | F7: 主分析样本 | I7: 交换尝试记录 | J7: =交易痛点!C6 -> 40
A8: 交易分组 | B8: 无法判断 | C8: =COUNTIFS(数据清洗!$E$2:$E$177,1,数据清洗!$X$2:$X$177,"无法判断") -> 13 | D8: =COUNTIFS(数据清洗!$E$2:$E$177,1) -> 122 | E8: =IF(D8=0,"",C8/D8) -> 0.10655738 | F8: 主分析样本 | I8: 明确均未尝试 | J8: =交易痛点!C9 -> 41
A9: 交易分组 | B9: 明确均未尝试 | C9: =COUNTIFS(数据清洗!$E$2:$E$177,1,数据清洗!$X$2:$X$177,"明确均未尝试") -> 41 | D9: =COUNTIFS(数据清洗!$E$2:$E$177,1) -> 122 | E9: =IF(D9=0,"",C9/D9) -> 0.33606557 | F9: 主分析样本 | I9: 无法判断 | J9: =交易痛点!C8 -> 13
A10: Q13 尝试渠道（多选） | B10: B站会员购市集 | C10: =COUNTIFS(数据清洗!$E$2:$E$177,1,数据清洗!$AX$2:$AX$177,1,数据清洗!$AY$2:$AY$177,1) -> 32 | D10: =COUNTIFS(数据清洗!$E$2:$E$177,1,数据清洗!$AX$2:$AX$177,1) -> 68 | E10: =IF(D10=0,"",C10/D10) -> 0.47058824 | F10: Q13合并渠道；限Q12可确认尝试，不分出售交换
A11: Q13 尝试渠道（多选） | B11: B站其他位置，如动态、评论、私信等 | C11: =COUNTIFS(数据清洗!$E$2:$E$177,1,数据清洗!$AX$2:$AX$177,1,数据清洗!$AZ$2:$AZ$177,1) -> 36 | D11: =COUNTIFS(数据清洗!$E$2:$E$177,1,数据清洗!$AX$2:$AX$177,1) -> 68 | E11: =IF(D11=0,"",C11/D11) -> 0.52941176 | F11: Q13合并渠道；限Q12可确认尝试，不分出售交换
A12: Q13 尝试渠道（多选） | B12: QQ群／QQ同好 | C12: =COUNTIFS(数据清洗!$E$2:$E$177,1,数据清洗!$AX$2:$AX$177,1,数据清洗!$BA$2:$BA$177,1) -> 13 | D12: =COUNTIFS(数据清洗!$E$2:$E$177,1,数据清洗!$AX$2:$AX$177,1) -> 68 | E12: =IF(D12=0,"",C12/D12) -> 0.19117647 | F12: Q13合并渠道；限Q12可确认尝试，不分出售交换
A13: Q13 尝试渠道（多选） | B13: 其他，请注明: | C13: =COUNTIFS(数据清洗!$E$2:$E$177,1,数据清洗!$AX$2:$AX$177,1,数据清洗!$BB$2:$BB$177,1) -> 0 | D13: =COUNTIFS(数据清洗!$E$2:$E$177,1,数据清洗!$AX$2:$AX$177,1) -> 68 | E13: =IF(D13=0,"",C13/D13) -> 0 | F13: Q13合并渠道；限Q12可确认尝试，不分出售交换
A14: Q13 尝试渠道（多选） | B14: 微信群／微信同好 | C14: =COUNTIFS(数据清洗!$E$2:$E$177,1,数据清洗!$AX$2:$AX$177,1,数据清洗!$BC$2:$BC$177,1) -> 28 | D14: =COUNTIFS(数据清洗!$E$2:$E$177,1,数据清洗!$AX$2:$AX$177,1) -> 68 | E14: =IF(D14=0,"",C14/D14) -> 0.41176471 | F14: Q13合并渠道；限Q12可确认尝试，不分出售交换
A15: Q13 尝试渠道（多选） | B15: 线下门店／展会／同好活动 | C15: =COUNTIFS(数据清洗!$E$2:$E$177,1,数据清洗!$AX$2:$AX$177,1,数据清洗!$BD$2:$BD$177,1) -> 17 | D15: =COUNTIFS(数据清洗!$E$2:$E$177,1,数据清洗!$AX$2:$AX$177,1) -> 68 | E15: =IF(D15=0,"",C15/D15) -> 0.25 | F15: Q13合并渠道；限Q12可确认尝试，不分出售交换
A16: Q13 尝试渠道（多选） | B16: 记不清 | C16: =COUNTIFS(数据清洗!$E$2:$E$177,1,数据清洗!$AX$2:$AX$177,1,数据清洗!$BE$2:$BE$177,1) -> 0 | D16: =COUNTIFS(数据清洗!$E$2:$E$177,1,数据清洗!$AX$2:$AX$177,1) -> 68 | E16: =IF(D16=0,"",C16/D16) -> 0 | F16: Q13合并渠道；限Q12可确认尝试，不分出售交换
A17: Q13 尝试渠道（多选） | B17: 闲鱼 | C17: =COUNTIFS(数据清洗!$E$2:$E$177,1,数据清洗!$AX$2:$AX$177,1,数据清洗!$BF$2:$BF$177,1) -> 37 | D17: =COUNTIFS(数据清洗!$E$2:$E$177,1,数据清洗!$AX$2:$AX$177,1) -> 68 | E17: =IF(D17=0,"",C17/D17) -> 0.54411765 | F17: Q13合并渠道；限Q12可确认尝试，不分出售交换
A18: 出售尝试记录痛点 | B18: 付款或发货顺序难以协商 | C18: =COUNTIFS(数据清洗!$E$2:$E$177,1,数据清洗!$BG$2:$BG$177,1,数据清洗!$X$2:$X$177,"出售尝试记录",数据清洗!$BH$2:$BH$177,1) -> 1 | D18: =COUNTIFS(数据清洗!$E$2:$E$177,1,数据清洗!$BG$2:$BG$177,1,数据清洗!$X$2:$X$177,"出售尝试记录") -> 9 | E18: =IF(D18=0,"",C18/D18) -> 0.11111111 | F18: 仅Q12与Q14行可配对、无互斥冲突；小样本探索
A19: 出售尝试记录痛点 | B19: 其他，请注明: | C19: =COUNTIFS(数据清洗!$E$2:$E$177,1,数据清洗!$BG$2:$BG$177,1,数据清洗!$X$2:$X$177,"出售尝试记录",数据清洗!$BI$2:$BI$177,1) -> 0 | D19: =COUNTIFS(数据清洗!$E$2:$E$177,1,数据清洗!$BG$2:$BG$177,1,数据清洗!$X$2:$X$177,"出售尝试记录") -> 9 | E19: =IF(D19=0,"",C19/D19) -> 0 | F19: 仅Q12与Q14行可配对、无互斥冲突；小样本探索
A20: 出售尝试记录痛点 | B20: 对方临时取消或不再回复 | C20: =COUNTIFS(数据清洗!$E$2:$E$177,1,数据清洗!$BG$2:$BG$177,1,数据清洗!$X$2:$X$177,"出售尝试记录",数据清洗!$BJ$2:$BJ$177,1) -> 3 | D20: =COUNTIFS(数据清洗!$E$2:$E$177,1,数据清洗!$BG$2:$BG$177,1,数据清洗!$X$2:$X$177,"出售尝试记录") -> 9 | E20: =IF(D20=0,"",C20/D20) -> 0.33333333 | F20: 仅Q12与Q14行可配对、无互斥冲突；小样本探索
A21: 出售尝试记录痛点 | B21: 对方对我提供的商品信息有疑虑 | C21: =COUNTIFS(数据清洗!$E$2:$E$177,1,数据清洗!$BG$2:$BG$177,1,数据清洗!$X$2:$X$177,"出售尝试记录",数据清洗!$BK$2:$BK$177,1) -> 3 | D21: =COUNTIFS(数据清洗!$E$2:$E$177,1,数据清洗!$BG$2:$BG$177,1,数据清洗!$X$2:$X$177,"出售尝试记录") -> 9 | E21: =IF(D21=0,"",C21/D21) -> 0.33333333 | F21: 仅Q12与Q14行可配对、无互斥冲突；小样本探索
A22: 出售尝试记录痛点 | B22: 没有遇到明显问题 | C22: =COUNTIFS(数据清洗!$E$2:$E$177,1,数据清洗!$BG$2:$BG$177,1,数据清洗!$X$2:$X$177,"出售尝试记录",数据清洗!$BL$2:$BL$177,1) -> 0 | D22: =COUNTIFS(数据清洗!$E$2:$E$177,1,数据清洗!$BG$2:$BG$177,1,数据清洗!$X$2:$X$177,"出售尝试记录") -> 9 | E22: =IF(D22=0,"",C22/D22) -> 0 | F22: 仅Q12与Q14行可配对、无互斥冲突；小样本探索
A23: 出售尝试记录痛点 | B23: 记不清 | C23: =COUNTIFS(数据清洗!$E$2:$E$177,1,数据清洗!$BG$2:$BG$177,1,数据清洗!$X$2:$X$177,"出售尝试记录",数据清洗!$BM$2:$BM$177,1) -> 0 | D23: =COUNTIFS(数据清洗!$E$2:$E$177,1,数据清洗!$BG$2:$BG$177,1,数据清洗!$X$2:$X$177,"出售尝试记录") -> 9 | E23: =IF(D23=0,"",C23/D23) -> 0 | F23: 仅Q12与Q14行可配对、无互斥冲突；小样本探索
A24: 出售尝试记录痛点 | B24: 遇到物流损坏或丢失 | C24: =COUNTIFS(数据清洗!$E$2:$E$177,1,数据清洗!$BG$2:$BG$177,1,数据清洗!$X$2:$X$177,"出售尝试记录",数据清洗!$BN$2:$BN$177,1) -> 1 | D24: =COUNTIFS(数据清洗!$E$2:$E$177,1,数据清洗!$BG$2:$BG$177,1,数据清洗!$X$2:$X$177,"出售尝试记录") -> 9 | E24: =IF(D24=0,"",C24/D24) -> 0.11111111 | F24: 仅Q12与Q14行可配对、无互斥冲突；小样本探索
A25: 出售尝试记录痛点 | B25: 遇到纠纷后难以解决 | C25: =COUNTIFS(数据清洗!$E$2:$E$177,1,数据清洗!$BG$2:$BG$177,1,数据清洗!$X$2:$X$177,"出售尝试记录",数据清洗!$BO$2:$BO$177,1) -> 1 | D25: =COUNTIFS(数据清洗!$E$2:$E$177,1,数据清洗!$BG$2:$BG$177,1,数据清洗!$X$2:$X$177,"出售尝试记录") -> 9 | E25: =IF(D25=0,"",C25/D25) -> 0.11111111 | F25: 仅Q12与Q14行可配对、无互斥冲突；小样本探索
A26: 出售尝试记录痛点 | B26: 难以就价格／补差价达成一致 | C26: =COUNTIFS(数据清洗!$E$2:$E$177,1,数据清洗!$BG$2:$BG$177,1,数据清洗!$X$2:$X$177,"出售尝试记录",数据清洗!$BQ$2:$BQ$177,1) -> 5 | D26: =COUNTIFS(数据清洗!$E$2:$E$177,1,数据清洗!$BG$2:$BG$177,1,数据清洗!$X$2:$X$177,"出售尝试记录") -> 9 | E26: =IF(D26=0,"",C26/D26) -> 0.55555556 | F26: 仅Q12与Q14行可配对、无互斥冲突；小样本探索
A27: 出售尝试记录痛点 | B27: 难以找到想要我这件周边的人 | C27: =COUNTIFS(数据清洗!$E$2:$E$177,1,数据清洗!$BG$2:$BG$177,1,数据清洗!$X$2:$X$177,"出售尝试记录",数据清洗!$BR$2:$BR$177,1) -> 2 | D27: =COUNTIFS(数据清洗!$E$2:$E$177,1,数据清洗!$BG$2:$BG$177,1,数据清洗!$X$2:$X$177,"出售尝试记录") -> 9 | E27: =IF(D27=0,"",C27/D27) -> 0.22222222 | F27: 仅Q12与Q14行可配对、无互斥冲突；小样本探索
A28: 出售尝试记录痛点 | B28: 需要反复沟通品相、包装等细节 | C28: =COUNTIFS(数据清洗!$E$2:$E$177,1,数据清洗!$BG$2:$BG$177,1,数据清洗!$X$2:$X$177,"出售尝试记录",数据清洗!$BT$2:$BT$177,1) -> 4 | D28: =COUNTIFS(数据清洗!$E$2:$E$177,1,数据清洗!$BG$2:$BG$177,1,数据清洗!$X$2:$X$177,"出售尝试记录") -> 9 | E28: =IF(D28=0,"",C28/D28) -> 0.44444444 | F28: 仅Q12与Q14行可配对、无互斥冲突；小样本探索
A29: 交换尝试记录痛点 | B29: 付款或发货顺序难以协商 | C29: =COUNTIFS(数据清洗!$E$2:$E$177,1,数据清洗!$BG$2:$BG$177,1,数据清洗!$X$2:$X$177,"交换尝试记录",数据清洗!$BH$2:$BH$177,1) -> 7 | D29: =COUNTIFS(数据清洗!$E$2:$E$177,1,数据清洗!$BG$2:$BG$177,1,数据清洗!$X$2:$X$177,"交换尝试记录") -> 18 | E29: =IF(D29=0,"",C29/D29) -> 0.38888889 | F29: 仅Q12与Q14行可配对、无互斥冲突；小样本探索
A30: 交换尝试记录痛点 | B30: 其他，请注明: | C30: =COUNTIFS(数据清洗!$E$2:$E$177,1,数据清洗!$BG$2:$BG$177,1,数据清洗!$X$2:$X$177,"交换尝试记录",数据清洗!$BI$2:$BI$177,1) -> 0 | D30: =COUNTIFS(数据清洗!$E$2:$E$177,1,数据清洗!$BG$2:$BG$177,1,数据清洗!$X$2:$X$177,"交换尝试记录") -> 18 | E30: =IF(D30=0,"",C30/D30) -> 0 | F30: 仅Q12与Q14行可配对、无互斥冲突；小样本探索
A31: 交换尝试记录痛点 | B31: 对方临时取消或不再回复 | C31: =COUNTIFS(数据清洗!$E$2:$E$177,1,数据清洗!$BG$2:$BG$177,1,数据清洗!$X$2:$X$177,"交换尝试记录",数据清洗!$BJ$2:$BJ$177,1) -> 2 | D31: =COUNTIFS(数据清洗!$E$2:$E$177,1,数据清洗!$BG$2:$BG$177,1,数据清洗!$X$2:$X$177,"交换尝试记录") -> 18 | E31: =IF(D31=0,"",C31/D31) -> 0.11111111 | F31: 仅Q12与Q14行可配对、无互斥冲突；小样本探索
A32: 交换尝试记录痛点 | B32: 对方对我提供的商品信息有疑虑 | C32: =COUNTIFS(数据清洗!$E$2:$E$177,1,数据清洗!$BG$2:$BG$177,1,数据清洗!$X$2:$X$177,"交换尝试记录",数据清洗!$BK$2:$BK$177,1) -> 6 | D32: =COUNTIFS(数据清洗!$E$2:$E$177,1,数据清洗!$BG$2:$BG$177,1,数据清洗!$X$2:$X$177,"交换尝试记录") -> 18 | E32: =IF(D32=0,"",C32/D32) -> 0.33333333 | F32: 仅Q12与Q14行可配对、无互斥冲突；小样本探索
A33: 交换尝试记录痛点 | B33: 没有遇到明显问题 | C33: =COUNTIFS(数据清洗!$E$2:$E$177,1,数据清洗!$BG$2:$BG$177,1,数据清洗!$X$2:$X$177,"交换尝试记录",数据清洗!$BL$2:$BL$177,1) -> 0 | D33: =COUNTIFS(数据清洗!$E$2:$E$177,1,数据清洗!$BG$2:$BG$177,1,数据清洗!$X$2:$X$177,"交换尝试记录") -> 18 | E33: =IF(D33=0,"",C33/D33) -> 0 | F33: 仅Q12与Q14行可配对、无互斥冲突；小样本探索
A34: 交换尝试记录痛点 | B34: 记不清 | C34: =COUNTIFS(数据清洗!$E$2:$E$177,1,数据清洗!$BG$2:$BG$177,1,数据清洗!$X$2:$X$177,"交换尝试记录",数据清洗!$BM$2:$BM$177,1) -> 0 | D34: =COUNTIFS(数据清洗!$E$2:$E$177,1,数据清洗!$BG$2:$BG$177,1,数据清洗!$X$2:$X$177,"交换尝试记录") -> 18 | E34: =IF(D34=0,"",C34/D34) -> 0 | F34: 仅Q12与Q14行可配对、无互斥冲突；小样本探索
A35: 交换尝试记录痛点 | B35: 遇到物流损坏或丢失 | C35: =COUNTIFS(数据清洗!$E$2:$E$177,1,数据清洗!$BG$2:$BG$177,1,数据清洗!$X$2:$X$177,"交换尝试记录",数据清洗!$BN$2:$BN$177,1) -> 2 | D35: =COUNTIFS(数据清洗!$E$2:$E$177,1,数据清洗!$BG$2:$BG$177,1,数据清洗!$X$2:$X$177,"交换尝试记录") -> 18 | E35: =IF(D35=0,"",C35/D35) -> 0.11111111 | F35: 仅Q12与Q14行可配对、无互斥冲突；小样本探索
A36: 交换尝试记录痛点 | B36: 遇到纠纷后难以解决 | C36: =COUNTIFS(数据清洗!$E$2:$E$177,1,数据清洗!$BG$2:$BG$177,1,数据清洗!$X$2:$X$177,"交换尝试记录",数据清洗!$BO$2:$BO$177,1) -> 6 | D36: =COUNTIFS(数据清洗!$E$2:$E$177,1,数据清洗!$BG$2:$BG$177,1,数据清洗!$X$2:$X$177,"交换尝试记录") -> 18 | E36: =IF(D36=0,"",C36/D36) -> 0.33333333 | F36: 仅Q12与Q14行可配对、无互斥冲突；小样本探索
A37: 交换尝试记录痛点 | B37: 难以判断对方提供的商品信息是否真实【仅交换行】 | C37: =COUNTIFS(数据清洗!$E$2:$E$177,1,数据清洗!$BG$2:$BG$177,1,数据清洗!$X$2:$X$177,"交换尝试记录",数据清洗!$BP$2:$BP$177,1) -> 9 | D37: =COUNTIFS(数据清洗!$E$2:$E$177,1,数据清洗!$BG$2:$BG$177,1,数据清洗!$X$2:$X$177,"交换尝试记录") -> 18 | E37: =IF(D37=0,"",C37/D37) -> 0.5 | F37: 仅Q12与Q14行可配对、无互斥冲突；小样本探索
A38: 交换尝试记录痛点 | B38: 难以就价格／补差价达成一致 | C38: =COUNTIFS(数据清洗!$E$2:$E$177,1,数据清洗!$BG$2:$BG$177,1,数据清洗!$X$2:$X$177,"交换尝试记录",数据清洗!$BQ$2:$BQ$177,1) -> 5 | D38: =COUNTIFS(数据清洗!$E$2:$E$177,1,数据清洗!$BG$2:$BG$177,1,数据清洗!$X$2:$X$177,"交换尝试记录") -> 18 | E38: =IF(D38=0,"",C38/D38) -> 0.27777778 | F38: 仅Q12与Q14行可配对、无互斥冲突；小样本探索
A39: 交换尝试记录痛点 | B39: 难以找到想要我这件周边的人 | C39: =COUNTIFS(数据清洗!$E$2:$E$177,1,数据清洗!$BG$2:$BG$177,1,数据清洗!$X$2:$X$177,"交换尝试记录",数据清洗!$BR$2:$BR$177,1) -> 3 | D39: =COUNTIFS(数据清洗!$E$2:$E$177,1,数据清洗!$BG$2:$BG$177,1,数据清洗!$X$2:$X$177,"交换尝试记录") -> 18 | E39: =IF(D39=0,"",C39/D39) -> 0.16666667 | F39: 仅Q12与Q14行可配对、无互斥冲突；小样本探索
A40: 交换尝试记录痛点 | B40: 难以找到愿意拿出我想要款式的交换对象【仅交换行】 | C40: =COUNTIFS(数据清洗!$E$2:$E$177,1,数据清洗!$BG$2:$BG$177,1,数据清洗!$X$2:$X$177,"交换尝试记录",数据清洗!$BS$2:$BS$177,1) -> 9 | D40: =COUNTIFS(数据清洗!$E$2:$E$177,1,数据清洗!$BG$2:$BG$177,1,数据清洗!$X$2:$X$177,"交换尝试记录") -> 18 | E40: =IF(D40=0,"",C40/D40) -> 0.5 | F40: 仅Q12与Q14行可配对、无互斥冲突；小样本探索
A41: 交换尝试记录痛点 | B41: 需要反复沟通品相、包装等细节 | C41: =COUNTIFS(数据清洗!$E$2:$E$177,1,数据清洗!$BG$2:$BG$177,1,数据清洗!$X$2:$X$177,"交换尝试记录",数据清洗!$BT$2:$BT$177,1) -> 9 | D41: =COUNTIFS(数据清洗!$E$2:$E$177,1,数据清洗!$BG$2:$BG$177,1,数据清洗!$X$2:$X$177,"交换尝试记录") -> 18 | E41: =IF(D41=0,"",C41/D41) -> 0.5 | F41: 仅Q12与Q14行可配对、无互斥冲突；小样本探索

Sheet 功能意向
A1: 功能意向
A2: Q6缺少服务与状态配对，不能估计市集认知/使用率。Q16只统计明确可能性填写；名称被勾选不等于愿意使用。
A5: 功能 | B5: 高意向 n | C5: 有效 N | D5: 高意向 n/N | E5: 缺失或歧义 | F5: 不适用人数 | G5: 排除不适用后
A6: 发布出售 | B6: =COUNTIFS(数据清洗!$E$2:$E$177,1,数据清洗!$CQ$2:$CQ$177,4)+COUNTIFS(数据清洗!$E$2:$E$177,1,数据清洗!$CQ$2:$CQ$177,5) -> 47 | C6: =COUNTIFS(数据清洗!$E$2:$E$177,1,数据清洗!$CQ$2:$CQ$177,"<>") -> 59 | D6: =IF(C6=0,"",B6/C6) -> 0.79661017 | E6: =COUNTIFS(数据清洗!$E$2:$E$177,1)-C6 -> 63 | F6: =COUNTIFS(数据清洗!$E$2:$E$177,1,数据清洗!$CQ$2:$CQ$177,97) -> 1 | G6: =IF(C6-F6=0,"",B6/(C6-F6)) -> 0.81034483
A7: 寻找交换 | B7: =COUNTIFS(数据清洗!$E$2:$E$177,1,数据清洗!$CS$2:$CS$177,4)+COUNTIFS(数据清洗!$E$2:$E$177,1,数据清洗!$CS$2:$CS$177,5) -> 41 | C7: =COUNTIFS(数据清洗!$E$2:$E$177,1,数据清洗!$CS$2:$CS$177,"<>") -> 63 | D7: =IF(C7=0,"",B7/C7) -> 0.65079365 | E7: =COUNTIFS(数据清洗!$E$2:$E$177,1)-C7 -> 59 | F7: =COUNTIFS(数据清洗!$E$2:$E$177,1,数据清洗!$CS$2:$CS$177,97) -> 0 | G7: =IF(C7-F7=0,"",B7/(C7-F7)) -> 0.65079365
A8: IP兴趣标签 | B8: =COUNTIFS(数据清洗!$E$2:$E$177,1,数据清洗!$CU$2:$CU$177,4)+COUNTIFS(数据清洗!$E$2:$E$177,1,数据清洗!$CU$2:$CU$177,5) -> 44 | C8: =COUNTIFS(数据清洗!$E$2:$E$177,1,数据清洗!$CU$2:$CU$177,"<>") -> 57 | D8: =IF(C8=0,"",B8/C8) -> 0.77192982 | E8: =COUNTIFS(数据清洗!$E$2:$E$177,1)-C8 -> 65 | F8: =COUNTIFS(数据清洗!$E$2:$E$177,1,数据清洗!$CU$2:$CU$177,97) -> 3 | G8: =IF(C8-F8=0,"",B8/(C8-F8)) -> 0.81481481
A9: 订单来源信息 | B9: =COUNTIFS(数据清洗!$E$2:$E$177,1,数据清洗!$CW$2:$CW$177,4)+COUNTIFS(数据清洗!$E$2:$E$177,1,数据清洗!$CW$2:$CW$177,5) -> 28 | C9: =COUNTIFS(数据清洗!$E$2:$E$177,1,数据清洗!$CW$2:$CW$177,"<>") -> 52 | D9: =IF(C9=0,"",B9/C9) -> 0.53846154 | E9: =COUNTIFS(数据清洗!$E$2:$E$177,1)-C9 -> 70 | F9: =COUNTIFS(数据清洗!$E$2:$E$177,1,数据清洗!$CW$2:$CW$177,97) -> 2 | G9: =IF(C9-F9=0,"",B9/(C9-F9)) -> 0.56
A11: 高意向=比较可能或非常可能。四项分母52–63不等；非随机缺失明显，不可按百分比直接排功能优先级。
A13: 题目/范围 | B13: 选项 | C13: 人数 n | D13: 有效分母 N | E13: 比例 n/N | F13: 口径
A14: Q17 顾虑（多选） | B14: 不确定付款、发货和纠纷处理是否有保障 | C14: =COUNTIFS(数据清洗!$E$2:$E$177,1,数据清洗!$BU$2:$BU$177,1,数据清洗!$BV$2:$BV$177,1) -> 51 | D14: =COUNTIFS(数据清洗!$E$2:$E$177,1,数据清洗!$BU$2:$BU$177,1) -> 117 | E14: =IF(D14=0,"",C14/D14) -> 0.43589744 | F14: Q17顾虑；排除互斥项混选
A15: Q17 顾虑（多选） | B15: 不确定商品信息是否可信 | C15: =COUNTIFS(数据清洗!$E$2:$E$177,1,数据清洗!$BU$2:$BU$177,1,数据清洗!$BW$2:$BW$177,1) -> 42 | D15: =COUNTIFS(数据清洗!$E$2:$E$177,1,数据清洗!$BU$2:$BU$177,1) -> 117 | E15: =IF(D15=0,"",C15/D15) -> 0.35897436 | F15: Q17顾虑；排除互斥项混选
A16: Q17 顾虑（多选） | B16: 不确定能否找到合适的交易对象 | C16: =COUNTIFS(数据清洗!$E$2:$E$177,1,数据清洗!$BU$2:$BU$177,1,数据清洗!$BX$2:$BX$177,1) -> 45 | D16: =COUNTIFS(数据清洗!$E$2:$E$177,1,数据清洗!$BU$2:$BU$177,1) -> 117 | E16: =IF(D16=0,"",C16/D16) -> 0.38461538 | F16: Q17顾虑；排除互斥项混选
A17: Q17 顾虑（多选） | B17: 信息不足，暂时无法判断 | C17: =COUNTIFS(数据清洗!$E$2:$E$177,1,数据清洗!$BU$2:$BU$177,1,数据清洗!$BY$2:$BY$177,1) -> 1 | D17: =COUNTIFS(数据清洗!$E$2:$E$177,1,数据清洗!$BU$2:$BU$177,1) -> 117 | E17: =IF(D17=0,"",C17/D17) -> 0.0085470085 | F17: Q17顾虑；排除互斥项混选
A18: Q17 顾虑（多选） | B18: 其他，请注明: | C18: =COUNTIFS(数据清洗!$E$2:$E$177,1,数据清洗!$BU$2:$BU$177,1,数据清洗!$BZ$2:$BZ$177,1) -> 6 | D18: =COUNTIFS(数据清洗!$E$2:$E$177,1,数据清洗!$BU$2:$BU$177,1) -> 117 | E18: =IF(D18=0,"",C18/D18) -> 0.051282051 | F18: Q17顾虑；排除互斥项混选
A19: Q17 顾虑（多选） | B19: 担心可交易的商品范围有限 | C19: =COUNTIFS(数据清洗!$E$2:$E$177,1,数据清洗!$BU$2:$BU$177,1,数据清洗!$CA$2:$CA$177,1) -> 17 | D19: =COUNTIFS(数据清洗!$E$2:$E$177,1,数据清洗!$BU$2:$BU$177,1) -> 117 | E19: =IF(D19=0,"",C19/D19) -> 0.14529915 | F19: Q17顾虑；排除互斥项混选
A20: Q17 顾虑（多选） | B20: 担心手续费或其他使用成本 | C20: =COUNTIFS(数据清洗!$E$2:$E$177,1,数据清洗!$BU$2:$BU$177,1,数据清洗!$CB$2:$CB$177,1) -> 25 | D20: =COUNTIFS(数据清洗!$E$2:$E$177,1,数据清洗!$BU$2:$BU$177,1) -> 117 | E20: =IF(D20=0,"",C20/D20) -> 0.21367521 | F20: Q17顾虑；排除互斥项混选
A21: Q17 顾虑（多选） | B21: 担心操作或沟通过于麻烦 | C21: =COUNTIFS(数据清洗!$E$2:$E$177,1,数据清洗!$BU$2:$BU$177,1,数据清洗!$CC$2:$CC$177,1) -> 26 | D21: =COUNTIFS(数据清洗!$E$2:$E$177,1,数据清洗!$BU$2:$BU$177,1) -> 117 | E21: =IF(D21=0,"",C21/D21) -> 0.22222222 | F21: Q17顾虑；排除互斥项混选
A22: Q17 顾虑（多选） | B22: 担心暴露兴趣、购买记录等隐私 | C22: =COUNTIFS(数据清洗!$E$2:$E$177,1,数据清洗!$BU$2:$BU$177,1,数据清洗!$CD$2:$CD$177,1) -> 36 | D22: =COUNTIFS(数据清洗!$E$2:$E$177,1,数据清洗!$BU$2:$BU$177,1) -> 117 | E22: =IF(D22=0,"",C22/D22) -> 0.30769231 | F22: Q17顾虑；排除互斥项混选
A23: Q17 顾虑（多选） | B23: 暂无顾虑 | C23: =COUNTIFS(数据清洗!$E$2:$E$177,1,数据清洗!$BU$2:$BU$177,1,数据清洗!$CE$2:$CE$177,1) -> 3 | D23: =COUNTIFS(数据清洗!$E$2:$E$177,1,数据清洗!$BU$2:$BU$177,1) -> 117 | E23: =IF(D23=0,"",C23/D23) -> 0.025641026 | F23: Q17顾虑；排除互斥项混选
A24: Q18 主要原因（单一回答） | B24: 其他，请注明: | C24: =COUNTIFS(数据清洗!$E$2:$E$177,1,数据清洗!$CF$2:$CF$177,1,数据清洗!$CG$2:$CG$177,1) -> 2 | D24: =COUNTIFS(数据清洗!$E$2:$E$177,1,数据清洗!$CF$2:$CF$177,1) -> 49 | E24: =IF(D24=0,"",C24/D24) -> 0.040816327 | F24: Q18仅保留单一选择，不能把多选解释为最主要原因
A25: Q18 主要原因（单一回答） | B25: 希望尝试更多渠道，增加找到对象的机会 | C25: =COUNTIFS(数据清洗!$E$2:$E$177,1,数据清洗!$CF$2:$CF$177,1,数据清洗!$CH$2:$CH$177,1) -> 7 | D25: =COUNTIFS(数据清洗!$E$2:$E$177,1,数据清洗!$CF$2:$CF$177,1) -> 49 | E25: =IF(D25=0,"",C25/D25) -> 0.14285714 | F25: Q18仅保留单一选择，不能把多选解释为最主要原因
A26: Q18 主要原因（单一回答） | B26: 希望更容易遇到相同IP的同好 | C26: =COUNTIFS(数据清洗!$E$2:$E$177,1,数据清洗!$CF$2:$CF$177,1,数据清洗!$CI$2:$CI$177,1) -> 5 | D26: =COUNTIFS(数据清洗!$E$2:$E$177,1,数据清洗!$CF$2:$CF$177,1) -> 49 | E26: =IF(D26=0,"",C26/D26) -> 0.10204082 | F26: Q18仅保留单一选择，不能把多选解释为最主要原因
A27: Q18 主要原因（单一回答） | B27: 希望有更多可参考的商品来源信息 | C27: =COUNTIFS(数据清洗!$E$2:$E$177,1,数据清洗!$CF$2:$CF$177,1,数据清洗!$CJ$2:$CJ$177,1) -> 6 | D27: =COUNTIFS(数据清洗!$E$2:$E$177,1,数据清洗!$CF$2:$CF$177,1) -> 49 | E27: =IF(D27=0,"",C27/D27) -> 0.12244898 | F27: Q18仅保留单一选择，不能把多选解释为最主要原因
A28: Q18 主要原因（单一回答） | B28: 我是否使用主要取决于交易保障规则 | C28: =COUNTIFS(数据清洗!$E$2:$E$177,1,数据清洗!$CF$2:$CF$177,1,数据清洗!$CK$2:$CK$177,1) -> 3 | D28: =COUNTIFS(数据清洗!$E$2:$E$177,1,数据清洗!$CF$2:$CF$177,1) -> 49 | E28: =IF(D28=0,"",C28/D28) -> 0.06122449 | F28: Q18仅保留单一选择，不能把多选解释为最主要原因
A29: Q18 主要原因（单一回答） | B29: 我是否使用主要取决于费用 | C29: =COUNTIFS(数据清洗!$E$2:$E$177,1,数据清洗!$CF$2:$CF$177,1,数据清洗!$CL$2:$CL$177,1) -> 2 | D29: =COUNTIFS(数据清洗!$E$2:$E$177,1,数据清洗!$CF$2:$CF$177,1) -> 49 | E29: =IF(D29=0,"",C29/D29) -> 0.040816327 | F29: Q18仅保留单一选择，不能把多选解释为最主要原因
A30: Q18 主要原因（单一回答） | B30: 我是否使用主要取决于隐私保护方式 | C30: =COUNTIFS(数据清洗!$E$2:$E$177,1,数据清洗!$CF$2:$CF$177,1,数据清洗!$CM$2:$CM$177,1) -> 3 | D30: =COUNTIFS(数据清洗!$E$2:$E$177,1,数据清洗!$CF$2:$CF$177,1) -> 49 | E30: =IF(D30=0,"",C30/D30) -> 0.06122449 | F30: Q18仅保留单一选择，不能把多选解释为最主要原因
A31: Q18 主要原因（单一回答） | B31: 现有渠道已经能满足我的需要 | C31: =COUNTIFS(数据清洗!$E$2:$E$177,1,数据清洗!$CF$2:$CF$177,1,数据清洗!$CN$2:$CN$177,1) -> 7 | D31: =COUNTIFS(数据清洗!$E$2:$E$177,1,数据清洗!$CF$2:$CF$177,1) -> 49 | E31: =IF(D31=0,"",C31/D31) -> 0.14285714 | F31: Q18仅保留单一选择，不能把多选解释为最主要原因
A32: Q18 主要原因（单一回答） | B32: 目前没有出售或交换需求 | C32: =COUNTIFS(数据清洗!$E$2:$E$177,1,数据清洗!$CF$2:$CF$177,1,数据清洗!$CO$2:$CO$177,1) -> 14 | D32: =COUNTIFS(数据清洗!$E$2:$E$177,1,数据清洗!$CF$2:$CF$177,1) -> 49 | E32: =IF(D32=0,"",C32/D32) -> 0.28571429 | F32: Q18仅保留单一选择，不能把多选解释为最主要原因
A33: Q18 主要原因（单一回答） | B33: 需要更多信息才能判断 | C33: =COUNTIFS(数据清洗!$E$2:$E$177,1,数据清洗!$CF$2:$CF$177,1,数据清洗!$CP$2:$CP$177,1) -> 0 | D33: =COUNTIFS(数据清洗!$E$2:$E$177,1,数据清洗!$CF$2:$CF$177,1) -> 49 | E33: =IF(D33=0,"",C33/D33) -> 0 | F33: Q18仅保留单一选择，不能把多选解释为最主要原因
A34: Q16 发布出售 | B34: 非常不可能 | C34: =COUNTIFS(数据清洗!$E$2:$E$177,1,数据清洗!$CQ$2:$CQ$177,"<>",数据清洗!$CQ$2:$CQ$177,1) -> 0 | D34: =COUNTIFS(数据清洗!$E$2:$E$177,1,数据清洗!$CQ$2:$CQ$177,"<>") -> 59 | E34: =IF(D34=0,"",C34/D34) -> 0 | F34: 发布周边出售信息；仅有效填写者，含不适用
A35: Q16 发布出售 | B35: 比较不可能 | C35: =COUNTIFS(数据清洗!$E$2:$E$177,1,数据清洗!$CQ$2:$CQ$177,"<>",数据清洗!$CQ$2:$CQ$177,2) -> 2 | D35: =COUNTIFS(数据清洗!$E$2:$E$177,1,数据清洗!$CQ$2:$CQ$177,"<>") -> 59 | E35: =IF(D35=0,"",C35/D35) -> 0.033898305 | F35: 发布周边出售信息；仅有效填写者，含不适用
A36: Q16 发布出售 | B36: 不确定或需更多规则 | C36: =COUNTIFS(数据清洗!$E$2:$E$177,1,数据清洗!$CQ$2:$CQ$177,"<>",数据清洗!$CQ$2:$CQ$177,3) -> 9 | D36: =COUNTIFS(数据清洗!$E$2:$E$177,1,数据清洗!$CQ$2:$CQ$177,"<>") -> 59 | E36: =IF(D36=0,"",C36/D36) -> 0.15254237 | F36: 发布周边出售信息；仅有效填写者，含不适用
A37: Q16 发布出售 | B37: 比较可能 | C37: =COUNTIFS(数据清洗!$E$2:$E$177,1,数据清洗!$CQ$2:$CQ$177,"<>",数据清洗!$CQ$2:$CQ$177,4) -> 25 | D37: =COUNTIFS(数据清洗!$E$2:$E$177,1,数据清洗!$CQ$2:$CQ$177,"<>") -> 59 | E37: =IF(D37=0,"",C37/D37) -> 0.42372881 | F37: 发布周边出售信息；仅有效填写者，含不适用
A38: Q16 发布出售 | B38: 非常可能 | C38: =COUNTIFS(数据清洗!$E$2:$E$177,1,数据清洗!$CQ$2:$CQ$177,"<>",数据清洗!$CQ$2:$CQ$177,5) -> 22 | D38: =COUNTIFS(数据清洗!$E$2:$E$177,1,数据清洗!$CQ$2:$CQ$177,"<>") -> 59 | E38: =IF(D38=0,"",C38/D38) -> 0.37288136 | F38: 发布周边出售信息；仅有效填写者，含不适用
A39: Q16 发布出售 | B39: 不适用 | C39: =COUNTIFS(数据清洗!$E$2:$E$177,1,数据清洗!$CQ$2:$CQ$177,"<>",数据清洗!$CQ$2:$CQ$177,97) -> 1 | D39: =COUNTIFS(数据清洗!$E$2:$E$177,1,数据清洗!$CQ$2:$CQ$177,"<>") -> 59 | E39: =IF(D39=0,"",C39/D39) -> 0.016949153 | F39: 发布周边出售信息；仅有效填写者，含不适用
A40: Q16 寻找交换 | B40: 非常不可能 | C40: =COUNTIFS(数据清洗!$E$2:$E$177,1,数据清洗!$CS$2:$CS$177,"<>",数据清洗!$CS$2:$CS$177,1) -> 3 | D40: =COUNTIFS(数据清洗!$E$2:$E$177,1,数据清洗!$CS$2:$CS$177,"<>") -> 63 | E40: =IF(D40=0,"",C40/D40) -> 0.047619048 | F40: 寻找周边交换对象；仅有效填写者，含不适用
A41: Q16 寻找交换 | B41: 比较不可能 | C41: =COUNTIFS(数据清洗!$E$2:$E$177,1,数据清洗!$CS$2:$CS$177,"<>",数据清洗!$CS$2:$CS$177,2) -> 5 | D41: =COUNTIFS(数据清洗!$E$2:$E$177,1,数据清洗!$CS$2:$CS$177,"<>") -> 63 | E41: =IF(D41=0,"",C41/D41) -> 0.079365079 | F41: 寻找周边交换对象；仅有效填写者，含不适用
A42: Q16 寻找交换 | B42: 不确定或需更多规则 | C42: =COUNTIFS(数据清洗!$E$2:$E$177,1,数据清洗!$CS$2:$CS$177,"<>",数据清洗!$CS$2:$CS$177,3) -> 14 | D42: =COUNTIFS(数据清洗!$E$2:$E$177,1,数据清洗!$CS$2:$CS$177,"<>") -> 63 | E42: =IF(D42=0,"",C42/D42) -> 0.22222222 | F42: 寻找周边交换对象；仅有效填写者，含不适用
A43: Q16 寻找交换 | B43: 比较可能 | C43: =COUNTIFS(数据清洗!$E$2:$E$177,1,数据清洗!$CS$2:$CS$177,"<>",数据清洗!$CS$2:$CS$177,4) -> 22 | D43: =COUNTIFS(数据清洗!$E$2:$E$177,1,数据清洗!$CS$2:$CS$177,"<>") -> 63 | E43: =IF(D43=0,"",C43/D43) -> 0.34920635 | F43: 寻找周边交换对象；仅有效填写者，含不适用
A44: Q16 寻找交换 | B44: 非常可能 | C44: =COUNTIFS(数据清洗!$E$2:$E$177,1,数据清洗!$CS$2:$CS$177,"<>",数据清洗!$CS$2:$CS$177,5) -> 19 | D44: =COUNTIFS(数据清洗!$E$2:$E$177,1,数据清洗!$CS$2:$CS$177,"<>") -> 63 | E44: =IF(D44=0,"",C44/D44) -> 0.3015873 | F44: 寻找周边交换对象；仅有效填写者，含不适用
A45: Q16 寻找交换 | B45: 不适用 | C45: =COUNTIFS(数据清洗!$E$2:$E$177,1,数据清洗!$CS$2:$CS$177,"<>",数据清洗!$CS$2:$CS$177,97) -> 0 | D45: =COUNTIFS(数据清洗!$E$2:$E$177,1,数据清洗!$CS$2:$CS$177,"<>") -> 63 | E45: =IF(D45=0,"",C45/D45) -> 0 | F45: 寻找周边交换对象；仅有效填写者，含不适用
A46: Q16 IP兴趣标签 | B46: 非常不可能 | C46: =COUNTIFS(数据清洗!$E$2:$E$177,1,数据清洗!$CU$2:$CU$177,"<>",数据清洗!$CU$2:$CU$177,1) -> 1 | D46: =COUNTIFS(数据清洗!$E$2:$E$177,1,数据清洗!$CU$2:$CU$177,"<>") -> 57 | E46: =IF(D46=0,"",C46/D46) -> 0.01754386 | F46: 为自己的周边展示IP兴趣标签，帮助他人发现；仅有效填写者，含不适用
A47: Q16 IP兴趣标签 | B47: 比较不可能 | C47: =COUNTIFS(数据清洗!$E$2:$E$177,1,数据清洗!$CU$2:$CU$177,"<>",数据清洗!$CU$2:$CU$177,2) -> 0 | D47: =COUNTIFS(数据清洗!$E$2:$E$177,1,数据清洗!$CU$2:$CU$177,"<>") -> 57 | E47: =IF(D47=0,"",C47/D47) -> 0 | F47: 为自己的周边展示IP兴趣标签，帮助他人发现；仅有效填写者，含不适用
A48: Q16 IP兴趣标签 | B48: 不确定或需更多规则 | C48: =COUNTIFS(数据清洗!$E$2:$E$177,1,数据清洗!$CU$2:$CU$177,"<>",数据清洗!$CU$2:$CU$177,3) -> 9 | D48: =COUNTIFS(数据清洗!$E$2:$E$177,1,数据清洗!$CU$2:$CU$177,"<>") -> 57 | E48: =IF(D48=0,"",C48/D48) -> 0.15789474 | F48: 为自己的周边展示IP兴趣标签，帮助他人发现；仅有效填写者，含不适用
A49: Q16 IP兴趣标签 | B49: 比较可能 | C49: =COUNTIFS(数据清洗!$E$2:$E$177,1,数据清洗!$CU$2:$CU$177,"<>",数据清洗!$CU$2:$CU$177,4) -> 27 | D49: =COUNTIFS(数据清洗!$E$2:$E$177,1,数据清洗!$CU$2:$CU$177,"<>") -> 57 | E49: =IF(D49=0,"",C49/D49) -> 0.47368421 | F49: 为自己的周边展示IP兴趣标签，帮助他人发现；仅有效填写者，含不适用
A50: Q16 IP兴趣标签 | B50: 非常可能 | C50: =COUNTIFS(数据清洗!$E$2:$E$177,1,数据清洗!$CU$2:$CU$177,"<>",数据清洗!$CU$2:$CU$177,5) -> 17 | D50: =COUNTIFS(数据清洗!$E$2:$E$177,1,数据清洗!$CU$2:$CU$177,"<>") -> 57 | E50: =IF(D50=0,"",C50/D50) -> 0.29824561 | F50: 为自己的周边展示IP兴趣标签，帮助他人发现；仅有效填写者，含不适用
A51: Q16 IP兴趣标签 | B51: 不适用 | C51: =COUNTIFS(数据清洗!$E$2:$E$177,1,数据清洗!$CU$2:$CU$177,"<>",数据清洗!$CU$2:$CU$177,97) -> 3 | D51: =COUNTIFS(数据清洗!$E$2:$E$177,1,数据清洗!$CU$2:$CU$177,"<>") -> 57 | E51: =IF(D51=0,"",C51/D51) -> 0.052631579 | F51: 为自己的周边展示IP兴趣标签，帮助他人发现；仅有效填写者，含不适用
A52: Q16 订单来源信息 | B52: 非常不可能 | C52: =COUNTIFS(数据清洗!$E$2:$E$177,1,数据清洗!$CW$2:$CW$177,"<>",数据清洗!$CW$2:$CW$177,1) -> 1 | D52: =COUNTIFS(数据清洗!$E$2:$E$177,1,数据清洗!$CW$2:$CW$177,"<>") -> 52 | E52: =IF(D52=0,"",C52/D52) -> 0.019230769 | F52: 为自己的周边展示可选择的会员购订单来源信息；仅有效填写者，含不适用
A53: Q16 订单来源信息 | B53: 比较不可能 | C53: =COUNTIFS(数据清洗!$E$2:$E$177,1,数据清洗!$CW$2:$CW$177,"<>",数据清洗!$CW$2:$CW$177,2) -> 9 | D53: =COUNTIFS(数据清洗!$E$2:$E$177,1,数据清洗!$CW$2:$CW$177,"<>") -> 52 | E53: =IF(D53=0,"",C53/D53) -> 0.17307692 | F53: 为自己的周边展示可选择的会员购订单来源信息；仅有效填写者，含不适用
A54: Q16 订单来源信息 | B54: 不确定或需更多规则 | C54: =COUNTIFS(数据清洗!$E$2:$E$177,1,数据清洗!$CW$2:$CW$177,"<>",数据清洗!$CW$2:$CW$177,3) -> 12 | D54: =COUNTIFS(数据清洗!$E$2:$E$177,1,数据清洗!$CW$2:$CW$177,"<>") -> 52 | E54: =IF(D54=0,"",C54/D54) -> 0.23076923 | F54: 为自己的周边展示可选择的会员购订单来源信息；仅有效填写者，含不适用
A55: Q16 订单来源信息 | B55: 比较可能 | C55: =COUNTIFS(数据清洗!$E$2:$E$177,1,数据清洗!$CW$2:$CW$177,"<>",数据清洗!$CW$2:$CW$177,4) -> 14 | D55: =COUNTIFS(数据清洗!$E$2:$E$177,1,数据清洗!$CW$2:$CW$177,"<>") -> 52 | E55: =IF(D55=0,"",C55/D55) -> 0.26923077 | F55: 为自己的周边展示可选择的会员购订单来源信息；仅有效填写者，含不适用
A56: Q16 订单来源信息 | B56: 非常可能 | C56: =COUNTIFS(数据清洗!$E$2:$E$177,1,数据清洗!$CW$2:$CW$177,"<>",数据清洗!$CW$2:$CW$177,5) -> 14 | D56: =COUNTIFS(数据清洗!$E$2:$E$177,1,数据清洗!$CW$2:$CW$177,"<>") -> 52 | E56: =IF(D56=0,"",C56/D56) -> 0.26923077 | F56: 为自己的周边展示可选择的会员购订单来源信息；仅有效填写者，含不适用
A57: Q16 订单来源信息 | B57: 不适用 | C57: =COUNTIFS(数据清洗!$E$2:$E$177,1,数据清洗!$CW$2:$CW$177,"<>",数据清洗!$CW$2:$CW$177,97) -> 2 | D57: =COUNTIFS(数据清洗!$E$2:$E$177,1,数据清洗!$CW$2:$CW$177,"<>") -> 52 | E57: =IF(D57=0,"",C57/D57) -> 0.038461538 | F57: 为自己的周边展示可选择的会员购订单来源信息；仅有效填写者，含不适用

Sheet 用户分群
A1: 用户分群
A2: 出售与交换为导出可确认的行为记录，不能解释为仅出售/仅交换用户。分母少于5不显示比例，少于30只作探索。
A5: 分组维度 | B5: 组别 | C5: 组人数 | D5: 有闲置 n | E5: 闲置 n/N | F5: 出售高意向 n | G5: 出售有效 N | H5: 出售意向 n/N | I5: 交换高意向 n | J5: 交换有效 N | K5: 交换意向 n/N
A6: 近12月购买 | B6: 买过 | C6: =COUNTIFS(数据清洗!$E$2:$E$177,1,数据清洗!$L$2:$L$177,1) -> 94 | D6: =COUNTIFS(数据清洗!$E$2:$E$177,1,数据清洗!$L$2:$L$177,1,数据清洗!$M$2:$M$177,"有") -> 46 | E6: =IF(C6<5,"",D6/C6) -> 0.4893617 | F6: =COUNTIFS(数据清洗!$E$2:$E$177,1,数据清洗!$L$2:$L$177,1,数据清洗!$CQ$2:$CQ$177,4)+COUNTIFS(数据清洗!$E$2:$E$177,1,数据清洗!$L$2:$L$177,1,数据清洗!$CQ$2:$CQ$177,5) -> 47 | G6: =COUNTIFS(数据清洗!$E$2:$E$177,1,数据清洗!$L$2:$L$177,1,数据清洗!$CQ$2:$CQ$177,"<>") -> 58 | H6: =IF(G6<5,"",F6/G6) -> 0.81034483 | I6: =COUNTIFS(数据清洗!$E$2:$E$177,1,数据清洗!$L$2:$L$177,1,数据清洗!$CS$2:$CS$177,4)+COUNTIFS(数据清洗!$E$2:$E$177,1,数据清洗!$L$2:$L$177,1,数据清洗!$CS$2:$CS$177,5) -> 40 | J6: =COUNTIFS(数据清洗!$E$2:$E$177,1,数据清洗!$L$2:$L$177,1,数据清洗!$CS$2:$CS$177,"<>") -> 62 | K6: =IF(J6<5,"",I6/J6) -> 0.64516129
A7: 近12月购买 | B7: 未购买 | C7: =COUNTIFS(数据清洗!$E$2:$E$177,1,数据清洗!$L$2:$L$177,0) -> 28 | D7: =COUNTIFS(数据清洗!$E$2:$E$177,1,数据清洗!$L$2:$L$177,0,数据清洗!$M$2:$M$177,"有") -> 12 | E7: =IF(C7<5,"",D7/C7) -> 0.42857143 | F7: =COUNTIFS(数据清洗!$E$2:$E$177,1,数据清洗!$L$2:$L$177,0,数据清洗!$CQ$2:$CQ$177,4)+COUNTIFS(数据清洗!$E$2:$E$177,1,数据清洗!$L$2:$L$177,0,数据清洗!$CQ$2:$CQ$177,5) -> 0 | G7: =COUNTIFS(数据清洗!$E$2:$E$177,1,数据清洗!$L$2:$L$177,0,数据清洗!$CQ$2:$CQ$177,"<>") -> 1 | H7: =IF(G7<5,"",F7/G7) | I7: =COUNTIFS(数据清洗!$E$2:$E$177,1,数据清洗!$L$2:$L$177,0,数据清洗!$CS$2:$CS$177,4)+COUNTIFS(数据清洗!$E$2:$E$177,1,数据清洗!$L$2:$L$177,0,数据清洗!$CS$2:$CS$177,5) -> 1 | J7: =COUNTIFS(数据清洗!$E$2:$E$177,1,数据清洗!$L$2:$L$177,0,数据清洗!$CS$2:$CS$177,"<>") -> 1 | K7: =IF(J7<5,"",I7/J7)
A8: 闲置经历 | B8: 有 | C8: =COUNTIFS(数据清洗!$E$2:$E$177,1,数据清洗!$M$2:$M$177,"有") -> 58 | D8: =COUNTIFS(数据清洗!$E$2:$E$177,1,数据清洗!$M$2:$M$177,"有",数据清洗!$M$2:$M$177,"有") -> 58 | E8: =IF(C8<5,"",D8/C8) -> 1 | F8: =COUNTIFS(数据清洗!$E$2:$E$177,1,数据清洗!$M$2:$M$177,"有",数据清洗!$CQ$2:$CQ$177,4)+COUNTIFS(数据清洗!$E$2:$E$177,1,数据清洗!$M$2:$M$177,"有",数据清洗!$CQ$2:$CQ$177,5) -> 27 | G8: =COUNTIFS(数据清洗!$E$2:$E$177,1,数据清洗!$M$2:$M$177,"有",数据清洗!$CQ$2:$CQ$177,"<>") -> 33 | H8: =IF(G8<5,"",F8/G8) -> 0.81818182 | I8: =COUNTIFS(数据清洗!$E$2:$E$177,1,数据清洗!$M$2:$M$177,"有",数据清洗!$CS$2:$CS$177,4)+COUNTIFS(数据清洗!$E$2:$E$177,1,数据清洗!$M$2:$M$177,"有",数据清洗!$CS$2:$CS$177,5) -> 22 | J8: =COUNTIFS(数据清洗!$E$2:$E$177,1,数据清洗!$M$2:$M$177,"有",数据清洗!$CS$2:$CS$177,"<>") -> 33 | K8: =IF(J8<5,"",I8/J8) -> 0.66666667
A9: 闲置经历 | B9: 没有 | C9: =COUNTIFS(数据清洗!$E$2:$E$177,1,数据清洗!$M$2:$M$177,"没有") -> 43 | D9: =COUNTIFS(数据清洗!$E$2:$E$177,1,数据清洗!$M$2:$M$177,"没有",数据清洗!$M$2:$M$177,"有") -> 0 | E9: =IF(C9<5,"",D9/C9) -> 0 | F9: =COUNTIFS(数据清洗!$E$2:$E$177,1,数据清洗!$M$2:$M$177,"没有",数据清洗!$CQ$2:$CQ$177,4)+COUNTIFS(数据清洗!$E$2:$E$177,1,数据清洗!$M$2:$M$177,"没有",数据清洗!$CQ$2:$CQ$177,5) -> 18 | G9: =COUNTIFS(数据清洗!$E$2:$E$177,1,数据清洗!$M$2:$M$177,"没有",数据清洗!$CQ$2:$CQ$177,"<>") -> 22 | H9: =IF(G9<5,"",F9/G9) -> 0.81818182 | I9: =COUNTIFS(数据清洗!$E$2:$E$177,1,数据清洗!$M$2:$M$177,"没有",数据清洗!$CS$2:$CS$177,4)+COUNTIFS(数据清洗!$E$2:$E$177,1,数据清洗!$M$2:$M$177,"没有",数据清洗!$CS$2:$CS$177,5) -> 16 | J9: =COUNTIFS(数据清洗!$E$2:$E$177,1,数据清洗!$M$2:$M$177,"没有",数据清洗!$CS$2:$CS$177,"<>") -> 25 | K9: =IF(J9<5,"",I9/J9) -> 0.64
A10: 闲置经历 | B10: 不确定 | C10: =COUNTIFS(数据清洗!$E$2:$E$177,1,数据清洗!$M$2:$M$177,"不确定") -> 21 | D10: =COUNTIFS(数据清洗!$E$2:$E$177,1,数据清洗!$M$2:$M$177,"不确定",数据清洗!$M$2:$M$177,"有") -> 0 | E10: =IF(C10<5,"",D10/C10) -> 0 | F10: =COUNTIFS(数据清洗!$E$2:$E$177,1,数据清洗!$M$2:$M$177,"不确定",数据清洗!$CQ$2:$CQ$177,4)+COUNTIFS(数据清洗!$E$2:$E$177,1,数据清洗!$M$2:$M$177,"不确定",数据清洗!$CQ$2:$CQ$177,5) -> 2 | G10: =COUNTIFS(数据清洗!$E$2:$E$177,1,数据清洗!$M$2:$M$177,"不确定",数据清洗!$CQ$2:$CQ$177,"<>") -> 4 | H10: =IF(G10<5,"",F10/G10) | I10: =COUNTIFS(数据清洗!$E$2:$E$177,1,数据清洗!$M$2:$M$177,"不确定",数据清洗!$CS$2:$CS$177,4)+COUNTIFS(数据清洗!$E$2:$E$177,1,数据清洗!$M$2:$M$177,"不确定",数据清洗!$CS$2:$CS$177,5) -> 3 | J10: =COUNTIFS(数据清洗!$E$2:$E$177,1,数据清洗!$M$2:$M$177,"不确定",数据清洗!$CS$2:$CS$177,"<>") -> 5 | K10: =IF(J10<5,"",I10/J10) -> 0.6
A11: B站频率 | B11: 几乎每天 | C11: =COUNTIFS(数据清洗!$E$2:$E$177,1,数据清洗!$J$2:$J$177,"几乎每天") -> 39 | D11: =COUNTIFS(数据清洗!$E$2:$E$177,1,数据清洗!$J$2:$J$177,"几乎每天",数据清洗!$M$2:$M$177,"有") -> 17 | E11: =IF(C11<5,"",D11/C11) -> 0.43589744 | F11: =COUNTIFS(数据清洗!$E$2:$E$177,1,数据清洗!$J$2:$J$177,"几乎每天",数据清洗!$CQ$2:$CQ$177,4)+COUNTIFS(数据清洗!$E$2:$E$177,1,数据清洗!$J$2:$J$177,"几乎每天",数据清洗!$CQ$2:$CQ$177,5) -> 13 | G11: =COUNTIFS(数据清洗!$E$2:$E$177,1,数据清洗!$J$2:$J$177,"几乎每天",数据清洗!$CQ$2:$CQ$177,"<>") -> 17 | H11: =IF(G11<5,"",F11/G11) -> 0.76470588 | I11: =COUNTIFS(数据清洗!$E$2:$E$177,1,数据清洗!$J$2:$J$177,"几乎每天",数据清洗!$CS$2:$CS$177,4)+COUNTIFS(数据清洗!$E$2:$E$177,1,数据清洗!$J$2:$J$177,"几乎每天",数据清洗!$CS$2:$CS$177,5) -> 11 | J11: =COUNTIFS(数据清洗!$E$2:$E$177,1,数据清洗!$J$2:$J$177,"几乎每天",数据清洗!$CS$2:$CS$177,"<>") -> 18 | K11: =IF(J11<5,"",I11/J11) -> 0.61111111
A12: B站频率 | B12: 每周3–6天 | C12: =COUNTIFS(数据清洗!$E$2:$E$177,1,数据清洗!$J$2:$J$177,"每周3–6天") -> 34 | D12: =COUNTIFS(数据清洗!$E$2:$E$177,1,数据清洗!$J$2:$J$177,"每周3–6天",数据清洗!$M$2:$M$177,"有") -> 17 | E12: =IF(C12<5,"",D12/C12) -> 0.5 | F12: =COUNTIFS(数据清洗!$E$2:$E$177,1,数据清洗!$J$2:$J$177,"每周3–6天",数据清洗!$CQ$2:$CQ$177,4)+COUNTIFS(数据清洗!$E$2:$E$177,1,数据清洗!$J$2:$J$177,"每周3–6天",数据清洗!$CQ$2:$CQ$177,5) -> 11 | G12: =COUNTIFS(数据清洗!$E$2:$E$177,1,数据清洗!$J$2:$J$177,"每周3–6天",数据清洗!$CQ$2:$CQ$177,"<>") -> 14 | H12: =IF(G12<5,"",F12/G12) -> 0.78571429 | I12: =COUNTIFS(数据清洗!$E$2:$E$177,1,数据清洗!$J$2:$J$177,"每周3–6天",数据清洗!$CS$2:$CS$177,4)+COUNTIFS(数据清洗!$E$2:$E$177,1,数据清洗!$J$2:$J$177,"每周3–6天",数据清洗!$CS$2:$CS$177,5) -> 9 | J12: =COUNTIFS(数据清洗!$E$2:$E$177,1,数据清洗!$J$2:$J$177,"每周3–6天",数据清洗!$CS$2:$CS$177,"<>") -> 14 | K12: =IF(J12<5,"",I12/J12) -> 0.64285714
A13: B站频率 | B13: 每周1–2天 | C13: =COUNTIFS(数据清洗!$E$2:$E$177,1,数据清洗!$J$2:$J$177,"每周1–2天") -> 29 | D13: =COUNTIFS(数据清洗!$E$2:$E$177,1,数据清洗!$J$2:$J$177,"每周1–2天",数据清洗!$M$2:$M$177,"有") -> 17 | E13: =IF(C13<5,"",D13/C13) -> 0.5862069 | F13: =COUNTIFS(数据清洗!$E$2:$E$177,1,数据清洗!$J$2:$J$177,"每周1–2天",数据清洗!$CQ$2:$CQ$177,4)+COUNTIFS(数据清洗!$E$2:$E$177,1,数据清洗!$J$2:$J$177,"每周1–2天",数据清洗!$CQ$2:$CQ$177,5) -> 16 | G13: =COUNTIFS(数据清洗!$E$2:$E$177,1,数据清洗!$J$2:$J$177,"每周1–2天",数据清洗!$CQ$2:$CQ$177,"<>") -> 20 | H13: =IF(G13<5,"",F13/G13) -> 0.8 | I13: =COUNTIFS(数据清洗!$E$2:$E$177,1,数据清洗!$J$2:$J$177,"每周1–2天",数据清洗!$CS$2:$CS$177,4)+COUNTIFS(数据清洗!$E$2:$E$177,1,数据清洗!$J$2:$J$177,"每周1–2天",数据清洗!$CS$2:$CS$177,5) -> 15 | J13: =COUNTIFS(数据清洗!$E$2:$E$177,1,数据清洗!$J$2:$J$177,"每周1–2天",数据清洗!$CS$2:$CS$177,"<>") -> 23 | K13: =IF(J13<5,"",I13/J13) -> 0.65217391
A14: B站频率 | B14: 少于每周1天 | C14: =COUNTIFS(数据清洗!$E$2:$E$177,1,数据清洗!$J$2:$J$177,"少于每周1天") -> 13 | D14: =COUNTIFS(数据清洗!$E$2:$E$177,1,数据清洗!$J$2:$J$177,"少于每周1天",数据清洗!$M$2:$M$177,"有") -> 5 | E14: =IF(C14<5,"",D14/C14) -> 0.38461538 | F14: =COUNTIFS(数据清洗!$E$2:$E$177,1,数据清洗!$J$2:$J$177,"少于每周1天",数据清洗!$CQ$2:$CQ$177,4)+COUNTIFS(数据清洗!$E$2:$E$177,1,数据清洗!$J$2:$J$177,"少于每周1天",数据清洗!$CQ$2:$CQ$177,5) -> 6 | G14: =COUNTIFS(数据清洗!$E$2:$E$177,1,数据清洗!$J$2:$J$177,"少于每周1天",数据清洗!$CQ$2:$CQ$177,"<>") -> 7 | H14: =IF(G14<5,"",F14/G14) -> 0.85714286 | I14: =COUNTIFS(数据清洗!$E$2:$E$177,1,数据清洗!$J$2:$J$177,"少于每周1天",数据清洗!$CS$2:$CS$177,4)+COUNTIFS(数据清洗!$E$2:$E$177,1,数据清洗!$J$2:$J$177,"少于每周1天",数据清洗!$CS$2:$CS$177,5) -> 6 | J14: =COUNTIFS(数据清洗!$E$2:$E$177,1,数据清洗!$J$2:$J$177,"少于每周1天",数据清洗!$CS$2:$CS$177,"<>") -> 7 | K14: =IF(J14<5,"",I14/J14) -> 0.85714286
A15: B站频率 | B15: 过去3个月没有使用过 | C15: =COUNTIFS(数据清洗!$E$2:$E$177,1,数据清洗!$J$2:$J$177,"过去3个月没有使用过") -> 2 | D15: =COUNTIFS(数据清洗!$E$2:$E$177,1,数据清洗!$J$2:$J$177,"过去3个月没有使用过",数据清洗!$M$2:$M$177,"有") -> 0 | E15: =IF(C15<5,"",D15/C15) | F15: =COUNTIFS(数据清洗!$E$2:$E$177,1,数据清洗!$J$2:$J$177,"过去3个月没有使用过",数据清洗!$CQ$2:$CQ$177,4)+COUNTIFS(数据清洗!$E$2:$E$177,1,数据清洗!$J$2:$J$177,"过去3个月没有使用过",数据清洗!$CQ$2:$CQ$177,5) -> 0 | G15: =COUNTIFS(数据清洗!$E$2:$E$177,1,数据清洗!$J$2:$J$177,"过去3个月没有使用过",数据清洗!$CQ$2:$CQ$177,"<>") -> 0 | H15: =IF(G15<5,"",F15/G15) | I15: =COUNTIFS(数据清洗!$E$2:$E$177,1,数据清洗!$J$2:$J$177,"过去3个月没有使用过",数据清洗!$CS$2:$CS$177,4)+COUNTIFS(数据清洗!$E$2:$E$177,1,数据清洗!$J$2:$J$177,"过去3个月没有使用过",数据清洗!$CS$2:$CS$177,5) -> 0 | J15: =COUNTIFS(数据清洗!$E$2:$E$177,1,数据清洗!$J$2:$J$177,"过去3个月没有使用过",数据清洗!$CS$2:$CS$177,"<>") -> 0 | K15: =IF(J15<5,"",I15/J15)
A16: B站频率 | B16: 从未使用过B站 | C16: =COUNTIFS(数据清洗!$E$2:$E$177,1,数据清洗!$J$2:$J$177,"从未使用过B站") -> 5 | D16: =COUNTIFS(数据清洗!$E$2:$E$177,1,数据清洗!$J$2:$J$177,"从未使用过B站",数据清洗!$M$2:$M$177,"有") -> 2 | E16: =IF(C16<5,"",D16/C16) -> 0.4 | F16: =COUNTIFS(数据清洗!$E$2:$E$177,1,数据清洗!$J$2:$J$177,"从未使用过B站",数据清洗!$CQ$2:$CQ$177,4)+COUNTIFS(数据清洗!$E$2:$E$177,1,数据清洗!$J$2:$J$177,"从未使用过B站",数据清洗!$CQ$2:$CQ$177,5) -> 1 | G16: =COUNTIFS(数据清洗!$E$2:$E$177,1,数据清洗!$J$2:$J$177,"从未使用过B站",数据清洗!$CQ$2:$CQ$177,"<>") -> 1 | H16: =IF(G16<5,"",F16/G16) | I16: =COUNTIFS(数据清洗!$E$2:$E$177,1,数据清洗!$J$2:$J$177,"从未使用过B站",数据清洗!$CS$2:$CS$177,4)+COUNTIFS(数据清洗!$E$2:$E$177,1,数据清洗!$J$2:$J$177,"从未使用过B站",数据清洗!$CS$2:$CS$177,5) -> 0 | J16: =COUNTIFS(数据清洗!$E$2:$E$177,1,数据清洗!$J$2:$J$177,"从未使用过B站",数据清洗!$CS$2:$CS$177,"<>") -> 1 | K16: =IF(J16<5,"",I16/J16)
A17: 交易记录 | B17: 出售尝试记录 | C17: =COUNTIFS(数据清洗!$E$2:$E$177,1,数据清洗!$X$2:$X$177,"出售尝试记录") -> 28 | D17: =COUNTIFS(数据清洗!$E$2:$E$177,1,数据清洗!$X$2:$X$177,"出售尝试记录",数据清洗!$M$2:$M$177,"有") -> 20 | E17: =IF(C17<5,"",D17/C17) -> 0.71428571 | F17: =COUNTIFS(数据清洗!$E$2:$E$177,1,数据清洗!$X$2:$X$177,"出售尝试记录",数据清洗!$CQ$2:$CQ$177,4)+COUNTIFS(数据清洗!$E$2:$E$177,1,数据清洗!$X$2:$X$177,"出售尝试记录",数据清洗!$CQ$2:$CQ$177,5) -> 21 | G17: =COUNTIFS(数据清洗!$E$2:$E$177,1,数据清洗!$X$2:$X$177,"出售尝试记录",数据清洗!$CQ$2:$CQ$177,"<>") -> 23 | H17: =IF(G17<5,"",F17/G17) -> 0.91304348 | I17: =COUNTIFS(数据清洗!$E$2:$E$177,1,数据清洗!$X$2:$X$177,"出售尝试记录",数据清洗!$CS$2:$CS$177,4)+COUNTIFS(数据清洗!$E$2:$E$177,1,数据清洗!$X$2:$X$177,"出售尝试记录",数据清洗!$CS$2:$CS$177,5) -> 11 | J17: =COUNTIFS(数据清洗!$E$2:$E$177,1,数据清洗!$X$2:$X$177,"出售尝试记录",数据清洗!$CS$2:$CS$177,"<>") -> 22 | K17: =IF(J17<5,"",I17/J17) -> 0.5
A18: 交易记录 | B18: 交换尝试记录 | C18: =COUNTIFS(数据清洗!$E$2:$E$177,1,数据清洗!$X$2:$X$177,"交换尝试记录") -> 40 | D18: =COUNTIFS(数据清洗!$E$2:$E$177,1,数据清洗!$X$2:$X$177,"交换尝试记录",数据清洗!$M$2:$M$177,"有") -> 17 | E18: =IF(C18<5,"",D18/C18) -> 0.425 | F18: =COUNTIFS(数据清洗!$E$2:$E$177,1,数据清洗!$X$2:$X$177,"交换尝试记录",数据清洗!$CQ$2:$CQ$177,4)+COUNTIFS(数据清洗!$E$2:$E$177,1,数据清洗!$X$2:$X$177,"交换尝试记录",数据清洗!$CQ$2:$CQ$177,5) -> 23 | G18: =COUNTIFS(数据清洗!$E$2:$E$177,1,数据清洗!$X$2:$X$177,"交换尝试记录",数据清洗!$CQ$2:$CQ$177,"<>") -> 31 | H18: =IF(G18<5,"",F18/G18) -> 0.74193548 | I18: =COUNTIFS(数据清洗!$E$2:$E$177,1,数据清洗!$X$2:$X$177,"交换尝试记录",数据清洗!$CS$2:$CS$177,4)+COUNTIFS(数据清洗!$E$2:$E$177,1,数据清洗!$X$2:$X$177,"交换尝试记录",数据清洗!$CS$2:$CS$177,5) -> 27 | J18: =COUNTIFS(数据清洗!$E$2:$E$177,1,数据清洗!$X$2:$X$177,"交换尝试记录",数据清洗!$CS$2:$CS$177,"<>") -> 36 | K18: =IF(J18<5,"",I18/J18) -> 0.75
A19: 交易记录 | B19: 明确均未尝试 | C19: =COUNTIFS(数据清洗!$E$2:$E$177,1,数据清洗!$X$2:$X$177,"明确均未尝试") -> 41 | D19: =COUNTIFS(数据清洗!$E$2:$E$177,1,数据清洗!$X$2:$X$177,"明确均未尝试",数据清洗!$M$2:$M$177,"有") -> 9 | E19: =IF(C19<5,"",D19/C19) -> 0.2195122 | F19: =COUNTIFS(数据清洗!$E$2:$E$177,1,数据清洗!$X$2:$X$177,"明确均未尝试",数据清洗!$CQ$2:$CQ$177,4)+COUNTIFS(数据清洗!$E$2:$E$177,1,数据清洗!$X$2:$X$177,"明确均未尝试",数据清洗!$CQ$2:$CQ$177,5) -> 1 | G19: =COUNTIFS(数据清洗!$E$2:$E$177,1,数据清洗!$X$2:$X$177,"明确均未尝试",数据清洗!$CQ$2:$CQ$177,"<>") -> 2 | H19: =IF(G19<5,"",F19/G19) | I19: =COUNTIFS(数据清洗!$E$2:$E$177,1,数据清洗!$X$2:$X$177,"明确均未尝试",数据清洗!$CS$2:$CS$177,4)+COUNTIFS(数据清洗!$E$2:$E$177,1,数据清洗!$X$2:$X$177,"明确均未尝试",数据清洗!$CS$2:$CS$177,5) -> 1 | J19: =COUNTIFS(数据清洗!$E$2:$E$177,1,数据清洗!$X$2:$X$177,"明确均未尝试",数据清洗!$CS$2:$CS$177,"<>") -> 2 | K19: =IF(J19<5,"",I19/J19)
A20: 交易记录 | B20: 无法判断 | C20: =COUNTIFS(数据清洗!$E$2:$E$177,1,数据清洗!$X$2:$X$177,"无法判断") -> 13 | D20: =COUNTIFS(数据清洗!$E$2:$E$177,1,数据清洗!$X$2:$X$177,"无法判断",数据清洗!$M$2:$M$177,"有") -> 12 | E20: =IF(C20<5,"",D20/C20) -> 0.92307692 | F20: =COUNTIFS(数据清洗!$E$2:$E$177,1,数据清洗!$X$2:$X$177,"无法判断",数据清洗!$CQ$2:$CQ$177,4)+COUNTIFS(数据清洗!$E$2:$E$177,1,数据清洗!$X$2:$X$177,"无法判断",数据清洗!$CQ$2:$CQ$177,5) -> 2 | G20: =COUNTIFS(数据清洗!$E$2:$E$177,1,数据清洗!$X$2:$X$177,"无法判断",数据清洗!$CQ$2:$CQ$177,"<>") -> 3 | H20: =IF(G20<5,"",F20/G20) | I20: =COUNTIFS(数据清洗!$E$2:$E$177,1,数据清洗!$X$2:$X$177,"无法判断",数据清洗!$CS$2:$CS$177,4)+COUNTIFS(数据清洗!$E$2:$E$177,1,数据清洗!$X$2:$X$177,"无法判断",数据清洗!$CS$2:$CS$177,5) -> 2 | J20: =COUNTIFS(数据清洗!$E$2:$E$177,1,数据清洗!$X$2:$X$177,"无法判断",数据清洗!$CS$2:$CS$177,"<>") -> 3 | K20: =IF(J20<5,"",I20/J20)
A25: 敏感性指标 | B25: 主分析 n | C25: 主分析 N | D25: 主分析比例 | E25: 含异常群 n | F25: 筛选后 N | G25: 对照比例 | H25: 差值 百分点
A26: 近12月买过周边 | B26: =COUNTIFS(数据清洗!$E$2:$E$177,1,数据清洗!$L$2:$L$177,1) -> 94 | C26: =COUNTIFS(数据清洗!$E$2:$E$177,1) -> 122 | D26: =B26/C26 -> 0.7704918 | E26: =COUNTIFS(数据清洗!$D$2:$D$177,1,数据清洗!$L$2:$L$177,1) -> 115 | F26: =COUNTIFS(数据清洗!$D$2:$D$177,1) -> 175 | G26: =E26/F26 -> 0.65714286 | H26: =(D26-G26)*100 -> 11.334895
A27: 有闲置 | B27: =COUNTIFS(数据清洗!$E$2:$E$177,1,数据清洗!$M$2:$M$177,"有") -> 58 | C27: =COUNTIFS(数据清洗!$E$2:$E$177,1) -> 122 | D27: =B27/C27 -> 0.47540984 | E27: =COUNTIFS(数据清洗!$D$2:$D$177,1,数据清洗!$M$2:$M$177,"有") -> 75 | F27: =COUNTIFS(数据清洗!$D$2:$D$177,1) -> 175 | G27: =E27/F27 -> 0.42857143 | H27: =(D27-G27)*100 -> 4.6838407
A29: 对照含53份重复文本群，只检查清洗选择对结论的影响，不作为推荐结论。购买占比差异11.3个百分点；闲置占比差异4.7个百分点。

Sheet 数据清洗
A1: id | B1: source_row | C1: status | D1: eligible | E1: main | F1: duration | G1: age | H1: gender | I1: education | J1: frequency | K1: purchase | L1: purchased | M1: idle | N1: experience | O1: q11_conflict | P1: flags | Q1: repeat_text | R1: same_ip | S1: intent_missing | T1: q18_multi | U1: q14_row_error | V1: q12_type | W1: q12_freq | X1: trade_group | Y1: type_base | Z1: type_1 | AA1: type_2 | AB1: type_3 | AC1: type_4 | AD1: type_5 | AE1: type_6 | AF1: type_7 | AG1: buy_base | AH1: buy_1 | AI1: buy_2 | AJ1: buy_3 | AK1: buy_4 | AL1: buy_5 | AM1: buy_6 | AN1: buy_7 | AO1: buy_8 | AP1: buy_9 | AQ1: disposal_base | AR1: disposal_1 | AS1: disposal_2 | AT1: disposal_3 | AU1: disposal_4 | AV1: disposal_5 | AW1: disposal_6 | AX1: channel_base | AY1: channel_1 | AZ1: channel_2 | BA1: channel_3 | BB1: channel_4 | BC1: channel_5 | BD1: channel_6 | BE1: channel_7 | BF1: channel_8 | BG1: barrier_base | BH1: barrier_1 | BI1: barrier_2 | BJ1: barrier_3 | BK1: barrier_4 | BL1: barrier_5 | BM1: barrier_6 | BN1: barrier_7 | BO1: barrier_8 | BP1: barrier_9 | BQ1: barrier_10 | BR1: barrier_11 | BS1: barrier_12 | BT1: barrier_13 | BU1: concern_base | BV1: concern_1 | BW1: concern_2 | BX1: concern_3 | BY1: concern_4 | BZ1: concern_5 | CA1: concern_6 | CB1: concern_7 | CC1: concern_8 | CD1: concern_9 | CE1: concern_10 | CF1: reason_base | CG1: reason_1 | CH1: reason_2 | CI1: reason_3 | CJ1: reason_4 | CK1: reason_5 | CL1: reason_6 | CM1: reason_7 | CN1: reason_8 | CO1: reason_9 | CP1: reason_10 | CQ1: intent1 | CR1: intent_raw1 | CS1: intent2 | CT1: intent_raw2 | CU1: intent3 | CV1: intent_raw3 | CW1: intent4 | CX1: intent_raw4
A2: 1 | B2: 2 | C2: 主分析 | D2: 1 | E2: 1 | F2: 982 | G2: 30–39岁 | H2: 女 | I2: 硕士研究生及以上 | J2: 从未使用过B站 | K2: 1–2次 | L2: 1 | M2: 有 | N2: 可确认尝试 | O2: 0 | P2: Q14行无法可靠匹配；Q18最主要原因多选 | Q2: 0 | R2: 0 | S2: 0 | T2: 1 | U2: 1 | V2: 与他人交换周边 | W2: 完成1–2次 | X2: 交换尝试记录 | Y2: 1 | Z2: 1 | AA2: 0 | AB2: 0 | AC2: 1 | AD2: 1 | AE2: 1 | AF2: 0 | AG2: 1 | AH2: 0 | AI2: 0 | AJ2: 0 | AK2: 1 | AL2: 0 | AM2: 1 | AN2: 0 | AO2: 0 | AP2: 1 | AQ2: 1 | AR2: 0 | AS2: 0 | AT2: 0 | AU2: 0 | AV2: 0 | AW2: 1 | AX2: 1 | AY2: 0 | AZ2: 0 | BA2: 0 | BB2: 0 | BC2: 0 | BD2: 1 | BE2: 0 | BF2: 1 | BG2: 0 | BU2: 1 | BV2: 0 | BW2: 1 | BX2: 1 | BY2: 0 | BZ2: 0 | CA2: 0 | CB2: 1 | CC2: 1 | CD2: 1 | CE2: 0 | CF2: 0 | CQ2: 5 | CR2: 非常可能 | CS2: 3 | CT2: 不确定 | CU2: 4 | CV2: 比较可能 | CW2: 5 | CX2: 非常可能
A3: 2 | B3: 3 | C3: 主分析 | D3: 1 | E3: 1 | F3: 733 | G3: 23–29岁 | H3: 男 | I3: 本科 | J3: 每周1–2天 | K3: 3–5次 | L3: 1 | M3: 有 | N3: 可确认尝试 | O3: 0 | P3: Q18最主要原因多选；Q16第3项用词歧义；Q16第4项用词歧义 | Q3: 0 | R3: 0 | S3: 0 | T3: 1 | U3: 0 | V3: 出售个人周边 | W3: 完成3–5次 | X3: 出售尝试记录 | Y3: 1 | Z3: 0 | AA3: 0 | AB3: 0 | AC3: 1 | AD3: 1 | AE3: 0 | AF3: 0 | AG3: 1 | AH3: 1 | AI3: 1 | AJ3: 0 | AK3: 0 | AL3: 0 | AM3: 0 | AN3: 0 | AO3: 0 | AP3: 1 | AQ3: 1 | AR3: 1 | AS3: 0 | AT3: 1 | AU3: 1 | AV3: 0 | AW3: 0 | AX3: 1 | AY3: 1 | AZ3: 1 | BA3: 0 | BB3: 0 | BC3: 0 | BD3: 0 | BE3: 0 | BF3: 1 | BG3: 1 | BH3: 0 | BI3: 0 | BJ3: 1 | BK3: 0 | BL3: 0 | BM3: 0 | BN3: 0 | BO3: 1 | BP3: 0 | BQ3: 1 | BR3: 1 | BS3: 0 | BT3: 1 | BU3: 1 | BV3: 1 | BW3: 1 | BX3: 1 | BY3: 0 | BZ3: 0 | CA3: 0 | CB3: 0 | CC3: 1 | CD3: 1 | CE3: 0 | CF3: 0 | CQ3: 3 | CR3: 需要了解 | CS3: 3 | CT3: 需要了解 | CV3: 可能 | CX3: 可能
A4: 3 | B4: 4 | C4: 主分析 | D4: 1 | E4: 1 | F4: 830 | G4: 30–39岁 | H4: 男 | I4: 本科 | J4: 几乎每天 | K4: 3–5次 | L4: 1 | M4: 没有 | N4: 无法判断 | O4: 0 | P4: Q14行无法可靠匹配 | Q4: 0 | R4: 0 | S4: 0 | T4: 0 | U4: 1 | V4: 与他人交换周边 | W4: 没有尝试过 | X4: 无法判断 | Y4: 1 | Z4: 1 | AA4: 0 | AB4: 0 | AC4: 0 | AD4: 1 | AE4: 0 | AF4: 0 | AG4: 1 | AH4: 1 | AI4: 0 | AJ4: 0 | AK4: 0 | AL4: 0 | AM4: 0 | AN4: 0 | AO4: 0 | AP4: 0 | AQ4: 0 | AX4: 0 | BG4: 0 | BU4: 1 | BV4: 0 | BW4: 0 | BX4: 1 | BY4: 0 | BZ4: 0 | CA4: 1 | CB4: 0 | CC4: 0 | CD4: 0 | CE4: 0 | CF4: 1 | CG4: 0 | CH4: 0 | CI4: 0 | CJ4: 1 | CK4: 0 | CL4: 0 | CM4: 0 | CN4: 0 | CO4: 0 | CP4: 0 | CQ4: 4 | CR4: 比较可能 | CS4: 5 | CT4: 非常可能 | CU4: 3 | CV4: 不确定 | CW4: 2 | CX4: 比较不可能
A5: 4 | B5: 5 | C5: 主分析 | D5: 1 | E5: 1 | F5: 330 | G5: 30–39岁 | H5: 男 | I5: 本科 | J5: 每周1–2天 | K5: 1–2次 | L5: 1 | M5: 没有 | N5: 可确认尝试 | O5: 0 | P5: Q18最主要原因多选 | Q5: 0 | R5: 0 | S5: 0 | T5: 1 | U5: 0 | V5: 与他人交换周边 | W5: 完成6次及以上 | X5: 交换尝试记录 | Y5: 1 | Z5: 1 | AA5: 0 | AB5: 1 | AC5: 0 | AD5: 0 | AE5: 1 | AF5: 0 | AG5: 1 | AH5: 0 | AI5: 0 | AJ5: 1 | AK5: 1 | AL5: 0 | AM5: 1 | AN5: 0 | AO5: 0 | AP5: 0 | AQ5: 0 | AX5: 1 | AY5: 1 | AZ5: 0 | BA5: 0 | BB5: 0 | BC5: 1 | BD5: 0 | BE5: 0 | BF5: 0 | BG5: 1 | BH5: 0 | BI5: 0 | BJ5: 0 | BK5: 0 | BL5: 0 | BM5: 0 | BN5: 0 | BO5: 0 | BP5: 1 | BQ5: 1 | BR5: 0 | BS5: 0 | BT5: 1 | BU5: 1 | BV5: 1 | BW5: 1 | BX5: 0 | BY5: 0 | BZ5: 0 | CA5: 0 | CB5: 0 | CC5: 0 | CD5: 0 | CE5: 0 | CF5: 0 | CS5: 4 | CT5: 比较可能 | CU5: 4 | CV5: 比较可能
A6: 5 | B6: 6 | C6: 主分析 | D6: 1 | E6: 1 | F6: 272 | G6: 30–39岁 | H6: 男 | I6: 本科 | J6: 几乎每天 | K6: 0次 | L6: 0 | M6: 没有 | N6: 可确认尝试 | O6: 0 | P6: Q14行无法可靠匹配；Q16第4项用词歧义 | Q6: 0 | R6: 0 | S6: 0 | T6: 0 | U6: 1 | V6: 与他人交换周边 | W6: 完成1–2次 | X6: 交换尝试记录 | Y6: 0 | AG6: 0 | AQ6: 0 | AX6: 1 | AY6: 0 | AZ6: 1 | BA6: 0 | BB6: 0 | BC6: 0 | BD6: 0 | BE6: 0 | BF6: 0 | BG6: 0 | BU6: 1 | BV6: 0 | BW6: 1 | BX6: 0 | BY6: 0 | BZ6: 0 | CA6: 0 | CB6: 0 | CC6: 1 | CD6: 0 | CE6: 0 | CF6: 1 | CG6: 0 | CH6: 0 | CI6: 0 | CJ6: 0 | CK6: 0 | CL6: 0 | CM6: 1 | CN6: 0 | CO6: 0 | CP6: 0 | CQ6: 3 | CR6: 不确定 | CS6: 4 | CT6: 比较可能 | CU6: 3 | CV6: 不确定 | CX6: 可能
A7: 6 | B7: 7 | C7: 主分析 | D7: 1 | E7: 1 | F7: 697 | G7: 23–29岁 | H7: 女 | I7: 本科 | J7: 每周1–2天 | K7: 3–5次 | L7: 1 | M7: 有 | N7: 可确认尝试 | O7: 0 | P7: Q14行无法可靠匹配；Q18最主要原因多选 | Q7: 0 | R7: 0 | S7: 0 | T7: 1 | U7: 1 | V7: 与他人交换周边 | W7: 完成1–2次 | X7: 交换尝试记录 | Y7: 1 | Z7: 1 | AA7: 0 | AB7: 0 | AC7: 0 | AD7: 1 | AE7: 1 | AF7: 0 | AG7: 1 | AH7: 1 | AI7: 0 | AJ7: 1 | AK7: 0 | AL7: 0 | AM7: 1 | AN7: 1 | AO7: 0 | AP7: 0 | AQ7: 1 | AR7: 0 | AS7: 0 | AT7: 1 | AU7: 1 | AV7: 0 | AW7: 1 | AX7: 1 | AY7: 1 | AZ7: 1 | BA7: 1 | BB7: 0 | BC7: 1 | BD7: 0 | BE7: 0 | BF7: 0 | BG7: 0 | BU7: 1 | BV7: 0 | BW7: 1 | BX7: 0 | BY7: 0 | BZ7: 0 | CA7: 0 | CB7: 0 | CC7: 1 | CD7: 1 | CE7: 0 | CF7: 0 | CQ7: 3 | CR7: 不确定/需要了解更多规则 | CS7: 2 | CT7: 比较不可能 | CU7: 4 | CV7: 比较可能 | CW7: 97 | CX7: 不适用：没有对应需求或条件
A8: 7 | B8: 8 | C8: 主分析 | D8: 1 | E8: 1 | F8: 309 | G8: 18–22岁 | H8: 其他 | I8: 大专 | J8: 少于每周1天 | K8: 3–5次 | L8: 1 | M8: 不确定 | N8: 可确认尝试 | O8: 0 | P8: Q14行无法可靠匹配；Q18最主要原因多选 | Q8: 0 | R8: 0 | S8: 0 | T8: 1 | U8: 1 | V8: 与他人交换周边 | W8: 完成3–5次 | X8: 交换尝试记录 | Y8: 1 | Z8: 0 | AA8: 0 | AB8: 1 | AC8: 0 | AD8: 0 | AE8: 1 | AF8: 0 | AG8: 1 | AH8: 0 | AI8: 0 | AJ8: 0 | AK8: 1 | AL8: 0 | AM8: 1 | AN8: 1 | AO8: 0 | AP8: 0 | AQ8: 0 | AX8: 1 | AY8: 0 | AZ8: 1 | BA8: 0 | BB8: 0 | BC8: 0 | BD8: 1 | BE8: 0 | BF8: 0 | BG8: 0 | BU8: 1 | BV8: 0 | BW8: 0 | BX8: 0 | BY8: 0 | BZ8: 0 | CA8: 0 | CB8: 0 | CC8: 0 | CD8: 0 | CE8: 1 | CF8: 0 | CQ8: 97 | CR8: 不适用 | CS8: 4 | CT8: 比较可能 | CU8: 4 | CV8: 比较可能 | CW8: 4 | CX8: 比较可能
A9: 8 | B9: 9 | C9: 主分析 | D9: 1 | E9: 1 | F9: 580 | G9: 23–29岁 | H9: 女 | I9: 大专 | J9: 每周1–2天 | K9: 3–5次 | L9: 1 | M9: 有 | N9: 可确认尝试 | O9: 0 | P9: Q14行无法可靠匹配；Q18最主要原因多选 | Q9: 0 | R9: 0 | S9: 0 | T9: 1 | U9: 1 | V9: 出售个人周边 | W9: 完成1–2次 | X9: 出售尝试记录 | Y9: 1 | Z9: 1 | AA9: 0 | AB9: 1 | AC9: 0 | AD9: 0 | AE9: 0 | AF9: 0 | AG9: 1 | AH9: 0 | AI9: 1 | AJ9: 0 | AK9: 1 | AL9: 0 | AM9: 1 | AN9: 0 | AO9: 0 | AP9: 0 | AQ9: 1 | AR9: 1 | AS9: 0 | AT9: 1 | AU9: 0 | AV9: 1 | AW9: 0 | AX9: 1 | AY9: 0 | AZ9: 1 | BA9: 0 | BB9: 0 | BC9: 1 | BD9: 1 | BE9: 0 | BF9: 0 | BG9: 0 | BU9: 1 | BV9: 0 | BW9: 0 | BX9: 0 | BY9: 0 | BZ9: 0 | CA9: 1 | CB9: 1 | CC9: 0 | CD9: 0 | CE9: 0 | CF9: 0 | CQ9: 5 | CR9: 非常可能 | CS9: 4 | CT9: 比较可能 | CU9: 5 | CV9: 非常可能 | CW9: 3 | CX9: 不确定
A10: 9 | B10: 10 | C10: 主分析 | D10: 1 | E10: 1 | F10: 418 | G10: 23–29岁 | H10: 男 | I10: 本科 | J10: 每周1–2天 | K10: 3–5次 | L10: 1 | M10: 有 | N10: 可确认尝试 | O10: 0 | P10: Q14行无法可靠匹配；Q18最主要原因多选；Q16第4项用词歧义 | Q10: 0 | R10: 0 | S10: 0 | T10: 1 | U10: 1 | V10: 与他人交换周边 | W10: 完成3–5次 | X10: 交换尝试记录 | Y10: 1 | Z10: 0 | AA10: 0 | AB10: 0 | AC10: 1 | AD10: 1 | AE10: 1 | AF10: 0 | AG10: 1 | AH10: 1 | AI10: 0 | AJ10: 0 | AK10: 0 | AL10: 0 | AM10: 1 | AN10: 0 | AO10: 0 | AP10: 1 | AQ10: 1 | AR10: 0 | AS10: 0 | AT10: 1 | AU10: 1 | AV10: 1 | AW10: 1 | AX10: 1 | AY10: 1 | AZ10: 1 | BA10: 0 | BB10: 0 | BC10: 1 | BD10: 0 | BE10: 0 | BF10: 1 | BG10: 0 | BU10: 1 | BV10: 1 | BW10: 1 | BX10: 1 | BY10: 0 | BZ10: 0 | CA10: 0 | CB10: 0 | CC10: 0 | CD10: 0 | CE10: 0 | CF10: 0 | CQ10: 4 | CR10: 比较可能 | CS10: 4 | CT10: 比较可能 | CU10: 3 | CV10: 不确定 | CX10: 非常可爱
A11: 10 | B11: 11 | C11: 主分析 | D11: 1 | E11: 1 | F11: 222 | G11: 23–29岁 | H11: 男 | I11: 本科 | J11: 少于每周1天 | K11: 6–11次 | L11: 1 | M11: 没有 | N11: 可确认尝试 | O11: 0 | P11: 未触发已设检查（不代表真实性已验证） | Q11: 0 | R11: 0 | S11: 0 | T11: 0 | U11: 0 | V11: 与他人交换周边 | W11: 完成3–5次 | X11: 交换尝试记录 | Y11: 1 | Z11: 0 | AA11: 0 | AB11: 0 | AC11: 0 | AD11: 1 | AE11: 0 | AF11: 0 | AG11: 1 | AH11: 0 | AI11: 0 | AJ11: 0 | AK11: 0 | AL11: 0 | AM11: 1 | AN11: 0 | AO11: 0 | AP11: 0 | AQ11: 0 | AX11: 1 | AY11: 0 | AZ11: 0 | BA11: 0 | BB11: 0 | BC11: 0 | BD11: 0 | BE11: 0 | BF11: 1 | BG11: 1 | BH11: 0 | BI11: 0 | BJ11: 0 | BK11: 1 | BL11: 0 | BM11: 0 | BN11: 1 | BO11: 0 | BP11: 0 | BQ11: 0 | BR11: 0 | BS11: 0 | BT11: 0 | BU11: 1 | BV11: 0 | BW11: 1 | BX11: 0 | BY11: 0 | BZ11: 0 | CA11: 0 | CB11: 0 | CC11: 1 | CD11: 1 | CE11: 0 | CF11: 1 | CG11: 0 | CH11: 0 | CI11: 0 | CJ11: 0 | CK11: 0 | CL11: 0 | CM11: 0 | CN11: 1 | CO11: 0 | CP11: 0 | CQ11: 5 | CR11: 非常可能 | CS11: 4 | CT11: 比较可能 | CU11: 4 | CV11: 比较可能 | CW11: 5 | CX11: 非常可能
A12: 11 | B12: 12 | C12: 质量暂不纳入 | D12: 1 | E12: 0 | F12: 268 | G12: 30–39岁 | H12: 女 | I12: 本科 | J12: 每周3–6天 | K12: 0次 | L12: 0 | M12: 没有 | N12: 可确认尝试 | O12: 0 | P12: Q15五填空整段跨记录重复，主分析暂不纳入；Q16无可能性填写；Q14行无法可靠匹配；Q18最主要原因多选；concern互斥混选 | Q12: 1 | R12: 0 | S12: 1 | T12: 1 | U12: 1 | V12: 出售个人周边 | W12: 完成1–2次 | X12: 出售尝试记录 | Y12: 0 | AG12: 0 | AQ12: 0 | AX12: 1 | AY12: 1 | AZ12: 0 | BA12: 0 | BB12: 0 | BC12: 0 | BD12: 0 | BE12: 0 | BF12: 1 | BG12: 0 | BU12: 0 | CF12: 0
A13: 12 | B13: 13 | C13: 主分析 | D13: 1 | E13: 1 | F13: 309 | G13: 23–29岁 | H13: 男 | I13: 本科 | J13: 每周1–2天 | K13: 6–11次 | L13: 1 | M13: 有 | N13: 可确认尝试 | O13: 0 | P13: Q14行无法可靠匹配；Q18最主要原因多选 | Q13: 0 | R13: 0 | S13: 0 | T13: 1 | U13: 1 | V13: 与他人交换周边 | W13: 尝试过，但未完成 | X13: 交换尝试记录 | Y13: 1 | Z13: 0 | AA13: 0 | AB13: 1 | AC13: 1 | AD13: 1 | AE13: 0 | AF13: 0 | AG13: 1 | AH13: 0 | AI13: 0 | AJ13: 1 | AK13: 1 | AL13: 0 | AM13: 0 | AN13: 1 | AO13: 0 | AP13: 0 | AQ13: 1 | AR13: 0 | AS13: 0 | AT13: 1 | AU13: 1 | AV13: 1 | AW13: 0 | AX13: 1 | AY13: 1 | AZ13: 1 | BA13: 0 | BB13: 0 | BC13: 0 | BD13: 0 | BE13: 0 | BF13: 1 | BG13: 0 | BU13: 1 | BV13: 1 | BW13: 1 | BX13: 1 | BY13: 0 | BZ13: 0 | CA13: 0 | CB13: 0 | CC13: 0 | CD13: 0 | CE13: 0 | CF13: 0 | CQ13: 3 | CR13: 不确定 | CS13: 2 | CT13: 比较不可能 | CU13: 4 | CV13: 比较可能 | CW13: 5 | CX13: 非常可能
A14: 13 | B14: 14 | C14: 质量暂不纳入 | D14: 1 | E14: 0 | F14: 274 | G14: 23–29岁 | H14: 男 | I14: 本科 | J14: 每周3–6天 | K14: 0次 | L14: 0 | M14: 不确定 | N14: 无法判断 | O14: 0 | P14: Q15五填空整段跨记录重复，主分析暂不纳入；Q16无可能性填写；Q14行无法可靠匹配；Q18最主要原因多选 | Q14: 1 | R14: 0 | S14: 1 | T14: 1 | U14: 1 | V14: 与他人交换周边 | W14: 没有尝试过 | X14: 无法判断 | Y14: 0 | AG14: 0 | AQ14: 0 | AX14: 0 | BG14: 0 | BU14: 1 | BV14: 1 | BW14: 1 | BX14: 0 | BY14: 0 | BZ14: 0 | CA14: 0 | CB14: 1 | CC14: 0 | CD14: 0 | CE14: 0 | CF14: 0
A15: 14 | B15: 15 | C15: 主分析 | D15: 1 | E15: 1 | F15: 295 | G15: 23–29岁 | H15: 男 | I15: 本科 | J15: 每周3–6天 | K15: 0次 | L15: 0 | M15: 没有 | N15: 明确均未尝试 | O15: 0 | P15: Q16无可能性填写 | Q15: 0 | R15: 0 | S15: 1 | T15: 0 | U15: 0 | V15: 均没有尝试过 | W15: (跳过) | X15: 明确均未尝试 | Y15: 0 | AG15: 0 | AQ15: 0 | AX15: 0 | BG15: 0 | BU15: 1 | BV15: 0 | BW15: 0 | BX15: 1 | BY15: 0 | BZ15: 0 | CA15: 0 | CB15: 0 | CC15: 0 | CD15: 0 | CE15: 0 | CF15: 1 | CG15: 1 | CH15: 0 | CI15: 0 | CJ15: 0 | CK15: 0 | CL15: 0 | CM15: 0 | CN15: 0 | CO15: 0 | CP15: 0
A16: 15 | B16: 16 | C16: 主分析 | D16: 1 | E16: 1 | F16: 274 | G16: 18–22岁 | H16: 女 | I16: 本科 | J16: 少于每周1天 | K16: 1–2次 | L16: 1 | M16: 不确定 | N16: 明确均未尝试 | O16: 0 | P16: Q16无可能性填写 | Q16: 0 | R16: 0 | S16: 1 | T16: 0 | U16: 0 | V16: 均没有尝试过 | W16: (跳过) | X16: 明确均未尝试 | Y16: 1 | Z16: 0 | AA16: 0 | AB16: 1 | AC16: 1 | AD16: 1 | AE16: 0 | AF16: 0 | AG16: 1 | AH16: 0 | AI16: 1 | AJ16: 0 | AK16: 0 | AL16: 0 | AM16: 0 | AN16: 0 | AO16: 0 | AP16: 1 | AQ16: 0 | AX16: 0 | BG16: 0 | BU16: 1 | BV16: 1 | BW16: 0 | BX16: 0 | BY16: 0 | BZ16: 0 | CA16: 0 | CB16: 0 | CC16: 0 | CD16: 1 | CE16: 0 | CF16: 1 | CG16: 0 | CH16: 0 | CI16: 0 | CJ16: 0 | CK16: 0 | CL16: 0 | CM16: 0 | CN16: 0 | CO16: 1 | CP16: 0
A17: 16 | B17: 17 | C17: 主分析 | D17: 1 | E17: 1 | F17: 240 | G17: 30–39岁 | H17: 不愿透露 | I17: 本科 | J17: 每周3–6天 | K17: 1–2次 | L17: 1 | M17: 不确定 | N17: 明确均未尝试 | O17: 0 | P17: Q16无可能性填写 | Q17: 0 | R17: 0 | S17: 1 | T17: 0 | U17: 0 | V17: 均没有尝试过 | W17: (跳过) | X17: 明确均未尝试 | Y17: 1 | Z17: 0 | AA17: 0 | AB17: 0 | AC17: 1 | AD17: 0 | AE17: 0 | AF17: 0 | AG17: 1 | AH17: 0 | AI17: 1 | AJ17: 0 | AK17: 0 | AL17: 0 | AM17: 0 | AN17: 0 | AO17: 0 | AP17: 1 | AQ17: 0 | AX17: 0 | BG17: 0 | BU17: 1 | BV17: 0 | BW17: 0 | BX17: 0 | BY17: 0 | BZ17: 0 | CA17: 0 | CB17: 0 | CC17: 0 | CD17: 1 | CE17: 0 | CF17: 1 | CG17: 0 | CH17: 0 | CI17: 0 | CJ17: 0 | CK17: 1 | CL17: 0 | CM17: 0 | CN17: 0 | CO17: 0 | CP17: 0
A18: 17 | B18: 18 | C18: 主分析 | D18: 1 | E18: 1 | F18: 152 | G18: 30–39岁 | H18: 女 | I18: 本科 | J18: 每周1–2天 | K18: 0次 | L18: 0 | M18: 有 | N18: 无法判断 | O18: 1 | P18: Q11尝试与Q12均未尝试冲突；Q16无可能性填写 | Q18: 0 | R18: 0 | S18: 1 | T18: 0 | U18: 0 | V18: 均没有尝试过 | W18: (跳过) | X18: 无法判断 | Y18: 0 | AG18: 0 | AQ18: 0 | AX18: 0 | BG18: 0 | BU18: 1 | BV18: 0 | BW18: 0 | BX18: 0 | BY18: 0 | BZ18: 0 | CA18: 0 | CB18: 0 | CC18: 1 | CD18: 0 | CE18: 0 | CF18: 1 | CG18: 0 | CH18: 0 | CI18: 1 | CJ18: 0 | CK18: 0 | CL18: 0 | CM18: 0 | CN18: 0 | CO18: 0 | CP18: 0
A19: 18 | B19: 19 | C19: 主分析 | D19: 1 | E19: 1 | F19: 128 | G19: 30–39岁 | H19: 男 | I19: 不愿透露 | J19: 每周3–6天 | K19: 0次 | L19: 0 | M19: 有 | N19: 无法判断 | O19: 1 | P19: Q11尝试与Q12均未尝试冲突；Q16无可能性填写；Q18最主要原因多选 | Q19: 0 | R19: 0 | S19: 1 | T19: 1 | U19: 0 | V19: 均没有尝试过 | W19: (跳过) | X19: 无法判断 | Y19: 0 | AG19: 0 | AQ19: 0 | AX19: 0 | BG19: 0 | BU19: 1 | BV19: 0 | BW19: 0 | BX19: 1 | BY19: 0 | BZ19: 0 | CA19: 0 | CB19: 1 | CC19: 0 | CD19: 0 | CE19: 0 | CF19: 0
A20: 19 | B20: 20 | C20: 主分析 | D20: 1 | E20: 1 | F20: 143 | G20: 30–39岁 | H20: 男 | I20: 本科 | J20: 几乎每天 | K20: 1–2次 | L20: 1 | M20: 不确定 | N20: 明确均未尝试 | O20: 0 | P20: Q16无可能性填写 | Q20: 0 | R20: 0 | S20: 1 | T20: 0 | U20: 0 | V20: 均没有尝试过 | W20: (跳过) | X20: 明确均未尝试 | Y20: 1 | Z20: 0 | AA20: 0 | AB20: 0 | AC20: 1 | AD20: 0 | AE20: 1 | AF20: 0 | AG20: 1 | AH20: 0 | AI20: 0 | AJ20: 0 | AK20: 0 | AL20: 0 | AM20: 0 | AN20: 0 | AO20: 0 | AP20: 1 | AQ20: 0 | AX20: 0 | BG20: 0 | BU20: 1 | BV20: 0 | BW20: 0 | BX20: 1 | BY20: 0 | BZ20: 0 | CA20: 0 | CB20: 0 | CC20: 0 | CD20: 0 | CE20: 0 | CF20: 1 | CG20: 0 | CH20: 0 | CI20: 0 | CJ20: 1 | CK20: 0 | CL20: 0 | CM20: 0 | CN20: 0 | CO20: 0 | CP20: 0
A21: 20 | B21: 21 | C21: 质量暂不纳入 | D21: 1 | E21: 0 | F21: 256 | G21: 不愿透露 | H21: 女 | I21: 本科 | J21: 每周3–6天 | K21: 0次 | L21: 0 | M21: 有 | N21: 可确认尝试 | O21: 0 | P21: Q15五填空整段跨记录重复，主分析暂不纳入；年龄未披露，资格未完全核实；Q16无可能性填写；Q14行无法可靠匹配 | Q21: 1 | R21: 0 | S21: 1 | T21: 0 | U21: 1 | V21: 与他人交换周边 | W21: 完成3–5次 | X21: 交换尝试记录 | Y21: 0 | AG21: 0 | AQ21: 1 | AR21: 0 | AS21: 0 | AT21: 0 | AU21: 0 | AV21: 1 | AW21: 0 | AX21: 1 | AY21: 1 | AZ21: 0 | BA21: 0 | BB21: 0 | BC21: 0 | BD21: 0 | BE21: 0 | BF21: 1 | BG21: 0 | BU21: 1 | BV21: 1 | BW21: 1 | BX21: 1 | BY21: 0 | BZ21: 0 | CA21: 0 | CB21: 0 | CC21: 0 | CD21: 0 | CE21: 0 | CF21: 1 | CG21: 0 | CH21: 1 | CI21: 0 | CJ21: 0 | CK21: 0 | CL21: 0 | CM21: 0 | CN21: 0 | CO21: 0 | CP21: 0
A22: 21 | B22: 22 | C22: 质量暂不纳入 | D22: 1 | E22: 0 | F22: 225 | G22: 30–39岁 | H22: 男 | I22: 高中／中专／职高／技校 | J22: 过去3个月没有使用过 | K22: 1–2次 | L22: 1 | M22: 没有 | N22: 无法判断 | O22: 0 | P22: Q15五填空整段跨记录重复，主分析暂不纳入；Q16无可能性填写；Q14行无法可靠匹配 | Q22: 1 | R22: 0 | S22: 1 | T22: 0 | U22: 1 | V22: 与他人交换周边 | W22: 没有尝试过 | X22: 无法判断 | Y22: 1 | Z22: 0 | AA22: 0 | AB22: 0 | AC22: 0 | AD22: 0 | AE22: 1 | AF22: 0 | AG22: 1 | AH22: 0 | AI22: 1 | AJ22: 0 | AK22: 1 | AL22: 0 | AM22: 0 | AN22: 0 | AO22: 0 | AP22: 1 | AQ22: 0 | AX22: 0 | BG22: 0 | BU22: 1 | BV22: 0 | BW22: 0 | BX22: 1 | BY22: 0 | BZ22: 0 | CA22: 0 | CB22: 0 | CC22: 0 | CD22: 1 | CE22: 0 | CF22: 1 | CG22: 0 | CH22: 0 | CI22: 0 | CJ22: 0 | CK22: 0 | CL22: 0 | CM22: 0 | CN22: 1 | CO22: 0 | CP22: 0
A23: 22 | B23: 23 | C23: 质量暂不纳入 | D23: 1 | E23: 0 | F23: 285 | G23: 23–29岁 | H23: 男 | I23: 本科 | J23: 几乎每天 | K23: 1–2次 | L23: 1 | M23: 有 | N23: 可确认尝试 | O23: 0 | P23: Q15五填空整段跨记录重复，主分析暂不纳入；Q16无可能性填写；Q14行无法可靠匹配 | Q23: 1 | R23: 0 | S23: 1 | T23: 0 | U23: 1 | V23: 与他人交换周边 | W23: 完成1–2次 | X23: 交换尝试记录 | Y23: 1 | Z23: 0 | AA23: 0 | AB23: 0 | AC23: 1 | AD23: 0 | AE23: 0 | AF23: 0 | AG23: 1 | AH23: 0 | AI23: 0 | AJ23: 0 | AK23: 1 | AL23: 0 | AM23: 0 | AN23: 0 | AO23: 0 | AP23: 1 | AQ23: 1 | AR23: 0 | AS23: 0 | AT23: 0 | AU23: 1 | AV23: 0 | AW23: 0 | AX23: 1 | AY23: 0 | AZ23: 0 | BA23: 0 | BB23: 0 | BC23: 0 | BD23: 0 | BE23: 0 | BF23: 1 | BG23: 0 | BU23: 1 | BV23: 1 | BW23: 0 | BX23: 0 | BY23: 0 | BZ23: 0 | CA23: 0 | CB23: 0 | CC23: 0 | CD23: 0 | CE23: 0 | CF23: 1 | CG23: 0 | CH23: 0 | CI23: 1 | CJ23: 0 | CK23: 0 | CL23: 0 | CM23: 0 | CN23: 0 | CO23: 0 | CP23: 0
A24: 23 | B24: 24 | C24: 主分析 | D24: 1 | E24: 1 | F24: 313 | G24: 30–39岁 | H24: 男 | I24: 本科 | J24: 每周1–2天 | K24: 1–2次 | L24: 1 | M24: 有 | N24: 可确认尝试 | O24: 0 | P24: Q18最主要原因多选 | Q24: 0 | R24: 0 | S24: 0 | T24: 1 | U24: 0 | V24: 出售个人周边 | W24: 尝试过，但未完成 | X24: 出售尝试记录 | Y24: 1 | Z24: 0 | AA24: 0 | AB24: 0 | AC24: 0 | AD24: 1 | AE24: 0 | AF24: 0 | AG24: 1 | AH24: 1 | AI24: 0 | AJ24: 0 | AK24: 0 | AL24: 0 | AM24: 0 | AN24: 0 | AO24: 0 | AP24: 1 | AQ24: 1 | AR24: 0 | AS24: 0 | AT24: 0 | AU24: 1 | AV24: 0 | AW24: 0 | AX24: 1 | AY24: 1 | AZ24: 0 | BA24: 0 | BB24: 0 | BC24: 0 | BD24: 0 | BE24: 0 | BF24: 1 | BG24: 1 | BH24: 0 | BI24: 0 | BJ24: 0 | BK24: 0 | BL24: 0 | BM24: 0 | BN24: 0 | BO24: 0 | BP24: 0 | BQ24: 1 | BR24: 0 | BS24: 0 | BT24: 0 | BU24: 1 | BV24: 1 | BW24: 0 | BX24: 1 | BY24: 0 | BZ24: 0 | CA24: 0 | CB24: 0 | CC24: 0 | CD24: 0 | CE24: 0 | CF24: 0 | CQ24: 5 | CR24: 非常可能 | CS24: 4 | CT24: 比较可能 | CU24: 4 | CV24: 比较可能 | CW24: 3 | CX24: 不确定
A25: 24 | B25: 25 | C25: 质量暂不纳入 | D25: 1 | E25: 0 | F25: 240 | G25: 18–22岁 | H25: 女 | I25: 不愿透露 | J25: 每周3–6天 | K25: 3–5次 | L25: 1 | M25: 没有 | N25: 无法判断 | O25: 0 | P25: Q15五填空整段跨记录重复，主分析暂不纳入；Q16无可能性填写；Q14行无法可靠匹配；type互斥混选；channel互斥混选；concern互斥混选 | Q25: 1 | R25: 0 | S25: 1 | T25: 0 | U25: 1 | V25: 出售个人周边 | W25: 没有尝试过 | X25: 无法判断 | Y25: 0 | AG25: 1 | AH25: 0 | AI25: 1 | AJ25: 0 | AK25: 0 | AL25: 0 | AM25: 0 | AN25: 0 | AO25: 0 | AP25: 0 | AQ25: 0 | AX25: 0 | BG25: 0 | BU25: 0 | CF25: 1 | CG25: 0 | CH25: 1 | CI25: 0 | CJ25: 0 | CK25: 0 | CL25: 0 | CM25: 0 | CN25: 0 | CO25: 0 | CP25: 0
A26: 25 | B26: 26 | C26: 质量暂不纳入 | D26: 1 | E26: 0 | F26: 229 | G26: 30–39岁 | H26: 男 | I26: 本科 | J26: 少于每周1天 | K26: 6–11次 | L26: 1 | M26: 有 | N26: 无法判断 | O26: 0 | P26: Q15五填空整段跨记录重复，主分析暂不纳入；Q16无可能性填写；Q14行无法可靠匹配；Q18最主要原因多选 | Q26: 1 | R26: 0 | S26: 1 | T26: 1 | U26: 1 | V26: 与他人交换周边 | W26: 没有尝试过 | X26: 无法判断 | Y26: 1 | Z26: 0 | AA26: 0 | AB26: 1 | AC26: 1 | AD26: 0 | AE26: 1 | AF26: 0 | AG26: 1 | AH26: 0 | AI26: 0 | AJ26: 0 | AK26: 0 | AL26: 0 | AM26: 0 | AN26: 0 | AO26: 0 | AP26: 1 | AQ26: 1 | AR26: 1 | AS26: 0 | AT26: 0 | AU26: 1 | AV26: 1 | AW26: 0 | AX26: 0 | BG26: 0 | BU26: 1 | BV26: 0 | BW26: 0 | BX26: 1 | BY26: 0 | BZ26: 0 | CA26: 0 | CB26: 0 | CC26: 0 | CD26: 0 | CE26: 0 | CF26: 0
A27: 26 | B27: 27 | C27: 主分析 | D27: 1 | E27: 1 | F27: 250 | G27: 30–39岁 | H27: 不愿透露 | I27: 本科 | J27: 每周3–6天 | K27: 0次 | L27: 0 | M27: 不确定 | N27: 明确均未尝试 | O27: 0 | P27: Q16无可能性填写 | Q27: 0 | R27: 0 | S27: 1 | T27: 0 | U27: 0 | V27: 均没有尝试过 | W27: (跳过) | X27: 明确均未尝试 | Y27: 0 | AG27: 0 | AQ27: 0 | AX27: 0 | BG27: 0 | BU27: 1 | BV27: 0 | BW27: 1 | BX27: 0 | BY27: 0 | BZ27: 0 | CA27: 0 | CB27: 0 | CC27: 0 | CD27: 0 | CE27: 0 | CF27: 1 | CG27: 0 | CH27: 0 | CI27: 0 | CJ27: 0 | CK27: 0 | CL27: 0 | CM27: 0 | CN27: 0 | CO27: 1 | CP27: 0
A28: 27 | B28: 28 | C28: 主分析 | D28: 1 | E28: 1 | F28: 201 | G28: 23–29岁 | H28: 男 | I28: 本科 | J28: 每周3–6天 | K28: 3–5次 | L28: 1 | M28: 不确定 | N28: 明确均未尝试 | O28: 0 | P28: Q16无可能性填写；Q18最主要原因多选 | Q28: 0 | R28: 0 | S28: 1 | T28: 1 | U28: 0 | V28: 均没有尝试过 | W28: (跳过) | X28: 明确均未尝试 | Y28: 1 | Z28: 0 | AA28: 0 | AB28: 0 | AC28: 1 | AD28: 0 | AE28: 1 | AF28: 0 | AG28: 1 | AH28: 0 | AI28: 1 | AJ28: 0 | AK28: 0 | AL28: 0 | AM28: 0 | AN28: 0 | AO28: 0 | AP28: 0 | AQ28: 0 | AX28: 0 | BG28: 0 | BU28: 1 | BV28: 0 | BW28: 0 | BX28: 0 | BY28: 0 | BZ28: 1 | CA28: 0 | CB28: 0 | CC28: 0 | CD28: 0 | CE28: 0 | CF28: 0
A29: 28 | B29: 29 | C29: 质量暂不纳入 | D29: 1 | E29: 0 | F29: 190 | G29: 18–22岁 | H29: 男 | I29: 大专 | J29: 几乎每天 | K29: 0次 | L29: 0 | M29: 没有 | N29: 无法判断 | O29: 0 | P29: Q15五填空整段跨记录重复，主分析暂不纳入；Q16无可能性填写 | Q29: 1 | R29: 0 | S29: 1 | T29: 0 | U29: 0 | V29: 出售个人周边 | W29: 没有尝试过 | X29: 无法判断 | Y29: 0 | AG29: 0 | AQ29: 0 | AX29: 0 | BG29: 0 | BU29: 1 | BV29: 1 | BW29: 0 | BX29: 0 | BY29: 0 | BZ29: 0 | CA29: 0 | CB29: 0 | CC29: 0 | CD29: 1 | CE29: 0 | CF29: 1 | CG29: 0 | CH29: 0 | CI29: 0 | CJ29: 0 | CK29: 0 | CL29: 0 | CM29: 0 | CN29: 0 | CO29: 1 | CP29: 0
A30: 29 | B30: 30 | C30: 主分析 | D30: 1 | E30: 1 | F30: 286 | G30: 23–29岁 | H30: 男 | I30: 本科 | J30: 几乎每天 | K30: 6–11次 | L30: 1 | M30: 有 | N30: 无法判断 | O30: 1 | P30: Q11尝试与Q12均未尝试冲突；Q16无可能性填写 | Q30: 0 | R30: 0 | S30: 1 | T30: 0 | U30: 0 | V30: 均没有尝试过 | W30: (跳过) | X30: 无法判断 | Y30: 1 | Z30: 1 | AA30: 0 | AB30: 0 | AC30: 1 | AD30: 0 | AE30: 0 | AF30: 0 | AG30: 1 | AH30: 0 | AI30: 0 | AJ30: 0 | AK30: 1 | AL30: 0 | AM30: 0 | AN30: 1 | AO30: 0 | AP30: 0 | AQ30: 0 | AX30: 0 | BG30: 0 | BU30: 1 | BV30: 0 | BW30: 0 | BX30: 0 | BY30: 0 | BZ30: 0 | CA30: 0 | CB30: 0 | CC30: 0 | CD30: 1 | CE30: 0 | CF30: 1 | CG30: 0 | CH30: 0 | CI30: 0 | CJ30: 0 | CK30: 0 | CL30: 0 | CM30: 0 | CN30: 0 | CO30: 1 | CP30: 0
A31: 30 | B31: 31 | C31: 质量暂不纳入 | D31: 1 | E31: 0 | F31: 240 | G31: 30–39岁 | H31: 男 | I31: 本科 | J31: 每周1–2天 | K31: 0次 | L31: 0 | M31: 没有 | N31: 无法判断 | O31: 0 | P31: Q15五填空整段跨记录重复，主分析暂不纳入；Q16无可能性填写；Q18最主要原因多选；channel互斥混选 | Q31: 1 | R31: 0 | S31: 1 | T31: 1 | U31: 0 | V31: 与他人交换周边 | W31: 没有尝试过 | X31: 无法判断 | Y31: 0 | AG31: 0 | AQ31: 0 | AX31: 0 | BG31: 0 | BU31: 1 | BV31: 0 | BW31: 0 | BX31: 0 | BY31: 0 | BZ31: 1 | CA31: 0 | CB31: 0 | CC31: 0 | CD31: 0 | CE31: 0 | CF31: 0
A32: 31 | B32: 32 | C32: 质量暂不纳入 | D32: 1 | E32: 0 | F32: 201 | G32: 18–22岁 | H32: 男 | I32: 大专 | J32: 每周3–6天 | K32: 0次 | L32: 0 | M32: 没有 | N32: 无法判断 | O32: 0 | P32: Q15五填空整段跨记录重复，主分析暂不纳入；Q16无可能性填写；Q18最主要原因多选 | Q32: 1 | R32: 0 | S32: 1 | T32: 1 | U32: 0 | V32: 出售个人周边 | W32: 没有尝试过 | X32: 无法判断 | Y32: 0 | AG32: 0 | AQ32: 0 | AX32: 0 | BG32: 0 | BU32: 1 | BV32: 0 | BW32: 0 | BX32: 1 | BY32: 0 | BZ32: 0 | CA32: 0 | CB32: 0 | CC32: 0 | CD32: 0 | CE32: 0 | CF32: 0
A33: 32 | B33: 33 | C33: 质量暂不纳入 | D33: 1 | E33: 0 | F33: 132 | G33: 18–22岁 | H33: 男 | I33: 不愿透露 | J33: 几乎每天 | K33: 0次 | L33: 0 | M33: 不确定 | N33: 无法判断 | O33: 0 | P33: Q15五填空整段跨记录重复，主分析暂不纳入；Q16无可能性填写 | Q33: 1 | R33: 0 | S33: 1 | T33: 0 | U33: 0 | V33: 出售个人周边 | W33: 没有尝试过 | X33: 无法判断 | Y33: 0 | AG33: 0 | AQ33: 0 | AX33: 0 | BG33: 0 | BU33: 1 | BV33: 0 | BW33: 0 | BX33: 1 | BY33: 0 | BZ33: 0 | CA33: 0 | CB33: 0 | CC33: 1 | CD33: 0 | CE33: 0 | CF33: 1 | CG33: 0 | CH33: 0 | CI33: 0 | CJ33: 0 | CK33: 0 | CL33: 0 | CM33: 0 | CN33: 0 | CO33: 1 | CP33: 0
A34: 33 | B34: 34 | C34: 质量暂不纳入 | D34: 1 | E34: 0 | F34: 222 | G34: 30–39岁 | H34: 女 | I34: 硕士研究生及以上 | J34: 几乎每天 | K34: 0次 | L34: 0 | M34: 有 | N34: 可确认尝试 | O34: 0 | P34: Q15五填空整段跨记录重复，主分析暂不纳入；Q16无可能性填写；Q14行无法可靠匹配；barrier互斥混选 | Q34: 1 | R34: 0 | S34: 1 | T34: 0 | U34: 1 | V34: 与他人交换周边 | W34: 完成3–5次 | X34: 交换尝试记录 | Y34: 0 | AG34: 0 | AQ34: 1 | AR34: 0 | AS34: 1 | AT34: 0 | AU34: 0 | AV34: 1 | AW34: 0 | AX34: 1 | AY34: 1 | AZ34: 0 | BA34: 0 | BB34: 0 | BC34: 0 | BD34: 0 | BE34: 0 | BF34: 0 | BG34: 0 | BU34: 1 | BV34: 1 | BW34: 0 | BX34: 1 | BY34: 0 | BZ34: 0 | CA34: 0 | CB34: 0 | CC34: 0 | CD34: 0 | CE34: 0 | CF34: 1 | CG34: 0 | CH34: 1 | CI34: 0 | CJ34: 0 | CK34: 0 | CL34: 0 | CM34: 0 | CN34: 0 | CO34: 0 | CP34: 0
A35: 34 | B35: 35 | C35: 质量暂不纳入 | D35: 1 | E35: 0 | F35: 121 | G35: 23–29岁 | H35: 女 | I35: 大专 | J35: 每周3–6天 | K35: 买过，但记不清次数 | L35: 1 | M35: 没有 | N35: 无法判断 | O35: 0 | P35: Q15五填空整段跨记录重复，主分析暂不纳入；Q16无可能性填写 | Q35: 1 | R35: 0 | S35: 1 | T35: 0 | U35: 0 | V35: 出售个人周边 | W35: 没有尝试过 | X35: 无法判断 | Y35: 1 | Z35: 0 | AA35: 0 | AB35: 0 | AC35: 0 | AD35: 1 | AE35: 0 | AF35: 0 | AG35: 1 | AH35: 0 | AI35: 1 | AJ35: 0 | AK35: 0 | AL35: 0 | AM35: 0 | AN35: 0 | AO35: 0 | AP35: 1 | AQ35: 0 | AX35: 0 | BG35: 0 | BU35: 1 | BV35: 0 | BW35: 0 | BX35: 0 | BY35: 0 | BZ35: 0 | CA35: 0 | CB35: 0 | CC35: 0 | CD35: 0 | CE35: 1 | CF35: 1 | CG35: 0 | CH35: 0 | CI35: 0 | CJ35: 0 | CK35: 0 | CL35: 0 | CM35: 1 | CN35: 0 | CO35: 0 | CP35: 0
A36: 35 | B36: 36 | C36: 主分析 | D36: 1 | E36: 1 | F36: 174 | G36: 不愿透露 | H36: 男 | I36: 大专 | J36: 几乎每天 | K36: 0次 | L36: 0 | M36: 不确定 | N36: 明确均未尝试 | O36: 0 | P36: 年龄未披露，资格未完全核实；Q16无可能性填写 | Q36: 0 | R36: 0 | S36: 1 | T36: 0 | U36: 0 | V36: 均没有尝试过 | W36: (跳过) | X36: 明确均未尝试 | Y36: 0 | AG36: 0 | AQ36: 0 | AX36: 0 | BG36: 0 | BU36: 1 | BV36: 0 | BW36: 0 | BX36: 1 | BY36: 0 | BZ36: 0 | CA36: 0 | CB36: 0 | CC36: 0 | CD36: 1 | CE36: 0 | CF36: 1 | CG36: 0 | CH36: 0 | CI36: 0 | CJ36: 0 | CK36: 0 | CL36: 0 | CM36: 0 | CN36: 1 | CO36: 0 | CP36: 0
A37: 36 | B37: 37 | C37: 主分析 | D37: 1 | E37: 1 | F37: 560 | G37: 23–29岁 | H37: 女 | I37: 本科 | J37: 每周3–6天 | K37: 6–11次 | L37: 1 | M37: 没有 | N37: 可确认尝试 | O37: 0 | P37: Q18最主要原因多选 | Q37: 0 | R37: 0 | S37: 0 | T37: 1 | U37: 0 | V37: 出售个人周边 | W37: 完成3–5次 | X37: 出售尝试记录 | Y37: 1 | Z37: 1 | AA37: 0 | AB37: 0 | AC37: 0 | AD37: 1 | AE37: 1 | AF37: 0 | AG37: 1 | AH37: 1 | AI37: 1 | AJ37: 0 | AK37: 1 | AL37: 0 | AM37: 0 | AN37: 1 | AO37: 0 | AP37: 1 | AQ37: 0 | AX37: 1 | AY37: 1 | AZ37: 1 | BA37: 0 | BB37: 0 | BC37: 1 | BD37: 0 | BE37: 0 | BF37: 0 | BG37: 1 | BH37: 0 | BI37: 0 | BJ37: 1 | BK37: 0 | BL37: 0 | BM37: 0 | BN37: 0 | BO37: 0 | BP37: 0 | BQ37: 0 | BR37: 1 | BS37: 0 | BT37: 1 | BU37: 1 | BV37: 0 | BW37: 1 | BX37: 0 | BY37: 0 | BZ37: 0 | CA37: 1 | CB37: 0 | CC37: 1 | CD37: 0 | CE37: 0 | CF37: 0 | CQ37: 5 | CR37: 非常可能 | CS37: 2 | CT37: 比较不可能 | CU37: 4 | CV37: 比较可能 | CW37: 5 | CX37: 非常可能
A38: 37 | B38: 38 | C38: 主分析 | D38: 1 | E38: 1 | F38: 243 | G38: 23–29岁 | H38: 女 | I38: 本科 | J38: 每周3–6天 | K38: 3–5次 | L38: 1 | M38: 没有 | N38: 明确均未尝试 | O38: 0 | P38: Q16无可能性填写；Q18最主要原因多选 | Q38: 0 | R38: 0 | S38: 1 | T38: 1 | U38: 0 | V38: 均没有尝试过 | W38: (跳过) | X38: 明确均未尝试 | Y38: 1 | Z38: 0 | AA38: 0 | AB38: 0 | AC38: 1 | AD38: 0 | AE38: 0 | AF38: 0 | AG38: 1 | AH38: 0 | AI38: 1 | AJ38: 0 | AK38: 0 | AL38: 0 | AM38: 0 | AN38: 0 | AO38: 0 | AP38: 1 | AQ38: 0 | AX38: 0 | BG38: 0 | BU38: 1 | BV38: 0 | BW38: 0 | BX38: 0 | BY38: 0 | BZ38: 0 | CA38: 0 | CB38: 0 | CC38: 1 | CD38: 0 | CE38: 0 | CF38: 0
A39: 38 | B39: 39 | C39: 主分析 | D39: 1 | E39: 1 | F39: 290 | G39: 18–22岁 | H39: 女 | I39: 高中／中专／职高／技校 | J39: 每周3–6天 | K39: 1–2次 | L39: 1 | M39: 有 | N39: 明确均未尝试 | O39: 0 | P39: Q16无可能性填写；Q18最主要原因多选；type互斥混选 | Q39: 0 | R39: 0 | S39: 1 | T39: 1 | U39: 0 | V39: 均没有尝试过 | W39: (跳过) | X39: 明确均未尝试 | Y39: 0 | AG39: 1 | AH39: 0 | AI39: 1 | AJ39: 0 | AK39: 0 | AL39: 0 | AM39: 0 | AN39: 0 | AO39: 0 | AP39: 0 | AQ39: 1 | AR39: 0 | AS39: 0 | AT39: 0 | AU39: 0 | AV39: 1 | AW39: 0 | AX39: 0 | BG39: 0 | BU39: 1 | BV39: 0 | BW39: 1 | BX39: 1 | BY39: 0 | BZ39: 0 | CA39: 0 | CB39: 0 | CC39: 0 | CD39: 0 | CE39: 0 | CF39: 0
A40: 39 | B40: 40 | C40: 主分析 | D40: 1 | E40: 1 | F40: 208 | G40: 23–29岁 | H40: 男 | I40: 大专 | J40: 几乎每天 | K40: 1–2次 | L40: 1 | M40: 没有 | N40: 明确均未尝试 | O40: 0 | P40: Q16无可能性填写；Q18最主要原因多选；buy互斥混选 | Q40: 0 | R40: 0 | S40: 1 | T40: 1 | U40: 0 | V40: 均没有尝试过 | W40: (跳过) | X40: 明确均未尝试 | Y40: 1 | Z40: 1 | AA40: 1 | AB40: 1 | AC40: 1 | AD40: 1 | AE40: 0 | AF40: 0 | AG40: 0 | AQ40: 0 | AX40: 0 | BG40: 0 | BU40: 1 | BV40: 1 | BW40: 0 | BX40: 0 | BY40: 0 | BZ40: 0 | CA40: 0 | CB40: 1 | CC40: 0 | CD40: 0 | CE40: 0 | CF40: 0
A41: 40 | B41: 41 | C41: 主分析 | D41: 1 | E41: 1 | F41: 176 | G41: 18–22岁 | H41: 男 | I41: 本科 | J41: 少于每周1天 | K41: 0次 | L41: 0 | M41: 有 | N41: 明确均未尝试 | O41: 0 | P41: Q16无可能性填写 | Q41: 0 | R41: 0 | S41: 1 | T41: 0 | U41: 0 | V41: 均没有尝试过 | W41: (跳过) | X41: 明确均未尝试 | Y41: 0 | AG41: 0 | AQ41: 1 | AR41: 0 | AS41: 0 | AT41: 0 | AU41: 0 | AV41: 1 | AW41: 0 | AX41: 0 | BG41: 0 | BU41: 1 | BV41: 0 | BW41: 0 | BX41: 0 | BY41: 0 | BZ41: 0 | CA41: 0 | CB41: 0 | CC41: 0 | CD41: 1 | CE41: 0 | CF41: 1 | CG41: 0 | CH41: 0 | CI41: 0 | CJ41: 0 | CK41: 0 | CL41: 0 | CM41: 0 | CN41: 0 | CO41: 1 | CP41: 0
A42: 41 | B42: 42 | C42: 主分析 | D42: 1 | E42: 1 | F42: 195 | G42: 18–22岁 | H42: 男 | I42: 大专 | J42: 几乎每天 | K42: 0次 | L42: 0 | M42: 有 | N42: 明确均未尝试 | O42: 0 | P42: Q16无可能性填写；concern互斥混选 | Q42: 0 | R42: 0 | S42: 1 | T42: 0 | U42: 0 | V42: 均没有尝试过 | W42: (跳过) | X42: 明确均未尝试 | Y42: 0 | AG42: 0 | AQ42: 1 | AR42: 0 | AS42: 0 | AT42: 0 | AU42: 0 | AV42: 1 | AW42: 0 | AX42: 0 | BG42: 0 | BU42: 0 | CF42: 1 | CG42: 0 | CH42: 0 | CI42: 0 | CJ42: 0 | CK42: 0 | CL42: 0 | CM42: 1 | CN42: 0 | CO42: 0 | CP42: 0
A43: 42 | B43: 43 | C43: 质量暂不纳入 | D43: 1 | E43: 0 | F43: 247 | G43: 30–39岁 | H43: 男 | I43: 本科 | J43: 几乎每天 | K43: 0次 | L43: 0 | M43: 没有 | N43: 可确认尝试 | O43: 0 | P43: Q15五填空整段跨记录重复，主分析暂不纳入；Q16无可能性填写；Q14行无法可靠匹配；Q18最主要原因多选 | Q43: 1 | R43: 0 | S43: 1 | T43: 1 | U43: 1 | V43: 与他人交换周边 | W43: 尝试过，但未完成 | X43: 交换尝试记录 | Y43: 0 | AG43: 0 | AQ43: 0 | AX43: 1 | AY43: 0 | AZ43: 1 | BA43: 0 | BB43: 0 | BC43: 0 | BD43: 0 | BE43: 0 | BF43: 0 | BG43: 0 | BU43: 1 | BV43: 0 | BW43: 0 | BX43: 1 | BY43: 0 | BZ43: 0 | CA43: 0 | CB43: 0 | CC43: 0 | CD43: 0 | CE43: 0 | CF43: 0
A44: 43 | B44: 44 | C44: 主分析 | D44: 1 | E44: 1 | F44: 252 | G44: 30–39岁 | H44: 男 | I44: 大专 | J44: 过去3个月没有使用过 | K44: 6–11次 | L44: 1 | M44: 不确定 | N44: 明确均未尝试 | O44: 0 | P44: Q16无可能性填写 | Q44: 0 | R44: 0 | S44: 1 | T44: 0 | U44: 0 | V44: 均没有尝试过 | W44: (跳过) | X44: 明确均未尝试 | Y44: 1 | Z44: 0 | AA44: 0 | AB44: 0 | AC44: 1 | AD44: 0 | AE44: 0 | AF44: 0 | AG44: 1 | AH44: 1 | AI44: 1 | AJ44: 0 | AK44: 1 | AL44: 0 | AM44: 0 | AN44: 1 | AO44: 0 | AP44: 1 | AQ44: 0 | AX44: 0 | BG44: 0 | BU44: 1 | BV44: 0 | BW44: 0 | BX44: 0 | BY44: 0 | BZ44: 0 | CA44: 0 | CB44: 1 | CC44: 0 | CD44: 0 | CE44: 0 | CF44: 1 | CG44: 0 | CH44: 0 | CI44: 0 | CJ44: 0 | CK44: 0 | CL44: 0 | CM44: 0 | CN44: 0 | CO44: 1 | CP44: 0
A45: 44 | B45: 45 | C45: 质量暂不纳入 | D45: 1 | E45: 0 | F45: 252 | G45: 18–22岁 | H45: 男 | I45: 硕士研究生及以上 | J45: 每周3–6天 | K45: 0次 | L45: 0 | M45: 有 | N45: 无法判断 | O45: 0 | P45: Q15五填空整段跨记录重复，主分析暂不纳入；Q16无可能性填写；Q14行无法可靠匹配 | Q45: 1 | R45: 0 | S45: 1 | T45: 0 | U45: 1 | V45: 与他人交换周边 | W45: 没有尝试过 | X45: 无法判断 | Y45: 0 | AG45: 0 | AQ45: 1 | AR45: 1 | AS45: 0 | AT45: 0 | AU45: 0 | AV45: 0 | AW45: 0 | AX45: 0 | BG45: 0 | BU45: 1 | BV45: 0 | BW45: 1 | BX45: 0 | BY45: 0 | BZ45: 0 | CA45: 0 | CB45: 1 | CC45: 0 | CD45: 0 | CE45: 0 | CF45: 1 | CG45: 0 | CH45: 1 | CI45: 0 | CJ45: 0 | CK45: 0 | CL45: 0 | CM45: 0 | CN45: 0 | CO45: 0 | CP45: 0
A46: 45 | B46: 46 | C46: 质量暂不纳入 | D46: 1 | E46: 0 | F46: 265 | G46: 30–39岁 | H46: 女 | I46: 大专 | J46: 几乎每天 | K46: 0次 | L46: 0 | M46: 有 | N46: 无法判断 | O46: 0 | P46: Q15五填空整段跨记录重复，主分析暂不纳入；Q16无可能性填写；Q14行无法可靠匹配 | Q46: 1 | R46: 0 | S46: 1 | T46: 0 | U46: 1 | V46: 与他人交换周边 | W46: 没有尝试过 | X46: 无法判断 | Y46: 0 | AG46: 0 | AQ46: 1 | AR46: 0 | AS46: 0 | AT46: 0 | AU46: 1 | AV46: 0 | AW46: 0 | AX46: 0 | BG46: 0 | BU46: 1 | BV46: 0 | BW46: 0 | BX46: 1 | BY46: 0 | BZ46: 0 | CA46: 0 | CB46: 0 | CC46: 0 | CD46: 0 | CE46: 0 | CF46: 1 | CG46: 0 | CH46: 1 | CI46: 0 | CJ46: 0 | CK46: 0 | CL46: 0 | CM46: 0 | CN46: 0 | CO46: 0 | CP46: 0
A47: 46 | B47: 47 | C47: 主分析 | D47: 1 | E47: 1 | F47: 138 | G47: 23–29岁 | H47: 女 | I47: 本科 | J47: 从未使用过B站 | K47: 3–5次 | L47: 1 | M47: 有 | N47: 无法判断 | O47: 1 | P47: Q11尝试与Q12均未尝试冲突；Q16无可能性填写 | Q47: 0 | R47: 0 | S47: 1 | T47: 0 | U47: 0 | V47: 均没有尝试过 | W47: (跳过) | X47: 无法判断 | Y47: 1 | Z47: 1 | AA47: 0 | AB47: 0 | AC47: 1 | AD47: 0 | AE47: 0 | AF47: 0 | AG47: 1 | AH47: 0 | AI47: 0 | AJ47: 0 | AK47: 1 | AL47: 1 | AM47: 0 | AN47: 0 | AO47: 0 | AP47: 0 | AQ47: 0 | AX47: 0 | BG47: 0 | BU47: 1 | BV47: 0 | BW47: 0 | BX47: 1 | BY47: 0 | BZ47: 0 | CA47: 0 | CB47: 0 | CC47: 0 | CD47: 0 | CE47: 0 | CF47: 1 | CG47: 0 | CH47: 0 | CI47: 0 | CJ47: 0 | CK47: 0 | CL47: 0 | CM47: 0 | CN47: 0 | CO47: 1 | CP47: 0
A48: 47 | B48: 48 | C48: 质量暂不纳入 | D48: 1 | E48: 0 | F48: 165 | G48: 18–22岁 | H48: 男 | I48: 大专 | J48: 少于每周1天 | K48: 0次 | L48: 0 | M48: 没有 | N48: 可确认尝试 | O48: 0 | P48: Q15五填空整段跨记录重复，主分析暂不纳入；Q16无可能性填写；Q14行无法可靠匹配 | Q48: 1 | R48: 0 | S48: 1 | T48: 0 | U48: 1 | V48: 出售个人周边 | W48: 尝试过，但未完成 | X48: 出售尝试记录 | Y48: 0 | AG48: 0 | AQ48: 0 | AX48: 1 | AY48: 1 | AZ48: 0 | BA48: 0 | BB48: 0 | BC48: 0 | BD48: 0 | BE48: 0 | BF48: 1 | BG48: 0 | BU48: 1 | BV48: 0 | BW48: 1 | BX48: 0 | BY48: 0 | BZ48: 0 | CA48: 0 | CB48: 0 | CC48: 0 | CD48: 0 | CE48: 0 | CF48: 1 | CG48: 0 | CH48: 0 | CI48: 0 | CJ48: 0 | CK48: 0 | CL48: 1 | CM48: 0 | CN48: 0 | CO48: 0 | CP48: 0
A49: 48 | B49: 49 | C49: 主分析 | D49: 1 | E49: 1 | F49: 290 | G49: 30–39岁 | H49: 男 | I49: 本科 | J49: 每周3–6天 | K49: 0次 | L49: 0 | M49: 不确定 | N49: 明确均未尝试 | O49: 0 | P49: Q16无可能性填写 | Q49: 0 | R49: 0 | S49: 1 | T49: 0 | U49: 0 | V49: 均没有尝试过 | W49: (跳过) | X49: 明确均未尝试 | Y49: 0 | AG49: 0 | AQ49: 0 | AX49: 0 | BG49: 0 | BU49: 1 | BV49: 0 | BW49: 0 | BX49: 1 | BY49: 0 | BZ49: 0 | CA49: 0 | CB49: 0 | CC49: 0 | CD49: 0 | CE49: 0 | CF49: 1 | CG49: 0 | CH49: 0 | CI49: 0 | CJ49: 0 | CK49: 0 | CL49: 0 | CM49: 0 | CN49: 0 | CO49: 1 | CP49: 0
A50: 49 | B50: 50 | C50: 主分析 | D50: 1 | E50: 1 | F50: 159 | G50: 30–39岁 | H50: 男 | I50: 本科 | J50: 几乎每天 | K50: 0次 | L50: 0 | M50: 不确定 | N50: 明确均未尝试 | O50: 0 | P50: Q16无可能性填写 | Q50: 0 | R50: 0 | S50: 1 | T50: 0 | U50: 0 | V50: 均没有尝试过 | W50: (跳过) | X50: 明确均未尝试 | Y50: 0 | AG50: 0 | AQ50: 0 | AX50: 0 | BG50: 0 | BU50: 1 | BV50: 0 | BW50: 0 | BX50: 0 | BY50: 0 | BZ50: 1 | CA50: 0 | CB50: 0 | CC50: 1 | CD50: 0 | CE50: 0 | CF50: 1 | CG50: 0 | CH50: 0 | CI50: 0 | CJ50: 0 | CK50: 0 | CL50: 0 | CM50: 0 | CN50: 1 | CO50: 0 | CP50: 0
A51: 50 | B51: 51 | C51: 主分析 | D51: 1 | E51: 1 | F51: 172 | G51: 18–22岁 | H51: 男 | I51: 高中／中专／职高／技校 | J51: 过去3个月没有使用过 | K51: 1–2次 | L51: 1 | M51: 不确定 | N51: 明确均未尝试 | O51: 0 | P51: Q16无可能性填写；concern互斥混选 | Q51: 0 | R51: 0 | S51: 1 | T51: 0 | U51: 0 | V51: 均没有尝试过 | W51: (跳过) | X51: 明确均未尝试 | Y51: 1 | Z51: 1 | AA51: 0 | AB51: 0 | AC51: 1 | AD51: 0 | AE51: 1 | AF51: 0 | AG51: 1 | AH51: 0 | AI51: 1 | AJ51: 0 | AK51: 1 | AL51: 0 | AM51: 0 | AN51: 0 | AO51: 0 | AP51: 1 | AQ51: 0 | AX51: 0 | BG51: 0 | BU51: 0 | CF51: 1 | CG51: 0 | CH51: 1 | CI51: 0 | CJ51: 0 | CK51: 0 | CL51: 0 | CM51: 0 | CN51: 0 | CO51: 0 | CP51: 0
A52: 51 | B52: 52 | C52: 主分析 | D52: 1 | E52: 1 | F52: 137 | G52: 23–29岁 | H52: 不愿透露 | I52: 本科 | J52: 每周3–6天 | K52: 0次 | L52: 0 | M52: 没有 | N52: 明确均未尝试 | O52: 0 | P52: Q16无可能性填写；Q18最主要原因多选 | Q52: 0 | R52: 0 | S52: 1 | T52: 1 | U52: 0 | V52: 均没有尝试过 | W52: (跳过) | X52: 明确均未尝试 | Y52: 0 | AG52: 0 | AQ52: 0 | AX52: 0 | BG52: 0 | BU52: 1 | BV52: 0 | BW52: 0 | BX52: 0 | BY52: 0 | BZ52: 0 | CA52: 0 | CB52: 0 | CC52: 1 | CD52: 0 | CE52: 0 | CF52: 0
A53: 52 | B53: 53 | C53: 质量暂不纳入 | D53: 1 | E53: 0 | F53: 300 | G53: 23–29岁 | H53: 男 | I53: 不愿透露 | J53: 几乎每天 | K53: 1–2次 | L53: 1 | M53: 有 | N53: 可确认尝试 | O53: 0 | P53: Q15五填空整段跨记录重复，主分析暂不纳入；Q16无可能性填写；Q14行无法可靠匹配 | Q53: 1 | R53: 0 | S53: 1 | T53: 0 | U53: 1 | V53: 与他人交换周边 | W53: 尝试过，但未完成 | X53: 交换尝试记录 | Y53: 1 | Z53: 1 | AA53: 0 | AB53: 0 | AC53: 0 | AD53: 0 | AE53: 1 | AF53: 0 | AG53: 1 | AH53: 0 | AI53: 1 | AJ53: 0 | AK53: 0 | AL53: 0 | AM53: 0 | AN53: 0 | AO53: 0 | AP53: 0 | AQ53: 1 | AR53: 0 | AS53: 0 | AT53: 0 | AU53: 1 | AV53: 0 | AW53: 1 | AX53: 1 | AY53: 1 | AZ53: 0 | BA53: 0 | BB53: 0 | BC53: 0 | BD53: 0 | BE53: 0 | BF53: 0 | BG53: 0 | BU53: 1 | BV53: 0 | BW53: 0 | BX53: 0 | BY53: 0 | BZ53: 1 | CA53: 1 | CB53: 0 | CC53: 0 | CD53: 0 | CE53: 0 | CF53: 1 | CG53: 0 | CH53: 0 | CI53: 1 | CJ53: 0 | CK53: 0 | CL53: 0 | CM53: 0 | CN53: 0 | CO53: 0 | CP53: 0
A54: 53 | B54: 54 | C54: 质量暂不纳入 | D54: 1 | E54: 0 | F54: 150 | G54: 18–22岁 | H54: 女 | I54: 硕士研究生及以上 | J54: 每周3–6天 | K54: 1–2次 | L54: 1 | M54: 有 | N54: 可确认尝试 | O54: 0 | P54: Q15五填空整段跨记录重复，主分析暂不纳入；Q16无可能性填写；Q14行无法可靠匹配；Q18最主要原因多选 | Q54: 1 | R54: 0 | S54: 1 | T54: 1 | U54: 1 | V54: 出售个人周边 | W54: 尝试过，但未完成 | X54: 出售尝试记录 | Y54: 1 | Z54: 0 | AA54: 1 | AB54: 0 | AC54: 0 | AD54: 1 | AE54: 0 | AF54: 0 | AG54: 1 | AH54: 0 | AI54: 1 | AJ54: 0 | AK54: 1 | AL54: 0 | AM54: 0 | AN54: 0 | AO54: 0 | AP54: 1 | AQ54: 1 | AR54: 0 | AS54: 0 | AT54: 0 | AU54: 1 | AV54: 1 | AW54: 0 | AX54: 1 | AY54: 1 | AZ54: 1 | BA54: 0 | BB54: 0 | BC54: 0 | BD54: 0 | BE54: 0 | BF54: 1 | BG54: 0 | BU54: 1 | BV54: 1 | BW54: 0 | BX54: 1 | BY54: 0 | BZ54: 0 | CA54: 0 | CB54: 0 | CC54: 0 | CD54: 0 | CE54: 0 | CF54: 0
A55: 54 | B55: 55 | C55: 质量暂不纳入 | D55: 1 | E55: 0 | F55: 270 | G55: 23–29岁 | H55: 女 | I55: 本科 | J55: 几乎每天 | K55: 0次 | L55: 0 | M55: 没有 | N55: 可确认尝试 | O55: 0 | P55: Q15五填空整段跨记录重复，主分析暂不纳入；Q16无可能性填写；Q14行无法可靠匹配；concern互斥混选 | Q55: 1 | R55: 0 | S55: 1 | T55: 0 | U55: 1 | V55: 与他人交换周边 | W55: 尝试过，但未完成 | X55: 交换尝试记录 | Y55: 0 | AG55: 0 | AQ55: 0 | AX55: 1 | AY55: 1 | AZ55: 0 | BA55: 1 | BB55: 0 | BC55: 0 | BD55: 0 | BE55: 0 | BF55: 0 | BG55: 0 | BU55: 0 | CF55: 1 | CG55: 0 | CH55: 0 | CI55: 0 | CJ55: 0 | CK55: 0 | CL55: 0 | CM55: 0 | CN55: 1 | CO55: 0 | CP55: 0
A56: 55 | B56: 56 | C56: 主分析 | D56: 1 | E56: 1 | F56: 259 | G56: 23–29岁 | H56: 其他 | I56: 高中／中专／职高／技校 | J56: 每周3–6天 | K56: 0次 | L56: 0 | M56: 有 | N56: 明确均未尝试 | O56: 0 | P56: Q16无可能性填写 | Q56: 0 | R56: 0 | S56: 1 | T56: 0 | U56: 0 | V56: 均没有尝试过 | W56: (跳过) | X56: 明确均未尝试 | Y56: 0 | AG56: 0 | AQ56: 1 | AR56: 0 | AS56: 0 | AT56: 0 | AU56: 0 | AV56: 1 | AW56: 0 | AX56: 0 | BG56: 0 | BU56: 1 | BV56: 1 | BW56: 0 | BX56: 1 | BY56: 0 | BZ56: 0 | CA56: 0 | CB56: 0 | CC56: 0 | CD56: 0 | CE56: 0 | CF56: 1 | CG56: 0 | CH56: 0 | CI56: 0 | CJ56: 0 | CK56: 0 | CL56: 0 | CM56: 0 | CN56: 1 | CO56: 0 | CP56: 0
A57: 56 | B57: 57 | C57: 质量暂不纳入 | D57: 1 | E57: 0 | F57: 232 | G57: 23–29岁 | H57: 女 | I57: 硕士研究生及以上 | J57: 少于每周1天 | K57: 0次 | L57: 0 | M57: 没有 | N57: 可确认尝试 | O57: 0 | P57: Q15五填空整段跨记录重复，主分析暂不纳入；Q16无可能性填写；Q14行无法可靠匹配；Q18最主要原因多选 | Q57: 1 | R57: 0 | S57: 1 | T57: 1 | U57: 1 | V57: 出售个人周边 | W57: 尝试过，但未完成 | X57: 出售尝试记录 | Y57: 0 | AG57: 0 | AQ57: 0 | AX57: 1 | AY57: 0 | AZ57: 0 | BA57: 1 | BB57: 0 | BC57: 0 | BD57: 0 | BE57: 0 | BF57: 1 | BG57: 0 | BU57: 1 | BV57: 0 | BW57: 1 | BX57: 1 | BY57: 0 | BZ57: 0 | CA57: 0 | CB57: 0 | CC57: 0 | CD57: 0 | CE57: 0 | CF57: 0
A58: 57 | B58: 58 | C58: 主分析 | D58: 1 | E58: 1 | F58: 2796 | G58: 40岁及以上 | H58: 男 | I58: 本科 | J58: 每周3–6天 | K58: 6–11次 | L58: 1 | M58: 没有 | N58: 可确认尝试 | O58: 0 | P58: 同IP重复；仅标记；Q18最主要原因多选 | Q58: 0 | R58: 1 | S58: 0 | T58: 1 | U58: 0 | V58: 与他人交换周边 | W58: 完成6次及以上 | X58: 交换尝试记录 | Y58: 1 | Z58: 1 | AA58: 0 | AB58: 0 | AC58: 1 | AD58: 1 | AE58: 1 | AF58: 0 | AG58: 1 | AH58: 1 | AI58: 1 | AJ58: 0 | AK58: 1 | AL58: 0 | AM58: 0 | AN58: 1 | AO58: 0 | AP58: 1 | AQ58: 0 | AX58: 1 | AY58: 1 | AZ58: 1 | BA58: 0 | BB58: 0 | BC58: 0 | BD58: 1 | BE58: 0 | BF58: 1 | BG58: 1 | BH58: 1 | BI58: 0 | BJ58: 1 | BK58: 1 | BL58: 0 | BM58: 0 | BN58: 0 | BO58: 1 | BP58: 0 | BQ58: 1 | BR58: 0 | BS58: 0 | BT58: 1 | BU58: 1 | BV58: 1 | BW58: 1 | BX58: 1 | BY58: 0 | BZ58: 0 | CA58: 0 | CB58: 1 | CC58: 1 | CD58: 1 | CE58: 0 | CF58: 0 | CQ58: 4 | CR58: 比较可能 | CS58: 5 | CT58: 非常可能 | CU58: 4 | CV58: 比较可能 | CW58: 3 | CX58: 不确定
A59: 58 | B59: 59 | C59: 主分析 | D59: 1 | E59: 1 | F59: 265 | G59: 18–22岁 | H59: 女 | I59: 本科 | J59: 从未使用过B站 | K59: 6–11次 | L59: 1 | M59: 没有 | N59: 明确均未尝试 | O59: 0 | P59: Q16无可能性填写 | Q59: 0 | R59: 0 | S59: 1 | T59: 0 | U59: 0 | V59: 均没有尝试过 | W59: (跳过) | X59: 明确均未尝试 | Y59: 1 | Z59: 1 | AA59: 0 | AB59: 0 | AC59: 0 | AD59: 0 | AE59: 0 | AF59: 0 | AG59: 1 | AH59: 0 | AI59: 1 | AJ59: 0 | AK59: 0 | AL59: 0 | AM59: 0 | AN59: 1 | AO59: 0 | AP59: 0 | AQ59: 0 | AX59: 0 | BG59: 0 | BU59: 1 | BV59: 1 | BW59: 0 | BX59: 1 | BY59: 0 | BZ59: 1 | CA59: 0 | CB59: 0 | CC59: 0 | CD59: 0 | CE59: 0 | CF59: 1 | CG59: 0 | CH59: 0 | CI59: 0 | CJ59: 0 | CK59: 0 | CL59: 0 | CM59: 0 | CN59: 0 | CO59: 1 | CP59: 0
A60: 59 | B60: 60 | C60: 主分析 | D60: 1 | E60: 1 | F60: 271 | G60: 18–22岁 | H60: 女 | I60: 本科 | J60: 每周3–6天 | K60: 0次 | L60: 0 | M60: 有 | N60: 无法判断 | O60: 1 | P60: Q11尝试与Q12均未尝试冲突；Q16无可能性填写；Q18最主要原因多选 | Q60: 0 | R60: 0 | S60: 1 | T60: 1 | U60: 0 | V60: 均没有尝试过 | W60: (跳过) | X60: 无法判断 | Y60: 0 | AG60: 0 | AQ60: 0 | AX60: 0 | BG60: 0 | BU60: 1 | BV60: 0 | BW60: 1 | BX60: 0 | BY60: 0 | BZ60: 0 | CA60: 0 | CB60: 0 | CC60: 0 | CD60: 0 | CE60: 0 | CF60: 0
A61: 60 | B61: 61 | C61: 质量暂不纳入 | D61: 1 | E61: 0 | F61: 128 | G61: 23–29岁 | H61: 女 | I61: 本科 | J61: 过去3个月没有使用过 | K61: 0次 | L61: 0 | M61: 有 | N61: 无法判断 | O61: 0 | P61: Q15五填空整段跨记录重复，主分析暂不纳入；Q16无可能性填写；Q14行无法可靠匹配；Q18最主要原因多选 | Q61: 1 | R61: 0 | S61: 1 | T61: 1 | U61: 1 | V61: 出售个人周边 | W61: 没有尝试过 | X61: 无法判断 | Y61: 0 | AG61: 0 | AQ61: 1 | AR61: 1 | AS61: 0 | AT61: 0 | AU61: 1 | AV61: 1 | AW61: 0 | AX61: 0 | BG61: 0 | BU61: 1 | BV61: 0 | BW61: 0 | BX61: 1 | BY61: 0 | BZ61: 1 | CA61: 0 | CB61: 0 | CC61: 1 | CD61: 0 | CE61: 0 | CF61: 0
A62: 61 | B62: 62 | C62: 主分析 | D62: 1 | E62: 1 | F62: 141 | G62: 18–22岁 | H62: 男 | I62: 本科 | J62: 少于每周1天 | K62: 1–2次 | L62: 1 | M62: 没有 | N62: 明确均未尝试 | O62: 0 | P62: Q16无可能性填写 | Q62: 0 | R62: 0 | S62: 1 | T62: 0 | U62: 0 | V62: 均没有尝试过 | W62: (跳过) | X62: 明确均未尝试 | Y62: 1 | Z62: 1 | AA62: 0 | AB62: 0 | AC62: 1 | AD62: 1 | AE62: 0 | AF62: 0 | AG62: 1 | AH62: 0 | AI62: 1 | AJ62: 0 | AK62: 0 | AL62: 0 | AM62: 0 | AN62: 0 | AO62: 0 | AP62: 0 | AQ62: 0 | AX62: 0 | BG62: 0 | BU62: 1 | BV62: 1 | BW62: 0 | BX62: 0 | BY62: 0 | BZ62: 1 | CA62: 0 | CB62: 0 | CC62: 0 | CD62: 1 | CE62: 0 | CF62: 1 | CG62: 0 | CH62: 0 | CI62: 0 | CJ62: 0 | CK62: 0 | CL62: 0 | CM62: 1 | CN62: 0 | CO62: 0 | CP62: 0
A63: 62 | B63: 63 | C63: 主分析 | D63: 1 | E63: 1 | F63: 148 | G63: 23–29岁 | H63: 男 | I63: 本科 | J63: 几乎每天 | K63: 0次 | L63: 0 | M63: 有 | N63: 明确均未尝试 | O63: 0 | P63: Q16无可能性填写 | Q63: 0 | R63: 0 | S63: 1 | T63: 0 | U63: 0 | V63: 均没有尝试过 | W63: (跳过) | X63: 明确均未尝试 | Y63: 0 | AG63: 0 | AQ63: 1 | AR63: 0 | AS63: 0 | AT63: 0 | AU63: 0 | AV63: 1 | AW63: 0 | AX63: 0 | BG63: 0 | BU63: 1 | BV63: 0 | BW63: 0 | BX63: 1 | BY63: 0 | BZ63: 0 | CA63: 0 | CB63: 0 | CC63: 0 | CD63: 0 | CE63: 0 | CF63: 1 | CG63: 0 | CH63: 1 | CI63: 0 | CJ63: 0 | CK63: 0 | CL63: 0 | CM63: 0 | CN63: 0 | CO63: 0 | CP63: 0
A64: 63 | B64: 64 | C64: 质量暂不纳入 | D64: 1 | E64: 0 | F64: 288 | G64: 23–29岁 | H64: 女 | I64: 本科 | J64: 几乎每天 | K64: 买过，但记不清次数 | L64: 1 | M64: 没有 | N64: 可确认尝试 | O64: 0 | P64: Q15五填空整段跨记录重复，主分析暂不纳入；Q16无可能性填写；Q14行无法可靠匹配；Q18最主要原因多选 | Q64: 1 | R64: 0 | S64: 1 | T64: 1 | U64: 1 | V64: 与他人交换周边 | W64: 完成1–2次 | X64: 交换尝试记录 | Y64: 1 | Z64: 0 | AA64: 0 | AB64: 0 | AC64: 1 | AD64: 1 | AE64: 1 | AF64: 0 | AG64: 1 | AH64: 0 | AI64: 1 | AJ64: 0 | AK64: 0 | AL64: 0 | AM64: 0 | AN64: 0 | AO64: 0 | AP64: 0 | AQ64: 0 | AX64: 1 | AY64: 0 | AZ64: 0 | BA64: 0 | BB64: 0 | BC64: 0 | BD64: 0 | BE64: 0 | BF64: 1 | BG64: 0 | BU64: 1 | BV64: 0 | BW64: 0 | BX64: 1 | BY64: 0 | BZ64: 1 | CA64: 0 | CB64: 0 | CC64: 0 | CD64: 1 | CE64: 0 | CF64: 0
A65: 64 | B65: 65 | C65: 主分析 | D65: 1 | E65: 1 | F65: 219 | G65: 18–22岁 | H65: 男 | I65: 硕士研究生及以上 | J65: 几乎每天 | K65: 0次 | L65: 0 | M65: 有 | N65: 明确均未尝试 | O65: 0 | P65: Q16无可能性填写 | Q65: 0 | R65: 0 | S65: 1 | T65: 0 | U65: 0 | V65: 均没有尝试过 | W65: (跳过) | X65: 明确均未尝试 | Y65: 0 | AG65: 0 | AQ65: 1 | AR65: 0 | AS65: 0 | AT65: 0 | AU65: 0 | AV65: 1 | AW65: 0 | AX65: 0 | BG65: 0 | BU65: 1 | BV65: 0 | BW65: 0 | BX65: 1 | BY65: 0 | BZ65: 0 | CA65: 0 | CB65: 1 | CC65: 0 | CD65: 0 | CE65: 0 | CF65: 1 | CG65: 0 | CH65: 1 | CI65: 0 | CJ65: 0 | CK65: 0 | CL65: 0 | CM65: 0 | CN65: 0 | CO65: 0 | CP65: 0
A66: 65 | B66: 66 | C66: 质量暂不纳入 | D66: 1 | E66: 0 | F66: 246 | G66: 23–29岁 | H66: 男 | I66: 高中／中专／职高／技校 | J66: 几乎每天 | K66: 0次 | L66: 0 | M66: 没有 | N66: 可确认尝试 | O66: 0 | P66: Q15五填空整段跨记录重复，主分析暂不纳入；Q16无可能性填写；Q14行无法可靠匹配；Q18最主要原因多选 | Q66: 1 | R66: 0 | S66: 1 | T66: 1 | U66: 1 | V66: 出售个人周边 | W66: 完成3–5次 | X66: 出售尝试记录 | Y66: 0 | AG66: 0 | AQ66: 0 | AX66: 1 | AY66: 1 | AZ66: 0 | BA66: 0 | BB66: 0 | BC66: 0 | BD66: 0 | BE66: 0 | BF66: 0 | BG66: 0 | BU66: 1 | BV66: 0 | BW66: 1 | BX66: 0 | BY66: 0 | BZ66: 0 | CA66: 0 | CB66: 0 | CC66: 0 | CD66: 0 | CE66: 0 | CF66: 0
A67: 66 | B67: 67 | C67: 质量暂不纳入 | D67: 1 | E67: 0 | F67: 166 | G67: 30–39岁 | H67: 男 | I67: 本科 | J67: 几乎每天 | K67: 0次 | L67: 0 | M67: 不确定 | N67: 可确认尝试 | O67: 0 | P67: Q15五填空整段跨记录重复，主分析暂不纳入；Q16无可能性填写；Q14行无法可靠匹配 | Q67: 1 | R67: 0 | S67: 1 | T67: 0 | U67: 1 | V67: 与他人交换周边 | W67: 完成3–5次 | X67: 交换尝试记录 | Y67: 0 | AG67: 0 | AQ67: 0 | AX67: 1 | AY67: 1 | AZ67: 0 | BA67: 0 | BB67: 0 | BC67: 0 | BD67: 0 | BE67: 0 | BF67: 0 | BG67: 0 | BU67: 1 | BV67: 0 | BW67: 0 | BX67: 1 | BY67: 0 | BZ67: 0 | CA67: 0 | CB67: 0 | CC67: 0 | CD67: 0 | CE67: 0 | CF67: 1 | CG67: 0 | CH67: 0 | CI67: 1 | CJ67: 0 | CK67: 0 | CL67: 0 | CM67: 0 | CN67: 0 | CO67: 0 | CP67: 0
A68: 67 | B68: 68 | C68: 质量暂不纳入 | D68: 1 | E68: 0 | F68: 229 | G68: 18–22岁 | H68: 男 | I68: 本科 | J68: 几乎每天 | K68: 3–5次 | L68: 1 | M68: 有 | N68: 可确认尝试 | O68: 0 | P68: Q15五填空整段跨记录重复，主分析暂不纳入；Q16无可能性填写 | Q68: 1 | R68: 0 | S68: 1 | T68: 0 | U68: 0 | V68: 出售个人周边 | W68: 完成过，但记不清次数 | X68: 出售尝试记录 | Y68: 1 | Z68: 0 | AA68: 0 | AB68: 0 | AC68: 1 | AD68: 0 | AE68: 1 | AF68: 0 | AG68: 1 | AH68: 0 | AI68: 0 | AJ68: 0 | AK68: 1 | AL68: 1 | AM68: 0 | AN68: 0 | AO68: 0 | AP68: 1 | AQ68: 1 | AR68: 0 | AS68: 0 | AT68: 1 | AU68: 0 | AV68: 1 | AW68: 0 | AX68: 1 | AY68: 1 | AZ68: 0 | BA68: 0 | BB68: 0 | BC68: 0 | BD68: 0 | BE68: 0 | BF68: 0 | BG68: 1 | BH68: 0 | BI68: 0 | BJ68: 0 | BK68: 1 | BL68: 0 | BM68: 0 | BN68: 0 | BO68: 0 | BP68: 0 | BQ68: 0 | BR68: 0 | BS68: 0 | BT68: 0 | BU68: 1 | BV68: 0 | BW68: 0 | BX68: 1 | BY68: 0 | BZ68: 0 | CA68: 0 | CB68: 1 | CC68: 0 | CD68: 0 | CE68: 0 | CF68: 1 | CG68: 0 | CH68: 0 | CI68: 0 | CJ68: 1 | CK68: 0 | CL68: 0 | CM68: 0 | CN68: 0 | CO68: 0 | CP68: 0
A69: 68 | B69: 69 | C69: 主分析 | D69: 1 | E69: 1 | F69: 262 | G69: 18–22岁 | H69: 男 | I69: 大专 | J69: 几乎每天 | K69: 3–5次 | L69: 1 | M69: 有 | N69: 明确均未尝试 | O69: 0 | P69: Q16无可能性填写 | Q69: 0 | R69: 0 | S69: 1 | T69: 0 | U69: 0 | V69: 均没有尝试过 | W69: (跳过) | X69: 明确均未尝试 | Y69: 1 | Z69: 1 | AA69: 0 | AB69: 0 | AC69: 0 | AD69: 0 | AE69: 0 | AF69: 0 | AG69: 1 | AH69: 0 | AI69: 1 | AJ69: 0 | AK69: 1 | AL69: 0 | AM69: 0 | AN69: 0 | AO69: 0 | AP69: 0 | AQ69: 1 | AR69: 0 | AS69: 0 | AT69: 0 | AU69: 0 | AV69: 1 | AW69: 0 | AX69: 0 | BG69: 0 | BU69: 1 | BV69: 1 | BW69: 1 | BX69: 0 | BY69: 0 | BZ69: 0 | CA69: 1 | CB69: 0 | CC69: 0 | CD69: 1 | CE69: 0 | CF69: 1 | CG69: 0 | CH69: 0 | CI69: 0 | CJ69: 0 | CK69: 0 | CL69: 0 | CM69: 0 | CN69: 1 | CO69: 0 | CP69: 0
A70: 69 | B70: 70 | C70: 主分析 | D70: 1 | E70: 1 | F70: 233 | G70: 18–22岁 | H70: 女 | I70: 高中／中专／职高／技校 | J70: 几乎每天 | K70: 0次 | L70: 0 | M70: 不确定 | N70: 明确均未尝试 | O70: 0 | P70: Q16无可能性填写 | Q70: 0 | R70: 0 | S70: 1 | T70: 0 | U70: 0 | V70: 均没有尝试过 | W70: (跳过) | X70: 明确均未尝试 | Y70: 0 | AG70: 0 | AQ70: 0 | AX70: 0 | BG70: 0 | BU70: 1 | BV70: 0 | BW70: 0 | BX70: 0 | BY70: 1 | BZ70: 0 | CA70: 0 | CB70: 0 | CC70: 0 | CD70: 0 | CE70: 0 | CF70: 1 | CG70: 0 | CH70: 0 | CI70: 1 | CJ70: 0 | CK70: 0 | CL70: 0 | CM70: 0 | CN70: 0 | CO70: 0 | CP70: 0
A71: 70 | B71: 71 | C71: 主分析 | D71: 1 | E71: 1 | F71: 293 | G71: 18–22岁 | H71: 男 | I71: 本科 | J71: 几乎每天 | K71: 0次 | L71: 0 | M71: 不确定 | N71: 明确均未尝试 | O71: 0 | P71: Q16无可能性填写；concern互斥混选 | Q71: 0 | R71: 0 | S71: 1 | T71: 0 | U71: 0 | V71: 均没有尝试过 | W71: (跳过) | X71: 明确均未尝试 | Y71: 0 | AG71: 0 | AQ71: 0 | AX71: 0 | BG71: 0 | BU71: 0 | CF71: 1 | CG71: 1 | CH71: 0 | CI71: 0 | CJ71: 0 | CK71: 0 | CL71: 0 | CM71: 0 | CN71: 0 | CO71: 0 | CP71: 0
A72: 71 | B72: 72 | C72: 质量暂不纳入 | D72: 1 | E72: 0 | F72: 142 | G72: 18–22岁 | H72: 其他 | I72: 硕士研究生及以上 | J72: 几乎每天 | K72: 0次 | L72: 0 | M72: 没有 | N72: 无法判断 | O72: 0 | P72: Q15五填空整段跨记录重复，主分析暂不纳入；Q16无可能性填写 | Q72: 1 | R72: 0 | S72: 1 | T72: 0 | U72: 0 | V72: 出售个人周边 | W72: 没有尝试过 | X72: 无法判断 | Y72: 0 | AG72: 0 | AQ72: 0 | AX72: 0 | BG72: 0 | BU72: 1 | BV72: 1 | BW72: 0 | BX72: 0 | BY72: 0 | BZ72: 0 | CA72: 0 | CB72: 0 | CC72: 1 | CD72: 0 | CE72: 0 | CF72: 1 | CG72: 0 | CH72: 0 | CI72: 0 | CJ72: 0 | CK72: 0 | CL72: 0 | CM72: 0 | CN72: 1 | CO72: 0 | CP72: 0
A73: 72 | B73: 73 | C73: 主分析 | D73: 1 | E73: 1 | F73: 227 | G73: 18–22岁 | H73: 女 | I73: 本科 | J73: 几乎每天 | K73: 0次 | L73: 0 | M73: 有 | N73: 无法判断 | O73: 1 | P73: Q11尝试与Q12均未尝试冲突；Q16无可能性填写；Q18最主要原因多选；concern互斥混选 | Q73: 0 | R73: 0 | S73: 1 | T73: 1 | U73: 0 | V73: 均没有尝试过 | W73: (跳过) | X73: 无法判断 | Y73: 0 | AG73: 0 | AQ73: 0 | AX73: 0 | BG73: 0 | BU73: 0 | CF73: 0
A74: 73 | B74: 74 | C74: 主分析 | D74: 1 | E74: 1 | F74: 285 | G74: 30–39岁 | H74: 男 | I74: 本科 | J74: 每周3–6天 | K74: 0次 | L74: 0 | M74: 没有 | N74: 明确均未尝试 | O74: 0 | P74: Q16无可能性填写 | Q74: 0 | R74: 0 | S74: 1 | T74: 0 | U74: 0 | V74: 均没有尝试过 | W74: (跳过) | X74: 明确均未尝试 | Y74: 0 | AG74: 0 | AQ74: 0 | AX74: 0 | BG74: 0 | BU74: 1 | BV74: 0 | BW74: 0 | BX74: 1 | BY74: 0 | BZ74: 0 | CA74: 0 | CB74: 0 | CC74: 0 | CD74: 0 | CE74: 0 | CF74: 1 | CG74: 0 | CH74: 0 | CI74: 0 | CJ74: 1 | CK74: 0 | CL74: 0 | CM74: 0 | CN74: 0 | CO74: 0 | CP74: 0
A75: 74 | B75: 75 | C75: 主分析 | D75: 1 | E75: 1 | F75: 232 | G75: 不愿透露 | H75: 女 | I75: 本科 | J75: 每周3–6天 | K75: 0次 | L75: 0 | M75: 有 | N75: 明确均未尝试 | O75: 0 | P75: 年龄未披露，资格未完全核实；Q16无可能性填写 | Q75: 0 | R75: 0 | S75: 1 | T75: 0 | U75: 0 | V75: 均没有尝试过 | W75: (跳过) | X75: 明确均未尝试 | Y75: 0 | AG75: 0 | AQ75: 1 | AR75: 0 | AS75: 0 | AT75: 0 | AU75: 0 | AV75: 1 | AW75: 0 | AX75: 0 | BG75: 0 | BU75: 1 | BV75: 0 | BW75: 0 | BX75: 0 | BY75: 0 | BZ75: 0 | CA75: 0 | CB75: 0 | CC75: 0 | CD75: 1 | CE75: 0 | CF75: 1 | CG75: 0 | CH75: 0 | CI75: 0 | CJ75: 0 | CK75: 0 | CL75: 0 | CM75: 0 | CN75: 0 | CO75: 1 | CP75: 0
A76: 75 | B76: 76 | C76: 质量暂不纳入 | D76: 1 | E76: 0 | F76: 163 | G76: 30–39岁 | H76: 女 | I76: 本科 | J76: 几乎每天 | K76: 6–11次 | L76: 1 | M76: 不确定 | N76: 无法判断 | O76: 0 | P76: Q15五填空整段跨记录重复，主分析暂不纳入；Q16无可能性填写；Q14行无法可靠匹配 | Q76: 1 | R76: 0 | S76: 1 | T76: 0 | U76: 1 | V76: 出售个人周边 | W76: 没有尝试过 | X76: 无法判断 | Y76: 1 | Z76: 0 | AA76: 0 | AB76: 0 | AC76: 1 | AD76: 0 | AE76: 0 | AF76: 0 | AG76: 1 | AH76: 0 | AI76: 0 | AJ76: 0 | AK76: 1 | AL76: 0 | AM76: 0 | AN76: 0 | AO76: 0 | AP76: 1 | AQ76: 0 | AX76: 0 | BG76: 0 | BU76: 1 | BV76: 0 | BW76: 0 | BX76: 1 | BY76: 0 | BZ76: 0 | CA76: 0 | CB76: 1 | CC76: 0 | CD76: 0 | CE76: 0 | CF76: 1 | CG76: 0 | CH76: 1 | CI76: 0 | CJ76: 0 | CK76: 0 | CL76: 0 | CM76: 0 | CN76: 0 | CO76: 0 | CP76: 0
A77: 76 | B77: 77 | C77: 主分析 | D77: 1 | E77: 1 | F77: 153 | G77: 18–22岁 | H77: 其他 | I77: 本科 | J77: 几乎每天 | K77: 0次 | L77: 0 | M77: 不确定 | N77: 明确均未尝试 | O77: 0 | P77: Q16无可能性填写 | Q77: 0 | R77: 0 | S77: 1 | T77: 0 | U77: 0 | V77: 均没有尝试过 | W77: (跳过) | X77: 明确均未尝试 | Y77: 0 | AG77: 0 | AQ77: 0 | AX77: 0 | BG77: 0 | BU77: 1 | BV77: 0 | BW77: 0 | BX77: 0 | BY77: 0 | BZ77: 0 | CA77: 0 | CB77: 0 | CC77: 0 | CD77: 1 | CE77: 0 | CF77: 1 | CG77: 0 | CH77: 0 | CI77: 1 | CJ77: 0 | CK77: 0 | CL77: 0 | CM77: 0 | CN77: 0 | CO77: 0 | CP77: 0
A78: 77 | B78: 78 | C78: 主分析 | D78: 1 | E78: 1 | F78: 278 | G78: 23–29岁 | H78: 男 | I78: 硕士研究生及以上 | J78: 几乎每天 | K78: 6–11次 | L78: 1 | M78: 有 | N78: 明确均未尝试 | O78: 0 | P78: Q16无可能性填写；Q18最主要原因多选 | Q78: 0 | R78: 0 | S78: 1 | T78: 1 | U78: 0 | V78: 均没有尝试过 | W78: (跳过) | X78: 明确均未尝试 | Y78: 1 | Z78: 0 | AA78: 0 | AB78: 0 | AC78: 1 | AD78: 0 | AE78: 1 | AF78: 0 | AG78: 1 | AH78: 0 | AI78: 0 | AJ78: 0 | AK78: 1 | AL78: 0 | AM78: 0 | AN78: 0 | AO78: 0 | AP78: 1 | AQ78: 1 | AR78: 1 | AS78: 0 | AT78: 0 | AU78: 0 | AV78: 1 | AW78: 0 | AX78: 0 | BG78: 0 | BU78: 1 | BV78: 1 | BW78: 0 | BX78: 0 | BY78: 0 | BZ78: 0 | CA78: 0 | CB78: 1 | CC78: 0 | CD78: 1 | CE78: 0 | CF78: 0
A79: 78 | B79: 79 | C79: 质量暂不纳入 | D79: 1 | E79: 0 | F79: 200 | G79: 23–29岁 | H79: 女 | I79: 大专 | J79: 几乎每天 | K79: 1–2次 | L79: 1 | M79: 不确定 | N79: 可确认尝试 | O79: 0 | P79: Q15五填空整段跨记录重复，主分析暂不纳入；Q16无可能性填写；Q14行无法可靠匹配；Q18最主要原因多选 | Q79: 1 | R79: 0 | S79: 1 | T79: 1 | U79: 1 | V79: 与他人交换周边 | W79: 完成1–2次 | X79: 交换尝试记录 | Y79: 1 | Z79: 1 | AA79: 0 | AB79: 0 | AC79: 1 | AD79: 0 | AE79: 0 | AF79: 0 | AG79: 1 | AH79: 1 | AI79: 1 | AJ79: 0 | AK79: 0 | AL79: 0 | AM79: 0 | AN79: 0 | AO79: 0 | AP79: 1 | AQ79: 0 | AX79: 1 | AY79: 1 | AZ79: 1 | BA79: 0 | BB79: 0 | BC79: 0 | BD79: 0 | BE79: 0 | BF79: 0 | BG79: 0 | BU79: 1 | BV79: 1 | BW79: 0 | BX79: 0 | BY79: 0 | BZ79: 1 | CA79: 0 | CB79: 0 | CC79: 0 | CD79: 0 | CE79: 0 | CF79: 0
A80: 79 | B80: 80 | C80: 主分析 | D80: 1 | E80: 1 | F80: 195 | G80: 23–29岁 | H80: 男 | I80: 本科 | J80: 每周1–2天 | K80: 3–5次 | L80: 1 | M80: 没有 | N80: 可确认尝试 | O80: 0 | P80: Q14行无法可靠匹配；Q16第3项用词歧义 | Q80: 0 | R80: 0 | S80: 0 | T80: 0 | U80: 1 | V80: 与他人交换周边 | W80: 完成1–2次 | X80: 交换尝试记录 | Y80: 1 | Z80: 1 | AA80: 0 | AB80: 0 | AC80: 0 | AD80: 0 | AE80: 0 | AF80: 0 | AG80: 1 | AH80: 1 | AI80: 0 | AJ80: 0 | AK80: 0 | AL80: 0 | AM80: 0 | AN80: 0 | AO80: 0 | AP80: 0 | AQ80: 0 | AX80: 1 | AY80: 0 | AZ80: 0 | BA80: 1 | BB80: 0 | BC80: 0 | BD80: 0 | BE80: 0 | BF80: 0 | BG80: 0 | BU80: 1 | BV80: 1 | BW80: 1 | BX80: 1 | BY80: 0 | BZ80: 0 | CA80: 0 | CB80: 0 | CC80: 0 | CD80: 0 | CE80: 0 | CF80: 1 | CG80: 0 | CH80: 0 | CI80: 0 | CJ80: 0 | CK80: 0 | CL80: 1 | CM80: 0 | CN80: 0 | CO80: 0 | CP80: 0 | CV80: 不确定啊
A81: 80 | B81: 81 | C81: 质量暂不纳入 | D81: 1 | E81: 0 | F81: 202 | G81: 23–29岁 | H81: 女 | I81: 初中及以下 | J81: 每周1–2天 | K81: 0次 | L81: 0 | M81: 有 | N81: 可确认尝试 | O81: 0 | P81: Q15五填空整段跨记录重复，主分析暂不纳入；Q16无可能性填写；Q14行无法可靠匹配；Q18最主要原因多选；barrier互斥混选 | Q81: 1 | R81: 0 | S81: 1 | T81: 1 | U81: 1 | V81: 出售个人周边 | W81: 尝试过，但未完成 | X81: 出售尝试记录 | Y81: 0 | AG81: 0 | AQ81: 1 | AR81: 0 | AS81: 0 | AT81: 1 | AU81: 0 | AV81: 0 | AW81: 0 | AX81: 1 | AY81: 1 | AZ81: 0 | BA81: 0 | BB81: 0 | BC81: 0 | BD81: 0 | BE81: 0 | BF81: 0 | BG81: 0 | BU81: 1 | BV81: 0 | BW81: 0 | BX81: 1 | BY81: 0 | BZ81: 1 | CA81: 0 | CB81: 0 | CC81: 0 | CD81: 0 | CE81: 0 | CF81: 0
A82: 81 | B82: 82 | C82: 质量暂不纳入 | D82: 1 | E82: 0 | F82: 212 | G82: 18–22岁 | H82: 不愿透露 | I82: 大专 | J82: 每周1–2天 | K82: 0次 | L82: 0 | M82: 有 | N82: 无法判断 | O82: 0 | P82: Q15五填空整段跨记录重复，主分析暂不纳入；Q16无可能性填写；Q14行无法可靠匹配 | Q82: 1 | R82: 0 | S82: 1 | T82: 0 | U82: 1 | V82: 出售个人周边 | W82: 没有尝试过 | X82: 无法判断 | Y82: 0 | AG82: 0 | AQ82: 1 | AR82: 0 | AS82: 0 | AT82: 0 | AU82: 0 | AV82: 1 | AW82: 0 | AX82: 0 | BG82: 0 | BU82: 1 | BV82: 0 | BW82: 0 | BX82: 0 | BY82: 0 | BZ82: 0 | CA82: 1 | CB82: 0 | CC82: 0 | CD82: 0 | CE82: 0 | CF82: 1 | CG82: 0 | CH82: 0 | CI82: 0 | CJ82: 0 | CK82: 0 | CL82: 0 | CM82: 0 | CN82: 0 | CO82: 1 | CP82: 0
A83: 82 | B83: 83 | C83: 主分析 | D83: 1 | E83: 1 | F83: 209 | G83: 18–22岁 | H83: 女 | I83: 本科 | J83: 从未使用过B站 | K83: 0次 | L83: 0 | M83: 不确定 | N83: 明确均未尝试 | O83: 0 | P83: Q16无可能性填写 | Q83: 0 | R83: 0 | S83: 1 | T83: 0 | U83: 0 | V83: 均没有尝试过 | W83: (跳过) | X83: 明确均未尝试 | Y83: 0 | AG83: 0 | AQ83: 0 | AX83: 0 | BG83: 0 | BU83: 1 | BV83: 0 | BW83: 1 | BX83: 0 | BY83: 0 | BZ83: 0 | CA83: 0 | CB83: 0 | CC83: 0 | CD83: 0 | CE83: 0 | CF83: 1 | CG83: 0 | CH83: 0 | CI83: 0 | CJ83: 0 | CK83: 0 | CL83: 0 | CM83: 0 | CN83: 0 | CO83: 1 | CP83: 0
A84: 83 | B84: 84 | C84: 主分析 | D84: 1 | E84: 1 | F84: 354 | G84: 30–39岁 | H84: 男 | I84: 本科 | J84: 几乎每天 | K84: 1–2次 | L84: 1 | M84: 不确定 | N84: 可确认尝试 | O84: 0 | P84: Q14行无法可靠匹配；Q18最主要原因多选；Q16第1项用词歧义；Q16第3项用词歧义 | Q84: 0 | R84: 0 | S84: 0 | T84: 1 | U84: 1 | V84: 与他人交换周边 | W84: 尝试过，但未完成 | X84: 交换尝试记录 | Y84: 1 | Z84: 1 | AA84: 0 | AB84: 0 | AC84: 0 | AD84: 0 | AE84: 0 | AF84: 0 | AG84: 1 | AH84: 1 | AI84: 0 | AJ84: 0 | AK84: 0 | AL84: 0 | AM84: 0 | AN84: 0 | AO84: 0 | AP84: 1 | AQ84: 0 | AX84: 1 | AY84: 0 | AZ84: 1 | BA84: 0 | BB84: 0 | BC84: 0 | BD84: 0 | BE84: 0 | BF84: 1 | BG84: 0 | BU84: 1 | BV84: 0 | BW84: 0 | BX84: 0 | BY84: 0 | BZ84: 0 | CA84: 0 | CB84: 0 | CC84: 1 | CD84: 1 | CE84: 0 | CF84: 0 | CR84: 确定 | CS84: 3 | CT84: 不确定 | CV84: 比较确定 | CW84: 5 | CX84: 非常可能
A85: 84 | B85: 85 | C85: 质量暂不纳入 | D85: 1 | E85: 0 | F85: 160 | G85: 18–22岁 | H85: 男 | I85: 高中／中专／职高／技校 | J85: 几乎每天 | K85: 3–5次 | L85: 1 | M85: 有 | N85: 无法判断 | O85: 0 | P85: Q15五填空整段跨记录重复，主分析暂不纳入；Q16无可能性填写；Q14行无法可靠匹配；Q18最主要原因多选 | Q85: 1 | R85: 0 | S85: 1 | T85: 1 | U85: 1 | V85: 与他人交换周边 | W85: 没有尝试过 | X85: 无法判断 | Y85: 1 | Z85: 0 | AA85: 0 | AB85: 0 | AC85: 0 | AD85: 1 | AE85: 1 | AF85: 0 | AG85: 1 | AH85: 0 | AI85: 1 | AJ85: 0 | AK85: 0 | AL85: 0 | AM85: 0 | AN85: 0 | AO85: 0 | AP85: 1 | AQ85: 1 | AR85: 0 | AS85: 0 | AT85: 0 | AU85: 1 | AV85: 0 | AW85: 0 | AX85: 0 | BG85: 0 | BU85: 1 | BV85: 0 | BW85: 0 | BX85: 1 | BY85: 0 | BZ85: 0 | CA85: 0 | CB85: 0 | CC85: 0 | CD85: 0 | CE85: 0 | CF85: 0
A86: 85 | B86: 86 | C86: 质量暂不纳入 | D86: 1 | E86: 0 | F86: 181 | G86: 18–22岁 | H86: 女 | I86: 大专 | J86: 几乎每天 | K86: 0次 | L86: 0 | M86: 有 | N86: 无法判断 | O86: 0 | P86: Q15五填空整段跨记录重复，主分析暂不纳入；Q16无可能性填写 | Q86: 1 | R86: 0 | S86: 1 | T86: 0 | U86: 0 | V86: 出售个人周边 | W86: 没有尝试过 | X86: 无法判断 | Y86: 0 | AG86: 0 | AQ86: 1 | AR86: 0 | AS86: 0 | AT86: 1 | AU86: 0 | AV86: 0 | AW86: 0 | AX86: 0 | BG86: 0 | BU86: 1 | BV86: 0 | BW86: 0 | BX86: 1 | BY86: 0 | BZ86: 0 | CA86: 0 | CB86: 0 | CC86: 0 | CD86: 0 | CE86: 0 | CF86: 1 | CG86: 0 | CH86: 0 | CI86: 0 | CJ86: 0 | CK86: 0 | CL86: 0 | CM86: 0 | CN86: 0 | CO86: 1 | CP86: 0
A87: 86 | B87: 87 | C87: 质量暂不纳入 | D87: 1 | E87: 0 | F87: 226 | G87: 18–22岁 | H87: 女 | I87: 大专 | J87: 少于每周1天 | K87: 1–2次 | L87: 1 | M87: 没有 | N87: 无法判断 | O87: 0 | P87: Q15五填空整段跨记录重复，主分析暂不纳入；Q16无可能性填写；Q14行无法可靠匹配 | Q87: 1 | R87: 0 | S87: 1 | T87: 0 | U87: 1 | V87: 与他人交换周边 | W87: 没有尝试过 | X87: 无法判断 | Y87: 1 | Z87: 1 | AA87: 0 | AB87: 1 | AC87: 0 | AD87: 0 | AE87: 1 | AF87: 0 | AG87: 1 | AH87: 0 | AI87: 1 | AJ87: 0 | AK87: 0 | AL87: 0 | AM87: 0 | AN87: 0 | AO87: 0 | AP87: 1 | AQ87: 0 | AX87: 0 | BG87: 0 | BU87: 1 | BV87: 1 | BW87: 1 | BX87: 1 | BY87: 0 | BZ87: 0 | CA87: 0 | CB87: 0 | CC87: 1 | CD87: 0 | CE87: 0 | CF87: 1 | CG87: 0 | CH87: 0 | CI87: 0 | CJ87: 0 | CK87: 0 | CL87: 0 | CM87: 0 | CN87: 0 | CO87: 1 | CP87: 0
A88: 87 | B88: 88 | C88: 质量暂不纳入 | D88: 1 | E88: 0 | F88: 236 | G88: 23–29岁 | H88: 男 | I88: 本科 | J88: 几乎每天 | K88: 12次及以上 | L88: 1 | M88: 没有 | N88: 可确认尝试 | O88: 0 | P88: Q15五填空整段跨记录重复，主分析暂不纳入；Q16无可能性填写；Q14行无法可靠匹配；concern互斥混选 | Q88: 1 | R88: 0 | S88: 1 | T88: 0 | U88: 1 | V88: 出售个人周边 | W88: 完成3–5次 | X88: 出售尝试记录 | Y88: 1 | Z88: 0 | AA88: 0 | AB88: 1 | AC88: 1 | AD88: 0 | AE88: 0 | AF88: 0 | AG88: 1 | AH88: 0 | AI88: 0 | AJ88: 0 | AK88: 0 | AL88: 0 | AM88: 0 | AN88: 0 | AO88: 0 | AP88: 1 | AQ88: 0 | AX88: 1 | AY88: 1 | AZ88: 1 | BA88: 0 | BB88: 0 | BC88: 0 | BD88: 0 | BE88: 0 | BF88: 1 | BG88: 0 | BU88: 0 | CF88: 1 | CG88: 0 | CH88: 0 | CI88: 1 | CJ88: 0 | CK88: 0 | CL88: 0 | CM88: 0 | CN88: 0 | CO88: 0 | CP88: 0
A89: 88 | B89: 89 | C89: 质量暂不纳入 | D89: 1 | E89: 0 | F89: 210 | G89: 不愿透露 | H89: 男 | I89: 高中／中专／职高／技校 | J89: 几乎每天 | K89: 0次 | L89: 0 | M89: 没有 | N89: 可确认尝试 | O89: 0 | P89: Q15五填空整段跨记录重复，主分析暂不纳入；年龄未披露，资格未完全核实；Q16无可能性填写 | Q89: 1 | R89: 0 | S89: 1 | T89: 0 | U89: 0 | V89: 出售个人周边 | W89: 完成6次及以上 | X89: 出售尝试记录 | Y89: 0 | AG89: 0 | AQ89: 0 | AX89: 1 | AY89: 0 | AZ89: 0 | BA89: 0 | BB89: 0 | BC89: 1 | BD89: 1 | BE89: 0 | BF89: 1 | BG89: 1 | BH89: 0 | BI89: 0 | BJ89: 0 | BK89: 0 | BL89: 0 | BM89: 0 | BN89: 0 | BO89: 0 | BP89: 0 | BQ89: 1 | BR89: 1 | BS89: 0 | BT89: 0 | BU89: 1 | BV89: 1 | BW89: 1 | BX89: 1 | BY89: 0 | BZ89: 1 | CA89: 0 | CB89: 0 | CC89: 0 | CD89: 0 | CE89: 0 | CF89: 1 | CG89: 0 | CH89: 0 | CI89: 1 | CJ89: 0 | CK89: 0 | CL89: 0 | CM89: 0 | CN89: 0 | CO89: 0 | CP89: 0
A90: 89 | B90: 90 | C90: 主分析 | D90: 1 | E90: 1 | F90: 251 | G90: 18–22岁 | H90: 男 | I90: 本科 | J90: 少于每周1天 | K90: 6–11次 | L90: 1 | M90: 不确定 | N90: 明确均未尝试 | O90: 0 | P90: Q16无可能性填写 | Q90: 0 | R90: 0 | S90: 1 | T90: 0 | U90: 0 | V90: 均没有尝试过 | W90: (跳过) | X90: 明确均未尝试 | Y90: 1 | Z90: 0 | AA90: 0 | AB90: 1 | AC90: 1 | AD90: 1 | AE90: 0 | AF90: 0 | AG90: 1 | AH90: 0 | AI90: 1 | AJ90: 0 | AK90: 0 | AL90: 1 | AM90: 0 | AN90: 1 | AO90: 0 | AP90: 1 | AQ90: 0 | AX90: 0 | BG90: 0 | BU90: 1 | BV90: 0 | BW90: 0 | BX90: 0 | BY90: 0 | BZ90: 0 | CA90: 1 | CB90: 0 | CC90: 0 | CD90: 0 | CE90: 0 | CF90: 1 | CG90: 0 | CH90: 1 | CI90: 0 | CJ90: 0 | CK90: 0 | CL90: 0 | CM90: 0 | CN90: 0 | CO90: 0 | CP90: 0
A91: 90 | B91: 91 | C91: 质量暂不纳入 | D91: 1 | E91: 0 | F91: 190 | G91: 18–22岁 | H91: 男 | I91: 大专 | J91: 每周1–2天 | K91: 3–5次 | L91: 1 | M91: 没有 | N91: 无法判断 | O91: 0 | P91: Q15五填空整段跨记录重复，主分析暂不纳入；Q16无可能性填写；Q18最主要原因多选 | Q91: 1 | R91: 0 | S91: 1 | T91: 1 | U91: 0 | V91: 出售个人周边 | W91: 没有尝试过 | X91: 无法判断 | Y91: 1 | Z91: 0 | AA91: 0 | AB91: 1 | AC91: 0 | AD91: 0 | AE91: 0 | AF91: 0 | AG91: 1 | AH91: 0 | AI91: 1 | AJ91: 0 | AK91: 0 | AL91: 0 | AM91: 0 | AN91: 0 | AO91: 0 | AP91: 0 | AQ91: 0 | AX91: 0 | BG91: 0 | BU91: 1 | BV91: 0 | BW91: 1 | BX91: 0 | BY91: 0 | BZ91: 0 | CA91: 0 | CB91: 0 | CC91: 0 | CD91: 1 | CE91: 0 | CF91: 0
A92: 91 | B92: 92 | C92: 主分析 | D92: 1 | E92: 1 | F92: 163 | G92: 23–29岁 | H92: 男 | I92: 本科 | J92: 从未使用过B站 | K92: 0次 | L92: 0 | M92: 没有 | N92: 明确均未尝试 | O92: 0 | P92: Q16无可能性填写；concern互斥混选 | Q92: 0 | R92: 0 | S92: 1 | T92: 0 | U92: 0 | V92: 均没有尝试过 | W92: (跳过) | X92: 明确均未尝试 | Y92: 0 | AG92: 0 | AQ92: 0 | AX92: 0 | BG92: 0 | BU92: 0 | CF92: 1 | CG92: 0 | CH92: 0 | CI92: 0 | CJ92: 1 | CK92: 0 | CL92: 0 | CM92: 0 | CN92: 0 | CO92: 0 | CP92: 0
A93: 92 | B93: 93 | C93: 质量暂不纳入 | D93: 1 | E93: 0 | F93: 229 | G93: 18–22岁 | H93: 女 | I93: 本科 | J93: 每周3–6天 | K93: 0次 | L93: 0 | M93: 没有 | N93: 无法判断 | O93: 0 | P93: Q15五填空整段跨记录重复，主分析暂不纳入；Q16无可能性填写 | Q93: 1 | R93: 0 | S93: 1 | T93: 0 | U93: 0 | V93: 出售个人周边 | W93: 没有尝试过 | X93: 无法判断 | Y93: 0 | AG93: 0 | AQ93: 0 | AX93: 0 | BG93: 0 | BU93: 1 | BV93: 1 | BW93: 1 | BX93: 0 | BY93: 0 | BZ93: 0 | CA93: 0 | CB93: 0 | CC93: 0 | CD93: 0 | CE93: 0 | CF93: 1 | CG93: 0 | CH93: 0 | CI93: 0 | CJ93: 0 | CK93: 0 | CL93: 0 | CM93: 0 | CN93: 0 | CO93: 1 | CP93: 0
A94: 93 | B94: 94 | C94: 质量暂不纳入 | D94: 1 | E94: 0 | F94: 190 | G94: 23–29岁 | H94: 男 | I94: 本科 | J94: 几乎每天 | K94: 0次 | L94: 0 | M94: 没有 | N94: 无法判断 | O94: 0 | P94: Q15五填空整段跨记录重复，主分析暂不纳入；Q16无可能性填写；Q14行无法可靠匹配；concern互斥混选 | Q94: 1 | R94: 0 | S94: 1 | T94: 0 | U94: 1 | V94: 出售个人周边 | W94: 没有尝试过 | X94: 无法判断 | Y94: 0 | AG94: 0 | AQ94: 0 | AX94: 0 | BG94: 0 | BU94: 0 | CF94: 1 | CG94: 0 | CH94: 1 | CI94: 0 | CJ94: 0 | CK94: 0 | CL94: 0 | CM94: 0 | CN94: 0 | CO94: 0 | CP94: 0
A95: 94 | B95: 95 | C95: 质量暂不纳入 | D95: 1 | E95: 0 | F95: 248 | G95: 不愿透露 | H95: 女 | I95: 本科 | J95: 每周3–6天 | K95: 0次 | L95: 0 | M95: 有 | N95: 无法判断 | O95: 0 | P95: Q15五填空整段跨记录重复，主分析暂不纳入；年龄未披露，资格未完全核实；Q16无可能性填写；Q14行无法可靠匹配；Q18最主要原因多选 | Q95: 1 | R95: 0 | S95: 1 | T95: 1 | U95: 1 | V95: 出售个人周边 | W95: 没有尝试过 | X95: 无法判断 | Y95: 0 | AG95: 0 | AQ95: 1 | AR95: 0 | AS95: 0 | AT95: 0 | AU95: 0 | AV95: 0 | AW95: 1 | AX95: 0 | BG95: 0 | BU95: 1 | BV95: 1 | BW95: 0 | BX95: 0 | BY95: 0 | BZ95: 0 | CA95: 0 | CB95: 0 | CC95: 0 | CD95: 0 | CE95: 0 | CF95: 0
A96: 95 | B96: 96 | C96: 质量暂不纳入 | D96: 1 | E96: 0 | F96: 251 | G96: 23–29岁 | H96: 男 | I96: 本科 | J96: 过去3个月没有使用过 | K96: 0次 | L96: 0 | M96: 不确定 | N96: 可确认尝试 | O96: 0 | P96: Q15五填空整段跨记录重复，主分析暂不纳入；Q16无可能性填写；Q14行无法可靠匹配 | Q96: 1 | R96: 0 | S96: 1 | T96: 0 | U96: 1 | V96: 与他人交换周边 | W96: 完成3–5次 | X96: 交换尝试记录 | Y96: 0 | AG96: 0 | AQ96: 0 | AX96: 1 | AY96: 0 | AZ96: 0 | BA96: 0 | BB96: 0 | BC96: 0 | BD96: 0 | BE96: 0 | BF96: 1 | BG96: 0 | BU96: 1 | BV96: 0 | BW96: 1 | BX96: 0 | BY96: 0 | BZ96: 0 | CA96: 0 | CB96: 0 | CC96: 0 | CD96: 0 | CE96: 0 | CF96: 1 | CG96: 0 | CH96: 0 | CI96: 0 | CJ96: 0 | CK96: 0 | CL96: 0 | CM96: 0 | CN96: 0 | CO96: 1 | CP96: 0
A97: 96 | B97: 97 | C97: 主分析 | D97: 1 | E97: 1 | F97: 641 | G97: 18–22岁 | H97: 女 | I97: 本科 | J97: 几乎每天 | K97: 6–11次 | L97: 1 | M97: 没有 | N97: 可确认尝试 | O97: 0 | P97: Q18最主要原因多选 | Q97: 0 | R97: 0 | S97: 0 | T97: 1 | U97: 0 | V97: 与他人交换周边 | W97: 完成1–2次 | X97: 交换尝试记录 | Y97: 1 | Z97: 1 | AA97: 0 | AB97: 0 | AC97: 1 | AD97: 1 | AE97: 0 | AF97: 0 | AG97: 1 | AH97: 0 | AI97: 1 | AJ97: 0 | AK97: 1 | AL97: 0 | AM97: 1 | AN97: 1 | AO97: 0 | AP97: 0 | AQ97: 0 | AX97: 1 | AY97: 0 | AZ97: 0 | BA97: 0 | BB97: 0 | BC97: 1 | BD97: 1 | BE97: 0 | BF97: 0 | BG97: 1 | BH97: 0 | BI97: 0 | BJ97: 0 | BK97: 0 | BL97: 0 | BM97: 0 | BN97: 0 | BO97: 1 | BP97: 0 | BQ97: 0 | BR97: 0 | BS97: 1 | BT97: 1 | BU97: 1 | BV97: 0 | BW97: 1 | BX97: 1 | BY97: 0 | BZ97: 0 | CA97: 1 | CB97: 0 | CC97: 1 | CD97: 1 | CE97: 0 | CF97: 0 | CQ97: 4 | CR97: 比较可能 | CS97: 4 | CT97: 比较可能 | CU97: 5 | CV97: 非常可能 | CW97: 2 | CX97: 比较不可能
A98: 97 | B98: 98 | C98: 主分析 | D98: 1 | E98: 1 | F98: 169 | G98: 23–29岁 | H98: 男 | I98: 本科 | J98: 少于每周1天 | K98: 0次 | L98: 0 | M98: 没有 | N98: 明确均未尝试 | O98: 0 | P98: Q16无可能性填写 | Q98: 0 | R98: 0 | S98: 1 | T98: 0 | U98: 0 | V98: 均没有尝试过 | W98: (跳过) | X98: 明确均未尝试 | Y98: 0 | AG98: 0 | AQ98: 0 | AX98: 0 | BG98: 0 | BU98: 1 | BV98: 0 | BW98: 0 | BX98: 0 | BY98: 0 | BZ98: 0 | CA98: 1 | CB98: 0 | CC98: 0 | CD98: 0 | CE98: 0 | CF98: 1 | CG98: 0 | CH98: 0 | CI98: 0 | CJ98: 0 | CK98: 0 | CL98: 0 | CM98: 0 | CN98: 0 | CO98: 1 | CP98: 0
A99: 98 | B99: 99 | C99: 质量暂不纳入 | D99: 1 | E99: 0 | F99: 252 | G99: 30–39岁 | H99: 男 | I99: 本科 | J99: 每周1–2天 | K99: 0次 | L99: 0 | M99: 不确定 | N99: 无法判断 | O99: 0 | P99: Q15五填空整段跨记录重复，主分析暂不纳入；Q16无可能性填写；Q14行无法可靠匹配；concern互斥混选 | Q99: 1 | R99: 0 | S99: 1 | T99: 0 | U99: 1 | V99: 出售个人周边 | W99: 没有尝试过 | X99: 无法判断 | Y99: 0 | AG99: 0 | AQ99: 0 | AX99: 0 | BG99: 0 | BU99: 0 | CF99: 1 | CG99: 0 | CH99: 0 | CI99: 0 | CJ99: 0 | CK99: 0 | CL99: 0 | CM99: 0 | CN99: 0 | CO99: 1 | CP99: 0
A100: 99 | B100: 100 | C100: 质量暂不纳入 | D100: 1 | E100: 0 | F100: 288 | G100: 18–22岁 | H100: 女 | I100: 本科 | J100: 几乎每天 | K100: 3–5次 | L100: 1 | M100: 有 | N100: 无法判断 | O100: 0 | P100: Q15五填空整段跨记录重复，主分析暂不纳入；Q16无可能性填写；Q14行无法可靠匹配 | Q100: 1 | R100: 0 | S100: 1 | T100: 0 | U100: 1 | V100: 与他人交换周边 | W100: 没有尝试过 | X100: 无法判断 | Y100: 1 | Z100: 0 | AA100: 0 | AB100: 0 | AC100: 1 | AD100: 1 | AE100: 1 | AF100: 0 | AG100: 1 | AH100: 0 | AI100: 1 | AJ100: 0 | AK100: 1 | AL100: 0 | AM100: 0 | AN100: 0 | AO100: 0 | AP100: 0 | AQ100: 1 | AR100: 0 | AS100: 0 | AT100: 0 | AU100: 0 | AV100: 1 | AW100: 0 | AX100: 0 | BG100: 0 | BU100: 1 | BV100: 0 | BW100: 0 | BX100: 0 | BY100: 0 | BZ100: 0 | CA100: 0 | CB100: 1 | CC100: 0 | CD100: 0 | CE100: 0 | CF100: 1 | CG100: 0 | CH100: 1 | CI100: 0 | CJ100: 0 | CK100: 0 | CL100: 0 | CM100: 0 | CN100: 0 | CO100: 0 | CP100: 0
...
